Workbook
Name Summary: #REF!

Sheet Summary
B1: Rocktail Hospitality Services (This is it Cafe)
B2: Swiggy Summary - July 2025
B4: Details | C4: 1st to 5th | D4: 6th to 12th | E4: 13th to 19th | F4: 20th to 26th | G4: 27th to 31st | H4: Total
B6: No.of orders | C6: 1209 | D6: 1455 | E6: 1477 | F6: 1242 | G6: 482 | H6: =SUM(C6:G6)
B8: Total Income (Number that you see on Swiggy dashboard) | C8: =Cashflow!C10 | D8: =Cashflow!D10 | E8: =Cashflow!E10 | F8: =Cashflow!F10 | G8: =Cashflow!G10 | H8: =SUM(C8:G8)
B10: Avg. order value | C10: =IFERROR(C8/C60,) | D10: =IFERROR(D8/D6,0) | E10: =IFERROR(E8/E6,0) | F10: =IFERROR(F8/F6,0) | G10: =IFERROR(G8/G6,0) | H10: =IFERROR(H8/H6,0)
B12: No of Disputed Orders | C12: 0 | D12: 0 | E12: 0 | F12: 0 | G12: 0 | H12: =SUM(C12:G12)
B14: Refund amount for disputed orders | C14: =Cashflow!C13 | D14: =Cashflow!D13 | E14: =Cashflow!E13 | F14: =Cashflow!F13 | G14: =Cashflow!G13 | H14: =SUM(C14:G14)
B15: Discounts | C15: =Cashflow!C8 | D15: =Cashflow!D8 | E15: =Cashflow!E8 | F15: =Cashflow!F8 | G15: =Cashflow!G8 | H15: =SUM(C15:G15)
C16: =IFERROR(C15/C8,0) | D16: =IFERROR(D15/D8,0) | E16: =IFERROR(E15/E8,0) | F16: =IFERROR(F15/F8,0) | G16: =IFERROR(G15/G8,0) | H16: =IFERROR(H15/H8,0)
B17: Commission | C17: =Cashflow!C11 | D17: =Cashflow!D11 | E17: =Cashflow!E11 | F17: =Cashflow!F11 | G17: =Cashflow!G11 | H17: =SUM(C17:G17)
B18: (Calculated on Sales + GST) | C18: =IFERROR(C17/C8,0) | D18: =IFERROR(D17/D8,0) | E18: =IFERROR(E17/E8,0) | F18: =IFERROR(F17/F8,0) | G18: =IFERROR(G17/G8,0) | H18: =IFERROR(H17/H8,0)
B19: Marketing & Ads | C19: =Cashflow!C16 | D19: =Cashflow!D16 | E19: =Cashflow!E16 | F19: =Cashflow!F16 | G19: =Cashflow!G16 | H19: =SUM(C19:G19)
C20: =IFERROR(C19/C8,0) | D20: =IFERROR(D19/D8,0) | E20: =IFERROR(E19/E8,0) | F20: =IFERROR(F19/F8,0) | G20: =IFERROR(G19/G8,0) | H20: =IFERROR(H19/H8,0)
B21: Other charges & Tax Adjustments | C21: =Cashflow!C20+Cashflow!C25 | D21: =Cashflow!D20+Cashflow!D25 | E21: =Cashflow!E20+Cashflow!E25 | F21: =Cashflow!F20+Cashflow!F25 | G21: =Cashflow!G20+Cashflow!G25 | H21: =SUM(C21:G21)
C22: =IFERROR(C21/C8,0) | D22: =IFERROR(D21/D8,0) | E22: =IFERROR(E21/E8,0) | F22: =IFERROR(F21/F8,0) | G22: =IFERROR(G21/G8,0) | H22: =IFERROR(H21/H8,0)
B24: Money received | C24: =C8-C14-C17-C19-C21 | D24: =D8-D14-D17-D19-D21 | E24: =E8-E14-E17-E19-E21 | F24: =F8-F14-F17-F19-F21 | G24: =G8-G14-G17-G19-G21 | H24: =H8-H14-H17-H19-H21
C25: =IFERROR(C24/$C$8,0) | D25: =IFERROR(D24/$D$8,0) | E25: =IFERROR(E24/$E$8,0) | F25: =IFERROR(F24/$F$8,0) | G25: =IFERROR(G24/$G$8,0) | H25: =IFERROR(H24/$G$8,0)

Sheet Cashflow
A1: =Summary!B1 | K1: =H10+H8-H28 | M1: =H12*100/118
A2: Swiggy Cash Flow Statement - July 2025 | M2: =M1*0.02%
A4: S.No | B4: Details | C4: =Summary!C4 | D4: =Summary!D4 | E4: =Summary!E4 | F4: =Summary!F4 | G4: 27th to 31st | H4: Total
A5: 1 | B5: Item sales (Delivered orders) | C5: ='D1W1'!I2 | D5: ='D1W2'!I2 | E5: ='D1W3'!I2 | F5: ='D1W4'!I2 | G5: ='D1W5'!I2 | H5: =SUM(C5:G5)
B6: Add:- Packing charges | C6: ='D1W1'!J2 | D6: ='D1W2'!J2 | E6: ='D1W3'!J2 | F6: ='D1W4'!J2 | G6: ='D1W5'!J2 | H6: =SUM(C6:G6) | J6: GST | K6: =H10-H28
B7: Add:- Compensation paid for cancelled orders | C7: ='D1W1'!P1-'D1W1'!AG1 | D7: ='D1W2'!P1-'D1W2'!AG1 | E7: ='D1W3'!P1-'D1W3'!AG1 | F7: ='D1W4'!P1-'D1W4'!AG1 | G7: ='D1W5'!P1-'D1W5'!AG1 | H7: =SUM(C7:G7) | J7: TDS | K7: =H12*100/118
B8: Less:- Discount | C8: ='D1W1'!K2+'D1W1'!L2 | D8: ='D1W2'!K2+'D1W2'!L2 | E8: ='D1W3'!K2+'D1W3'!L2 | F8: ='D1W4'!K2+'D1W4'!L2 | G8: ='D1W5'!K2+'D1W5'!L2 | H8: =SUM(C8:G8)
B9: Add:- GST 5% | C9: ='D1W1'!O2 | D9: ='D1W2'!O2 | E9: ='D1W3'!O2 | F9: ='D1W4'!O2 | G9: ='D1W5'!O2 | H9: =SUM(C9:G9) | N9: =AVERAGE(J12:L12)
B10: Net Sales | C10: =C5+C6+C7-C8+C9 | D10: =D5+D6+D7-D8+D9 | E10: =E5+E6+E7-E8+E9 | F10: =F5+F6+F7-F8+F9 | G10: =G5+G6+G7-G8+G9 | H10: =SUM(C10:G10) | J10: =H10-H28
A11: 2 | B11: Less:- Commission | C11: =SUM(C12) | D11: =SUM(D12) | E11: =SUM(E12) | F11: =SUM(F12) | G11: =SUM(G12) | H11: =SUM(C11:G11)
B12: Platform Fee | C12: ='D1W1'!S3 | D12: ='D1W2'!S3 | E12: ='D1W3'!S3 | F12: ='D1W4'!S3 | G12: ='D1W5'!S3 | H12: =SUM(C12:G12) | J12: =C12/C10 | K12: =D12/D10 | L12: =E12/E10 | M12: =F12/F10 | N12: =AVERAGE(J12:M12)
A13: 3 | B13: Less:- Refunds | C13: =SUM(C14:C15) | D13: =SUM(D14:D15) | E13: =(E14+E15) | F13: =(F14+F15) | G13: =(G14+G15) | H13: =SUM(C13:G13)
B14: Paid by Restaurant | H14: =SUM(C14:G14)
B15: Received by Restaurant | C15: 0 | D15: 0 | E15: 0 | F15: 0 | G15: 0 | H15: =SUM(C15:G15) | J15: =C10+C8-C28 | K15: =D10+D8-D28 | L15: =E10+E8-E28 | M15: =F10+F8-F28 | N15: =G10+G8-G28
A16: 4 | B16: Less:- Marketing Charges | C16: =SUM(C17:C19) | D16: =SUM(D17:D19) | E16: =E17+E18+E19 | F16: =F17+F18+F19 | G16: =G17+G18+G19 | H16: =SUM(C16:G16) | J16: =C12*100/118 | K16: =D12*100/118 | L16: =E12*100/118 | M16: =F12*100/118 | N16: =G12*100/118
B17: High Priority | C17: =-'D2W1'!B13 | D17: =-'D2W2'!B14 | E17: =-'D2W3'!B14 | F17: =-'D2W4'!B9 | G17: =-'D2W5'!B8 | H17: =SUM(C17:G17) | J17: =J16*2% | K17: =K16*2% | L17: =L16*2% | M17: =M16*2% | N17: =N16*2%
B18: Call Center Service Fees | C18: ='D1W1'!Z3 | D18: ='D1W2'!Z3 | E18: ='D1W3'!Z3 | F18: ='D1W4'!Z3 | G18: ='D1W5'!Z3 | H18: =SUM(C18:G18)
B19: PocketHero Fee | C19: ='D1W1'!V3 | D19: ='D1W2'!V3 | E19: ='D1W3'!V3 | F19: ='D1W4'!V3 | G19: ='D1W5'!V3 | H19: =SUM(C19:G19)
A20: 5 | B20: Less:- Other Charges | C20: =SUM(C21:C23) | D20: =SUM(D21:D23) | E20: =E21+E22+E23 | F20: =F21+F22+F23 | G20: =G21+G22+G23 | H20: =SUM(C20:G20)
B21: Collection Charges | C21: ='D1W1'!X3 | D21: ='D1W2'!X3 | E21: ='D1W3'!X3 | F21: ='D1W4'!X3 | G21: ='D1W5'!X3 | H21: =SUM(C21:G21)
B22: Long Distance Fee | C22: ='D1W1'!T3 | D22: ='D1W2'!T3 | E22: ='D1W3'!T3 | F22: ='D1W4'!T3 | G22: ='D1W5'!T3 | H22: =SUM(C22:G22)
B23: Merchant Cancellation Charges | C23: ='D1W1'!Y3 | D23: ='D1W2'!Y3 | E23: ='D1W3'!Y3 | F23: ='D1W4'!Y3 | G23: ='D1W5'!Y3 | H23: =SUM(C23:G23)
B24: Profit from Swiggy | C24: =C5+C6+C7-C8+C9-C12-C13-C16-C20-C28 | D24: =D5+D6+D7-D8+D9-D12-D13-D16-D20-D28 | E24: =E5+E6+E7-E8+E9-E12-E13-E16-E20-E28 | F24: =F5+F6+F7-F8+F9-F12-F13-F16-F20-F28 | G24: =G5+G6+G7-G8+G9-G12-G13-G16-G20-G28 | H24: =SUM(C24:G24) | N24: 259885
A25: 6 | B25: Less:- Tax Adjustments | C25: =SUM(C26:C28) | D25: =SUM(D26:D28) | E25: =SUM(E26:E28) | F25: =SUM(F26:F28) | G25: =SUM(G26:G28) | H25: =SUM(C25:G25) | N25: 9643
B26: TDS deduction for aggrigators | C26: ='D1W1'!AJ4 | D26: ='D1W2'!AJ4 | E26: ='D1W3'!AJ4 | F26: ='D1W4'!AJ4 | G26: ='D1W5'!AJ4 | H26: =SUM(C26:G26)
B27: TCS | C27: ='D1W1'!AI4 | D27: ='D1W2'!AI4 | E27: ='D1W3'!AI4 | F27: ='D1W4'!AI4 | G27: ='D1W5'!AI4 | H27: =SUM(C27:G27) | N27: -23947.45
B28: GST collected and paid by swiggy | C28: ='D1W1'!AH4 | D28: ='D1W2'!AH4 | E28: ='D1W3'!AH4 | F28: ='D1W4'!AH4 | G28: ='D1W5'!AH4 | H28: =SUM(C28:G28) | N28: 12289.68
A29: 7 | B29: Expected Receipts | C29: =C24-C26 | D29: =D24-D26 | E29: =E24-E26 | F29: =F24-F26 | G29: =G24-G26 | H29: =SUM(C29:G29)
B30: Intriem payments | C30: 0 | D30: 0 | E30: 0 | F30: 0 | G30: 0 | H30: 0
B31: EMI Loan deductions | C31: 0 | D31: 0 | E31: 0 | F31: 0 | G31: 0 | H31: =SUM(C31:G31)
B32: Actual receipts | G32: =BANK!G2 | H32: =SUM(C32:G32)
A33: 8 | B33: Difference | C33: =C29-C30-C31-C32 | D33: =D29-D30-D31-D32 | E33: =E29-E30-E31-E32 | F33: =F29-F30-F31-F32 | G33: =G29-G30-G31-G32 | H33: =SUM(C33:G33)
B35: Notes:-
B36: 1. Last week bank credits will be credited in the next month.

Sheet BANK
C1: 1 | D1: 2 | E1: 3 | F1: 4 | G1: 5
B2: swiggy | C2: 21505.95 | D2: 30781.79 | E2: 30342.24 | F2: 38669.62
A10: Date | B10: Narration | C10: Chq./Ref.No. | D10: Value Dt | E10: Withdrawal Amt. | F10: Deposit Amt. | G10: Closing Balance
A11: 01/07/25 | B11: NEFT CR-YESB0000001-ONE 97 COMMUNICATIONS LIMITED SETTL-ROCKTAIL HOSPITALITY SERVICES-YESBN12025070104207251 | C11: YESBN12025070104207251 | D11: 01/07/25 | F11: 27641 | G11: 575581.24
A12: 01/07/25 | B12: NEFT CR-RATN0000999-PINELABS PVT LTD-ROCKTAIL HOSPITALITY SERVICES-RATNN52025070127611676 | C12: RATNN52025070127611676 | D12: 01/07/25 | F12: 1509.75 | G12: 577090.99
A13: 01/07/25 | B13: 42552392TERMINAL 1 CARDS SETTL. 01/07/25 | C13: 000000000000000 | D13: 01/07/25 | F13: 2521.73 | G13: 579612.72
A14: 01/07/25 | B14: GST/BANK REFERENCE NO: R2518264868104/CIN NO: HDFC25073600001570 | C14: 0250701360001319 | D14: 01/07/25 | E14: 108078 | G14: 471534.72
A15: 01/07/25 | B15: NEFT CR-YESB0000001-SWIGGY LIMITED-ROCKTAIL HOSPITALITY SERVICES-YESBN12025070105744412 | C15: YESBN12025070105744412 | D15: 01/07/25 | F15: 70187.2 | G15: 541721.92
A16: 02/07/25 | B16: NEFT CR-YESB0000001-ONE 97 COMMUNICATIONS LIMITED SETTL-ROCKTAIL HOSPITALITY SERVICES-YESBN12025070202489683 | C16: YESBN12025070202489683 | D16: 02/07/25 | F16: 32140.42 | G16: 573862.34
A17: 02/07/25 | B17: 42552392TERMINAL 1 CARDS SETTL. 02/07/25 | C17: 000000000000000 | D17: 02/07/25 | F17: 2252.65 | G17: 576114.99
A18: 02/07/25 | B18: 42552394TERMINAL 1 CARDS SETTL. 02/07/25 | C18: 000000000000000 | D18: 02/07/25 | F18: 556.76 | G18: 576671.75
A19: 02/07/25 | B19: NEFT CR-CITI0000002-ETERNAL LIMITED-ROCKTAIL HOSPITALITY SERVICES-CITIN52025070288932874 | C19: CITIN52025070288932874 | D19: 02/07/25 | F19: 47888.79 | G19: 624560.54
A20: 02/07/25 | B20: UPI-AGROMECH INDUSTRIES-BAJAJPAY.6879729.02771144@INDUS-INDB0MERCHA-107417334493-DOSA EQUIPMENT ADV | C20: 0000107417334493 | D20: 02/07/25 | E20: 30000 | G20: 594560.54
A21: 03/07/25 | B21: NEFT CR-YESB0000001-ONE 97 COMMUNICATIONS LIMITED SETTL-ROCKTAIL HOSPITALITY SERVICES-YESBN12025070301800334 | C21: YESBN12025070301800334 | D21: 03/07/25 | F21: 20179.42 | G21: 614739.96
A22: 03/07/25 | B22: 42552392TERMINAL 1 CARDS SETTL. 03/07/25 | C22: 000000000000000 | D22: 03/07/25 | F22: 8653.95 | G22: 623393.91
A23: 04/07/25 | B23: NEFT CR-YESB0000001-ONE 97 COMMUNICATIONS LIMITED SETTL-ROCKTAIL HOSPITALITY SERVICES-YESBN12025070403786865 | C23: YESBN12025070403786865 | D23: 04/07/25 | F23: 31048.13 | G23: 654442.04
A24: 04/07/25 | B24: 42552394TERMINAL 1 CARDS SETTL. 04/07/25 | C24: 000000000000000 | D24: 04/07/25 | F24: 4251.24 | G24: 658693.28
A25: 04/07/25 | B25: NEFT CR-YESB0000001-SWIGGY LIMITED-ROCKTAIL HOSPITALITY SERVICES-YESBN12025070405363208 | C25: YESBN12025070405363208 | D25: 04/07/25 | F25: 21022.24 | G25: 679715.52
A26: 04/07/25 | B26: NEFT CR-UTIB0000052-BUNDL TECHNOLOGIES PRIVATE LIMITED-ROCKTAIL HOSPITALITY SERVICES-UTIBN62025070410121377 | C26: UTIBN62025070410121377 | D26: 04/07/25 | F26: 46137.34 | G26: 725852.86
A27: 04/07/25 | B27: UPI-ZOMATO ONLINE ORDER-ZOMATOONLINEORD384743.RZP@RXAIRTEL-AIRP0000011-107550400754-ZOMATOONLINEORDER | C27: 0000107550400754 | D27: 04/07/25 | E27: 2589.1 | G27: 723263.76
A28: 04/07/25 | B28: UPI-ZOMATO ONLINE ORDER-ZOMATOONLINEORD384743.RZP@RXAIRTEL-AIRP0000011-107550521516-ZOMATOONLINEORDER | C28: 0000107550521516 | D28: 05/07/25 | E28: 2589.1 | G28: 720674.66
A29: 05/07/25 | B29: NEFT CR-YESB0000001-ONE 97 COMMUNICATIONS LIMITED SETTL-ROCKTAIL HOSPITALITY SERVICES-YESBN12025070503391886 | C29: YESBN12025070503391886 | D29: 05/07/25 | F29: 53539.04 | G29: 774213.7
A30: 05/07/25 | B30: 42552392TERMINAL 1 CARDS SETTL. 05/07/25 | C30: 000000000000000 | D30: 05/07/25 | F30: 3251.71 | G30: 777465.41
A31: 05/07/25 | B31: SETTLEMENT CHARGE-JUN25-CPY594 | C31: 000000000000000 | D31: 05/07/25 | E31: 30.68 | G31: 777434.73
A32: 05/07/25 | B32: SETTLEMENT CHARGE-JUN25-CPY597 | C32: 000000000000000 | D32: 05/07/25 | E32: 25.96 | G32: 777408.77
A33: 06/07/25 | B33: NEFT CR-YESB0000001-ONE 97 COMMUNICATIONS LIMITED SETTL-ROCKTAIL HOSPITALITY SERVICES-YESBN12025070603478046 | C33: YESBN12025070603478046 | D33: 06/07/25 | F33: 79401.62 | G33: 856810.39
A34: 06/07/25 | B34: EMI 162047443 CHQ S16204744311 0725162047443 | C34: 000000000000000 | D34: 06/07/25 | E34: 70666 | G34: 786144.39
A35: 06/07/25 | B35: 42552392TERMINAL 1 CARDS SETTL. 06/07/25 | C35: 000000000000000 | D35: 06/07/25 | F35: 7572.79 | G35: 793717.18
A36: 06/07/25 | B36: 42552394TERMINAL 1 CARDS SETTL. 06/07/25 | C36: 000000000000000 | D36: 06/07/25 | F36: 10604.11 | G36: 804321.29
A37: 06/07/25 | B37: UPI-WOLFFPACK VENTURES P-ABHISHEK.LADHA11-1@OKHDFCBANK-HDFC0000512-107618941469-LOAN EMI | C37: 0000107618941469 | D37: 06/07/25 | F37: 35333 | G37: 839654.29
A38: 06/07/25 | B38: UPI-HARISH RAGHAVENDRA-HARISH.RAGHAVENDRA26@OKHDFCBANK-ICIC0000069-245979904572-PIZZA STONE | C38: 0000245979904572 | D38: 06/07/25 | E38: 10000 | G38: 829654.29
A39: 06/07/25 | B39: UPI-RAZORPAY-PG.RAZORPAY@AXISBANK-UTIB0001506-321362241875-ZOMATOOREFUNDQP553 | C39: 0000321362241875 | D39: 06/07/25 | F39: 2589.1 | G39: 832243.39
A40: 07/07/25 | B40: NEFT CR-YESB0000001-ONE 97 COMMUNICATIONS LIMITED SETTL-ROCKTAIL HOSPITALITY SERVICES-YESBN12025070703506891 | C40: YESBN12025070703506891 | D40: 07/07/25 | F40: 68500.38 | G40: 900743.77
A41: 07/07/25 | B41: 42552392TERMINAL 1 CARDS SETTL. 07/07/25 | C41: 000000000000000 | D41: 07/07/25 | F41: 6448.08 | G41: 907191.85
A42: 07/07/25 | B42: 42552394TERMINAL 1 CARDS SETTL. 07/07/25 | C42: 000000000000000 | D42: 07/07/25 | F42: 6613.36 | G42: 913805.21
A43: 07/07/25 | B43: NEFT CR-CITI0000002-ETERNAL LIMITED-ROCKTAIL HOSPITALITY SERVICES-CITIN52025070790533046 | C43: CITIN52025070790533046 | D43: 07/07/25 | F43: 54165.64 | G43: 967970.85
A44: 07/07/25 | B44: UPI-GADDAM NIRANJAN-G.NIRANJANNANI-1@OKAXIS-UTIB0000027-107702908442-UPI | C44: 0000107702908442 | D44: 07/07/25 | E44: 500 | G44: 967470.85
A45: 08/07/25 | B45: NEFT CR-YESB0000001-ONE 97 COMMUNICATIONS LIMITED SETTL-ROCKTAIL HOSPITALITY SERVICES-YESBN12025070802852556 | C45: YESBN12025070802852556 | D45: 08/07/25 | F45: 29438 | G45: 996908.85
A46: 08/07/25 | B46: NEFT CR-SCBL0036001-AMERICAN EXPRESS BANKING CORP-ROCKTAIL HOSPITALITY SERVICES-SCBLN52025070800525663 | C46: SCBLN52025070800525663 | D46: 08/07/25 | F46: 968.25 | G46: 997877.1
A47: 08/07/25 | B47: 42552394TERMINAL 1 CARDS SETTL. 08/07/25 | C47: 000000000000000 | D47: 08/07/25 | F47: 5211.01 | G47: 1003088.1
A48: 08/07/25 | B48: NEFT CR-UTIB0005040-TAITAI CREAMERY (OPC) PRIVATE LIMITED-ROCKTAIL HOSPITALITY SERVICES-UTIBN62025070852598625 | C48: UTIBN62025070852598625 | D48: 08/07/25 | F48: 75600 | G48: 1078688.1
A49: 08/07/25 | B49: NEFT CR-YESB0000001-SWIGGY LIMITED-ROCKTAIL HOSPITALITY SERVICES-YESBN12025070805486343 | C49: YESBN12025070805486343 | D49: 08/07/25 | F49: 68352.06 | G49: 1147040.2
A50: 09/07/25 | B50: NEFT CR-YESB0000001-ONE 97 COMMUNICATIONS LIMITED SETTL-ROCKTAIL HOSPITALITY SERVICES-YESBN12025070901099685 | C50: YESBN12025070901099685 | D50: 09/07/25 | F50: 18537.32 | G50: 1165577.5
A51: 09/07/25 | B51: 42552394TERMINAL 1 CARDS SETTL. 09/07/25 | C51: 000000000000000 | D51: 09/07/25 | F51: 3122.15 | G51: 1168699.6
A52: 09/07/25 | B52: NEFT CR-UTIB0005040-TAITAI CREAMERY (OPC) PRIVATE LIMITED-ROCKTAIL HOSPITALITY SERVICES-UTIBN62025070964796785 | C52: UTIBN62025070964796785 | D52: 09/07/25 | F52: 29888 | G52: 1198587.6
A53: 09/07/25 | B53: NEFT CR-CITI0000002-ETERNAL LIMITED-ROCKTAIL HOSPITALITY SERVICES-CITIN52025070991841082 | C53: CITIN52025070991841082 | D53: 09/07/25 | F53: 50557.96 | G53: 1249145.6
A54: 09/07/25 | B54: UPI-BAGGAS HOME GALLERY-Q785954181@YBL-YESB0YBLUPI-107805281519-GLASSWARE | C54: 0000107805281519 | D54: 09/07/25 | E54: 14875 | G54: 1234270.6
A55: 09/07/25 | B55: NEFT CR-UTIB0000052-BUNDL TECHNOLOGIES PRIVATE LIMITED-ROCKTAIL HOSPITALITY SERVICES-UTIBN62025070965449789 | C55: UTIBN62025070965449789 | D55: 09/07/25 | F55: 21505.95 | G55: 1255776.6
A56: 09/07/25 | B56: UPI-VORUGANTI BHAVANI KA-BHAVANI.KARTHIK1@AXL-CNRB0000033-085621978100-MICS PURCHASE | C56: 0000085621978100 | D56: 09/07/25 | E56: 2000 | G56: 1253776.6
A57: 10/07/25 | B57: NEFT CR-YESB0000001-ONE 97 COMMUNICATIONS LIMITED SETTL-ROCKTAIL HOSPITALITY SERVICES-YESBN12025071001592673 | C57: YESBN12025071001592673 | D57: 10/07/25 | F57: 26457 | G57: 1280233.6
A58: 10/07/25 | B58: 42552394TERMINAL 1 CARDS SETTL. 10/07/25 | C58: 000000000000000 | D58: 10/07/25 | F58: 4769.65 | G58: 1285003.2
A59: 11/07/25 | B59: NEFT CR-YESB0000001-ONE 97 COMMUNICATIONS LIMITED SETTL-ROCKTAIL HOSPITALITY SERVICES-YESBN12025071101008823 | C59: YESBN12025071101008823 | D59: 11/07/25 | F59: 19914.83 | G59: 1304918
A60: 11/07/25 | B60: NEFT CR-SCBL0036001-AMERICAN EXPRESS BANKING CORP-ROCKTAIL HOSPITALITY SERVICES-SCBLN52025071100526164 | C60: SCBLN52025071100526164 | D60: 11/07/25 | F60: 2583.74 | G60: 1307501.8
A61: 11/07/25 | B61: 42552394TERMINAL 1 CARDS SETTL. 11/07/25 | C61: 000000000000000 | D61: 11/07/25 | F61: 10367.44 | G61: 1317869.2
A62: 11/07/25 | B62: NEFT CR-YESB0000001-SWIGGY LIMITED-ROCKTAIL HOSPITALITY SERVICES-YESBN12025071105078795 | C62: YESBN12025071105078795 | D62: 11/07/25 | F62: 35659.91 | G62: 1353529.1
A63: 11/07/25 | B63: SALARIES/ROCKTAIL DR - 57500000326520 - NEFT TRANSITORY ACCOUNT | C63: 0000000000000175 | D63: 11/07/25 | E63: 476368 | G63: 877161.12
A64: 11/07/25 | B64: FT - DR - 50100591782456 - LAXMIDHAR PRADHAN | C64: 0000000000000174 | D64: 11/07/25 | E64: 11133 | G64: 866028.12
A65: 11/07/25 | B65: CHQ:000174 AMT:106767 FT:5 DR - 50100591782700 - PAPPU BISHWAKARMA | C65: 000000000000000 | D65: 11/07/25 | E65: 10300 | G65: 855728.12
A66: 11/07/25 | B66: CHQ:000174 AMT:106767 FT:5 DR - 50100591783676 - URADI RAJ KUMAR | C66: 000000000000000 | D66: 11/07/25 | E66: 27800 | G66: 827928.12
A67: 11/07/25 | B67: CHQ:000174 AMT:106767 FT:5 DR - 50100301239701 - SUJOY GHOSH | C67: 000000000000000 | D67: 11/07/25 | E67: 35967 | G67: 791961.12
A68: 11/07/25 | B68: CHQ:000174 AMT:106767 FT:5 DR - 50100591782700 - PAPPU BISHWAKARMA | C68: 000000000000000 | D68: 11/07/25 | E68: 21567 | G68: 770394.12
A69: 11/07/25 | B69: NEFT RETURN-INCORRECT ACCOUNT NUMBER-VEMULLA MANI-INDBN52025071102237880 | C69: HDFCN52025071150688848 | D69: 11/07/25 | F69: 15800 | G69: 786194.12
A70: 11/07/25 | B70: UPI-RAFTAAR CRICKET ACAD-RAFTAARCRICKETCLUB@OKSBI-KKBK0007534-107937373983-UPI | C70: 0000107937373983 | D70: 11/07/25 | E70: 700 | G70: 785494.12
A71: 12/07/25 | B71: NEFT CR-YESB0000001-ONE 97 COMMUNICATIONS LIMITED SETTL-ROCKTAIL HOSPITALITY SERVICES-YESBN12025071203019008 | C71: YESBN12025071203019008 | D71: 12/07/25 | F71: 31738.86 | G71: 817232.98
A72: 12/07/25 | B72: IMPS-519310127803-NAGILLA HARIKRISHNA-BARB-XXXXXXXXXX0258-S | C72: 0000519310127803 | D72: 12/07/25 | E72: 200000 | G72: 617232.98
A73: 12/07/25 | B73: IMPS-519310126986-NAGILLA HARIKRISHNA-BARB-XXXXXXXXXX2369-S | C73: 0000519310126986 | D73: 12/07/25 | E73: 200000 | G73: 417232.98
A74: 12/07/25 | B74: 42552394TERMINAL 1 CARDS SETTL. 12/07/25 | C74: 000000000000000 | D74: 12/07/25 | F74: 11847.67 | G74: 429080.65
A75: 12/07/25 | B75: UPI-V MANI-8074123111@YBL-INDB0000226-107977671318-SALARY | C75: 0000107977671318 | D75: 12/07/25 | E75: 10000 | G75: 419080.65
A76: 13/07/25 | B76: NEFT CR-YESB0000001-ONE 97 COMMUNICATIONS LIMITED SETTL-ROCKTAIL HOSPITALITY SERVICES-YESBN12025071301973666 | C76: YESBN12025071301973666 | D76: 13/07/25 | F76: 73497.99 | G76: 492578.64
A77: 13/07/25 | B77: 42552392TERMINAL 1 CARDS SETTL. 13/07/25 | C77: 000000000000000 | D77: 13/07/25 | F77: 4814.84 | G77: 497393.48
A78: 13/07/25 | B78: 42552394TERMINAL 1 CARDS SETTL. 13/07/25 | C78: 000000000000000 | D78: 13/07/25 | F78: 21958.33 | G78: 519351.81
A79: 13/07/25 | B79: UPI-KANTAM VIJAYA PRIYA-PRIYAKANTAM30@OKSBI-SBIN0020879-519400992233-UPI | C79: 0000519400992233 | D79: 13/07/25 | F79: 65000 | G79: 584351.81
A80: 13/07/25 | B80: UPI-V MANI-8074123111@YBL-INDB0000226-108054317088-WATCHMAN SALARY | C80: 0000108054317088 | D80: 13/07/25 | E80: 15800 | G80: 568551.81
A81: 14/07/25 | B81: NEFT CR-YESB0000001-ONE 97 COMMUNICATIONS LIMITED SETTL-ROCKTAIL HOSPITALITY SERVICES-YESBN12025071402193670 | C81: YESBN12025071402193670 | D81: 14/07/25 | F81: 67040.1 | G81: 635591.91
A82: 14/07/25 | B82: IMPS-519510125018-HOUSE PARTY-HDFC-XXXXXXXXXX7641-ELECTRICTY BILL | C82: 0000519510125018 | D82: 14/07/25 | E82: 135603 | G82: 499988.91
A83: 14/07/25 | B83: 42552394TERMINAL 1 CARDS SETTL. 14/07/25 | C83: 000000000000000 | D83: 14/07/25 | F83: 13690.5 | G83: 513679.41
A84: 14/07/25 | B84: NEFT CR-CITI0000002-ETERNAL LIMITED-ROCKTAIL HOSPITALITY SERVICES-CITIN52025071493446674 | C84: CITIN52025071493446674 | D84: 14/07/25 | F84: 46422.19 | G84: 560101.6
A85: 14/07/25 | B85: UPI-SYED ANSAR ALI-9732961005@AXL-CNRB0000033-108091960389-VALET | C85: 0000108091960389 | D85: 14/07/25 | E85: 44000 | G85: 516101.6
A86: 14/07/25 | B86: UPI-GADDAM NIRANJAN-G.NIRANJANNANI-1@OKAXIS-UTIB0000027-108107881163-UPI | C86: 0000108107881163 | D86: 14/07/25 | E86: 500 | G86: 515601.6
A87: 15/07/25 | B87: NEFT CR-YESB0000001-ONE 97 COMMUNICATIONS LIMITED SETTL-ROCKTAIL HOSPITALITY SERVICES-YESBN12025071501000588 | C87: YESBN12025071501000588 | D87: 15/07/25 | F87: 34889.95 | G87: 550491.55
A88: 15/07/25 | B88: 42552394TERMINAL 1 CARDS SETTL. 15/07/25 | C88: 000000000000000 | D88: 15/07/25 | F88: 4573.95 | G88: 555065.5
A89: 15/07/25 | B89: NEFT CR-YESB0000001-SWIGGY LIMITED-ROCKTAIL HOSPITALITY SERVICES-YESBN12025071505559496 | C89: YESBN12025071505559496 | D89: 15/07/25 | F89: 64805.48 | G89: 619870.98
A90: 16/07/25 | B90: NEFT CR-YESB0000001-ONE 97 COMMUNICATIONS LIMITED SETTL-ROCKTAIL HOSPITALITY SERVICES-YESBN12025071601638813 | C90: YESBN12025071601638813 | D90: 16/07/25 | F90: 23902.29 | G90: 643773.27
A91: 16/07/25 | B91: 42552394TERMINAL 1 CARDS SETTL. 16/07/25 | C91: 000000000000000 | D91: 16/07/25 | F91: 10817.34 | G91: 654590.61
A92: 16/07/25 | B92: ACH D- PINE LABS PVT LTD-OMWEQ8HJVQBQHD | C92: 0000000980795150 | D92: 16/07/25 | E92: 1471 | G92: 653119.61
A93: 16/07/25 | B93: NEFT CR-CITI0000002-ETERNAL LIMITED-ROCKTAIL HOSPITALITY SERVICES-CITIN52025071694592127 | C93: CITIN52025071694592127 | D93: 16/07/25 | F93: 39040.07 | G93: 692159.68
A94: 16/07/25 | B94: NEFT CR-UTIB0000052-BUNDL TECHNOLOGIES PRIVATE LIMITED-ROCKTAIL HOSPITALITY SERVICES-UTIBN62025071642110281 | C94: UTIBN62025071642110281 | D94: 16/07/25 | F94: 30781.79 | G94: 722941.47
A95: 17/07/25 | B95: NEFT CR-YESB0000001-ONE 97 COMMUNICATIONS LIMITED SETTL-ROCKTAIL HOSPITALITY SERVICES-YESBN12025071703119976 | C95: YESBN12025071703119976 | D95: 17/07/25 | F95: 26324.74 | G95: 749266.21
A96: 17/07/25 | B96: NEFT CR-SCBL0036001-AMERICAN EXPRESS BANKING CORP-ROCKTAIL HOSPITALITY SERVICES-SCBLN52025071700529428 | C96: SCBLN52025071700529428 | D96: 17/07/25 | F96: 1690.26 | G96: 750956.47
A97: 17/07/25 | B97: 42552392TERMINAL 1 CARDS SETTL. 17/07/25 | C97: 000000000000000 | D97: 17/07/25 | F97: 2538.27 | G97: 753494.74
A98: 17/07/25 | B98: 42552394TERMINAL 1 CARDS SETTL. 17/07/25 | C98: 000000000000000 | D98: 17/07/25 | F98: 2401.73 | G98: 755896.47
A99: 17/07/25 | B99: UPI-KOYA SATISH-SSPROPERTIES789@OKHDFCBANK-HDFC0003665-108242381435-STAFF RENT | C99: 0000108242381435 | D99: 17/07/25 | E99: 39441 | G99: 716455.47
A100: 17/07/25 | B100: UPI-THIRUPATHAMMA MUTHUM-9490371940@YBL-CNRB0000033-108242417958-UPI | C100: 0000108242417958 | D100: 17/07/25 | E100: 38727 | G100: 677728.47
A101: 17/07/25 | B101: UPI-ARUN KUMAR P-IECAPECEO@OKSBI-SBIN0002714-108242863498-STAFF ROOM | C101: 0000108242863498 | D101: 17/07/25 | E101: 12789 | G101: 664939.47
A102: 17/07/25 | B102: UPI-SUJOY GHOSH-GSUJOY009@OKHDFCBANK-HDFC0009383-108242902503-STAFF RENT | C102: 0000108242902503 | D102: 17/07/25 | E102: 8000 | G102: 656939.47
A103: 18/07/25 | B103: NEFT CR-YESB0000001-ONE 97 COMMUNICATIONS LIMITED SETTL-ROCKTAIL HOSPITALITY SERVICES-YESBN12025071801463578 | C103: YESBN12025071801463578 | D103: 18/07/25 | F103: 36337.85 | G103: 693277.32
A104: 18/07/25 | B104: 42552394TERMINAL 1 CARDS SETTL. 18/07/25 | C104: 000000000000000 | D104: 18/07/25 | F104: 5128.16 | G104: 698405.48
A105: 18/07/25 | B105: NEFT CR-YESB0000001-SWIGGY LIMITED-ROCKTAIL HOSPITALITY SERVICES-YESBN12025071805178846 | C105: YESBN12025071805178846 | D105: 18/07/25 | F105: 18986.17 | G105: 717391.65
A106: 18/07/25 | B106: FT - DR - 50200018534149 - RIVERSIDE COFFEE | C106: 0000000000000177 | D106: 18/07/25 | E106: 22575 | G106: 694816.65
A107: 18/07/25 | B107: VENDOR PAYMENTS-ROCKTAIL HOSPITALITY SER DR - 57500000326520 - NEFT TRANSITORY ACCOUNT | C107: 0000000000000176 | D107: 18/07/25 | E107: 403698 | G107: 291118.65
...

Sheet Profit statement
B1: =Summary!B1
B2: Swiggy Profit Statement - July 2025
B4: Details | C4: =Cashflow!C4 | D4: =Cashflow!D4 | E4: =Cashflow!E4 | F4: =Cashflow!F4 | G4: =Summary!G4 | H4: Total
B5: A. Net Sales
B6: Total Income | C6: =Cashflow!C5+Cashflow!C6-Cashflow!C8+Cashflow!C9-Cashflow!C28 | D6: =Cashflow!D5+Cashflow!D6-Cashflow!D8+Cashflow!D9-Cashflow!D28 | E6: =Cashflow!E5+Cashflow!E6-Cashflow!E8+Cashflow!E9-Cashflow!E28 | F6: =Cashflow!F5+Cashflow!F6-Cashflow!F8+Cashflow!F9-Cashflow!F28 | G6: =Cashflow!G5+Cashflow!G6-Cashflow!G8+Cashflow!G9-Cashflow!G28 | H6: =SUM(C6:G6)
B7: Add- Adjust: Cancelled orders (By Swiggy) | C7: =Cashflow!C7 | D7: 0 | E7: =Cashflow!E7 | F7: =Cashflow!F7 | G7: =Cashflow!G7 | H7: =SUM(C7:G7)
B8: Net Sales (Number that you see on Numerize app) | C8: =C6+C7 | D8: =D6+D7 | E8: =E6+E7 | F8: =F6+F7 | G8: =G6+G7 | H8: =H6+H7
B10: B. Less:- Commission | C10: =Cashflow!C11 | D10: =Cashflow!D11 | E10: =Cashflow!E11 | F10: =Cashflow!F11 | G10: =Cashflow!G11 | H10: =SUM(C10:G10)
B12: C. Less:- Marketing & Ads | C12: =Cashflow!C16 | D12: =Cashflow!D16 | E12: =Cashflow!E16 | F12: =Cashflow!F16 | G12: =Cashflow!G16 | H12: =SUM(C12:G12)
B14: D. Less:- Refund on disputed orders | C14: =Cashflow!C13 | D14: =Cashflow!D13 | E14: =Cashflow!E13 | F14: =Cashflow!F13 | G14: =Cashflow!G13 | H14: =SUM(C14:G14)
B16: E. Other charges | C16: =Cashflow!C20 | D16: =Cashflow!D20 | E16: =Cashflow!E20 | F16: =Cashflow!F20 | G16: =Cashflow!G20 | H16: =SUM(C16:G16)
B18: F. Profit | C18: =C8-C10-C12-C14-C16 | D18: =D8-D10-D12-D14-D16 | E18: =E8-E10-E12-E14-E16 | F18: =F8-F10-F12-F14-F16 | G18: =G8-G10-G12-G14-G16 | H18: =H8-H10-H12-H14-H16
B19: Percentage | C19: =C18/C8 | D19: =D18/D8 | E19: =IFERROR(E18/E8,0) | F19: =IFERROR(F18/F8,0) | G19: =IFERROR(G18/G8,0) | H19: =H18/H8

Sheet Discrepancies
B1: =Summary!B1
B2: Swiggy Discrepancies - July 2025
B4: Details | C4: =Summary!C4 | D4: =Summary!D4 | E4: =Summary!E4 | F4: =Summary!F4 | G4: =Summary!G4 | H4: Total
B5: A. POS discrepancies
B6: Sales as per Swiggy | C6: =Cashflow!C10 | D6: =Cashflow!D10 | E6: =Cashflow!E10 | F6: =Cashflow!F10 | G6: =Cashflow!G10 | H6: =SUM(C6:G6)
B7: Sale as per POS | H7: =SUM(C7:G7)
B8: Difference | C8: =C6-C7 | D8: =D6-D7 | E8: =E6-E7 | F8: =F6-F7 | G8: =G6-G7 | H8: =SUM(C8:G8)
C9: =IFERROR(C8/C6,0) | D9: =IFERROR(D8/D6,0) | E9: =IFERROR(E8/E6,0) | F9: =IFERROR(F8/F6,0) | G9: =IFERROR(G8/G6,0) | H9: =IFERROR(H8/H6,0)
B11: B. Order discrepancies
B12: No.of delivered orders for which payment isn't received | C12: 0 | D12: 0 | E12: 0 | F12: 0 | G12: 0 | H12: =SUM(C12:G12)
B13: Value of such orders | C13: 0 | D13: 0 | E13: 0 | F13: 0 | G13: 0 | H13: =SUM(C13:G13)
B16: C. Payment discrepancies
B17: Expected receipts in the bank account | C17: =Cashflow!C29 | D17: =Cashflow!D29 | E17: =Cashflow!E29 | F17: =Cashflow!F29 | G17: =Cashflow!G29 | H17: =SUM(C17:G17)
B18: Interim Payments | C18: 0 | D18: 0 | E18: 0 | F18: 0 | G18: 0 | H18: =SUM(C18:G18)
B19: Actual receipts in the bank | H19: =SUM(C19:G19)
B20: Difference | C20: =C17-C19-C18 | D20: =D17-D19-D18 | E20: =E17-E19-E18 | F20: =F17-F19-F18 | G20: =G17-G19-G18 | H20: =H17-H19-H18
B22: Notes:
B23: 1. Last week bank credits will be credited in the next month.
B24: 2. There is difference between POS and actual sales, 208.43/- is less in POS

Sheet POS
G1: Week 1 | H1: Week 2 | I1: Week 3 | J1: Week 4 | K1: Week 5
G2: 34088 | H2: 46933 | I2: 48536 | J2: 62572 | K2: 31390
N8: {=SUBTOTAL(9,N10:N2235)}
A9: Invoice No. | B9: Date | C9: Payment Type | D9: Order Type | E9: Status | F9: Persons | G9: Area | H9: Assign To | I9: Cash | J9: Card | K9: Due Payment | L9: Other | M9: Wallet | N9: Online
A10: 86857 | B10: 45870 | C10: Cash | D10: Dine In | E10: Success | G10: Dine in | H10: Pavan | I10: 372 | J10: 0 | K10: 0 | L10: 0 | M10: 0 | N10: 0
A11: 86856 | B11: 45870 | C11: Other [Swiggy Dineout] | D11: Dine In | E11: Success | G11: Dine in | H11: Pavan | I11: 0 | J11: 0 | K11: 0 | L11: 2105 | M11: 0 | N11: 0
A12: 86855 | B12: 45870 | C12: Cash | D12: Dine In | E12: Success | F12: 2 | G12: Dine in | H12: Prashant | I12: 1009 | J12: 0 | K12: 0 | L12: 0 | M12: 0 | N12: 0
A13: 86854 | B13: 45870 | C13: Other [upi] | D13: Dine In | E13: Success | F13: 3 | G13: Dine in | H13: Prashant | I13: 0 | J13: 0 | K13: 0 | L13: 1678 | M13: 0 | N13: 0
A14: 86853 | B14: 45870 | C14: Other [upi] | D14: Dine In | E14: Success | G14: Dine in | H14: Pavan | I14: 0 | J14: 0 | K14: 0 | L14: 2272 | M14: 0 | N14: 0
A15: 86852 | B15: 45870 | C15: CARD | D15: Dine In | E15: Success | G15: Dine in | H15: Prashant | I15: 0 | J15: 1010 | K15: 0 | L15: 0 | M15: 0 | N15: 0
A16: 86851 | B16: 45870 | C16: Other [Swiggy Dineout] | D16: Dine In | E16: Success | F16: 3 | G16: Dine in | H16: Prashant | I16: 0 | J16: 0 | K16: 0 | L16: 1844 | M16: 0 | N16: 0
A17: 86850 | B17: 45870 | C17: Other [upi] | D17: Dine In | E17: Success | G17: Dine in | H17: Pavan | I17: 0 | J17: 0 | K17: 0 | L17: 120 | M17: 0 | N17: 0
A18: 86849 | B18: 45870 | C18: Other [Zomato Gold] | D18: Dine In | E18: Success | F18: 3 | G18: Dine in | H18: Pavan | I18: 0 | J18: 0 | K18: 0 | L18: 2687 | M18: 0 | N18: 0
A19: 86848 | B19: 45870 | C19: Other [Swiggy Dineout] | D19: Dine In | E19: Success | F19: 2 | G19: Dine in | H19: Prashant | I19: 0 | J19: 0 | K19: 0 | L19: 1525 | M19: 0 | N19: 0
A20: 86847 | B20: 45870 | C20: Other [upi] | D20: Dine In | E20: Success | G20: Dine in | H20: Prashant | I20: 0 | J20: 0 | K20: 0 | L20: 460 | M20: 0 | N20: 0
A21: 86846 | B21: 45870 | C21: Other [Zomato Gold] | D21: Dine In | E21: Success | G21: Dine in | H21: Pavan | I21: 0 | J21: 0 | K21: 0 | L21: 987 | M21: 0 | N21: 0
A22: 86845 | B22: 45870 | C22: Other [upi] | D22: Dine In | E22: Success | G22: Dine in | H22: Pavan | I22: 0 | J22: 0 | K22: 0 | L22: 307 | M22: 0 | N22: 0
A23: 86844 | B23: 45870 | C23: Other [Swiggy Dineout] | D23: Dine In | E23: Success | G23: Dine in | I23: 0 | J23: 0 | K23: 0 | L23: 2830 | M23: 0 | N23: 0
A24: 86843 | B24: 45870 | C24: Other [Zomato Gold] | D24: Dine In | E24: Success | F24: 4 | G24: Dine in | H24: Prashant | I24: 0 | J24: 0 | K24: 0 | L24: 2840 | M24: 0 | N24: 0
A25: 86842 | B25: 45870 | C25: Other [Zomato Gold] | D25: Dine In | E25: Success | G25: Dine in | H25: Prashant | I25: 0 | J25: 0 | K25: 0 | L25: 1535 | M25: 0 | N25: 0
A26: 86841 | B26: 45870 | C26: Other [Zomato Gold] | D26: Dine In | E26: Success | F26: 3 | G26: Dine in | H26: Prashant | I26: 0 | J26: 0 | K26: 0 | L26: 2390 | M26: 0 | N26: 0
A27: 86840 | B27: 45870 | C27: CARD | D27: Dine In | E27: Success | G27: Dine in | H27: This is It | I27: 0 | J27: 1547 | K27: 0 | L27: 0 | M27: 0 | N27: 0
A28: 86839 | B28: 45870 | C28: Other [Zomato Gold] | D28: Dine In | E28: Success | G28: Dine in | H28: Pavan | I28: 0 | J28: 0 | K28: 0 | L28: 1062 | M28: 0 | N28: 0
A29: 86838 | B29: 45870 | C29: Online | D29: Delivery(Parcel) | E29: Success | G29: Zomato | I29: 0 | J29: 0 | K29: 0 | L29: 0 | M29: 0 | N29: 784
A30: 86837 | B30: 45870 | C30: Other [upi] | D30: Dine In | E30: Success | G30: Dine in | H30: Prashant | I30: 0 | J30: 0 | K30: 0 | L30: 920 | M30: 0 | N30: 0
A31: 86836 | B31: 45870 | C31: Other [upi] | D31: Dine In | E31: Success | F31: 3 | G31: Dine in | H31: Prashant | I31: 0 | J31: 0 | K31: 0 | L31: 1064 | M31: 0 | N31: 0
A32: 86835 | B32: 45870 | C32: Online | D32: Delivery(Parcel) | E32: Success | G32: Swiggy_This is it Cafe | I32: 0 | J32: 0 | K32: 0 | L32: 0 | M32: 0 | N32: 403
A33: 86834 | B33: 45870 | C33: Other [upi] | D33: Dine In | E33: Success | F33: 4 | G33: Dine in | H33: Prashant | I33: 0 | J33: 0 | K33: 0 | L33: 1591 | M33: 0 | N33: 0
A34: 86833 | B34: 45870 | C34: Online | D34: Delivery(Parcel) | E34: Success | G34: Zomato | I34: 0 | J34: 0 | K34: 0 | L34: 0 | M34: 0 | N34: 980
A35: 86832 | B35: 45870 | C35: Online | D35: Delivery(Parcel) | E35: Success | G35: Zomato | I35: 0 | J35: 0 | K35: 0 | L35: 0 | M35: 0 | N35: 188
A36: 86831 | B36: 45870 | C36: Other [Swiggy Dineout] | D36: Dine In | E36: Success | G36: Dine in | H36: Pavan | I36: 0 | J36: 0 | K36: 0 | L36: 1393 | M36: 0 | N36: 0
A37: 86830 | B37: 45870 | C37: Other [upi] | D37: Dine In | E37: Success | G37: Dine in | H37: Pavan | I37: 0 | J37: 0 | K37: 0 | L37: 438 | M37: 0 | N37: 0
A38: 86829 | B38: 45870 | C38: CARD | D38: Dine In | E38: Success | F38: 2 | G38: Dine in | H38: Prashant | I38: 0 | J38: 2460 | K38: 0 | L38: 0 | M38: 0 | N38: 0
A39: 86828 | B39: 45870 | C39: Cash | D39: Dine In | E39: Success | G39: Dine in | H39: Pavan | I39: 900 | J39: 0 | K39: 0 | L39: 0 | M39: 0 | N39: 0
A40: 86827 | B40: 45870 | C40: Online | D40: Delivery(Parcel) | E40: Success | G40: Zomato | I40: 0 | J40: 0 | K40: 0 | L40: 0 | M40: 0 | N40: 775
A41: 86826 | B41: 45870 | C41: Other [upi] | D41: Dine In | E41: Success | G41: Dine in | H41: Pavan | I41: 0 | J41: 0 | K41: 0 | L41: 274 | M41: 0 | N41: 0
A42: 86825 | B42: 45870 | C42: Other [Zomato Gold] | D42: Dine In | E42: Success | G42: Dine in | H42: Pavan | I42: 0 | J42: 0 | K42: 0 | L42: 1393 | M42: 0 | N42: 0
A43: 86824 | B43: 45870 | C43: Other [upi] | D43: Dine In | E43: Success | G43: Dine in | H43: This is It | I43: 0 | J43: 0 | K43: 0 | L43: 669 | M43: 0 | N43: 0
A44: 86823 | B44: 45870 | C44: Online | D44: Delivery(Parcel) | E44: Success | G44: Zomato | I44: 0 | J44: 0 | K44: 0 | L44: 0 | M44: 0 | N44: 701
A45: 86822 | B45: 45870 | C45: Other [upi] | D45: Dine In | E45: Success | G45: Dine in | H45: Pavan | I45: 0 | J45: 0 | K45: 0 | L45: 723 | M45: 0 | N45: 0
A46: 86821 | B46: 45870 | C46: Other [Swiggy Dineout] | D46: Dine In | E46: Success | G46: Dine in | H46: Pavan | I46: 0 | J46: 0 | K46: 0 | L46: 764 | M46: 0 | N46: 0
A47: 86820 | B47: 45870 | C47: CARD | D47: Dine In | E47: Success | G47: Dine in | H47: Pavan | I47: 0 | J47: 1500 | K47: 0 | L47: 0 | M47: 0 | N47: 0
A48: 86819 | B48: 45870 | C48: Other [upi] | D48: Dine In | E48: Success | G48: Dine in | H48: Pavan | I48: 0 | J48: 0 | K48: 0 | L48: 1598 | M48: 0 | N48: 0
A49: 86818 | B49: 45870 | C49: Cash | D49: Dine In | E49: Success | G49: Dine in | H49: Pavan | I49: 1348 | J49: 0 | K49: 0 | L49: 0 | M49: 0 | N49: 0
A50: 86817 | B50: 45870 | C50: Other [upi] | D50: Dine In | E50: Success | G50: Dine in | I50: 0 | J50: 0 | K50: 0 | L50: 153 | M50: 0 | N50: 0
A51: 86816 | B51: 45870 | C51: Online | D51: Delivery(Parcel) | E51: Success | G51: Swiggy_This is it Cafe | I51: 0 | J51: 0 | K51: 0 | L51: 0 | M51: 0 | N51: 324
A52: 86815 | B52: 45870 | C52: Online | D52: Delivery(Parcel) | E52: Success | G52: Zomato | I52: 0 | J52: 0 | K52: 0 | L52: 0 | M52: 0 | N52: 414
A53: 86814 | B53: 45870 | C53: Other [upi] | D53: Dine In | E53: Success | G53: Dine in | H53: Pavan | I53: 0 | J53: 0 | K53: 0 | L53: 285 | M53: 0 | N53: 0
A54: 86813 | B54: 45870 | C54: Other [Zomato Gold] | D54: Dine In | E54: Success | G54: Dine in | H54: Pavan | I54: 0 | J54: 0 | K54: 0 | L54: 8126 | M54: 0 | N54: 0
A55: 86812 | B55: 45870 | C55: CARD | D55: Dine In | E55: Success | G55: Dine in | H55: Pavan | I55: 0 | J55: 1262 | K55: 0 | L55: 0 | M55: 0 | N55: 0
A56: 86811 | B56: 45870 | C56: Cash | D56: Dine In | E56: Success | G56: Dine in | I56: 372 | J56: 0 | K56: 0 | L56: 0 | M56: 0 | N56: 0
A57: 86810 | B57: 45870 | C57: Other [upi] | D57: Dine In | E57: Success | G57: Dine in | H57: Pavan | I57: 0 | J57: 0 | K57: 0 | L57: 350 | M57: 0 | N57: 0
A58: 86809 | B58: 45870 | C58: Online | D58: Delivery(Parcel) | E58: Success | G58: Swiggy_This is it Cafe | I58: 0 | J58: 0 | K58: 0 | L58: 0 | M58: 0 | N58: 424
A59: 86808 | B59: 45870 | C59: Other [upi] | D59: Dine In | E59: Success | G59: Dine in | H59: Pavan | I59: 0 | J59: 0 | K59: 0 | L59: 274 | M59: 0 | N59: 0
A60: 86807 | B60: 45870 | C60: Online | D60: Delivery(Parcel) | E60: Success | G60: Swiggy_This is it Cafe | I60: 0 | J60: 0 | K60: 0 | L60: 0 | M60: 0 | N60: 230
A61: 86806 | B61: 45870 | C61: Online | D61: Delivery(Parcel) | E61: Success | G61: Swiggy_This is it Cafe | I61: 0 | J61: 0 | K61: 0 | L61: 0 | M61: 0 | N61: 686
A62: 86805 | B62: 45870 | C62: Online | D62: Delivery(Parcel) | E62: Success | G62: Zomato | I62: 0 | J62: 0 | K62: 0 | L62: 0 | M62: 0 | N62: 256
A63: 86804 | B63: 45870 | C63: Online | D63: Delivery(Parcel) | E63: Success | G63: Zomato | I63: 0 | J63: 0 | K63: 0 | L63: 0 | M63: 0 | N63: 372
A64: C2740 | B64: 45869 | C64: Cash | D64: Dine In | E64: Complimentary | I64: 482 | J64: 0 | K64: 0 | L64: 0 | M64: 0 | N64: 0
A65: C2739 | B65: 45869 | C65: Cash | D65: Dine In | E65: Complimentary | I65: 548 | J65: 0 | K65: 0 | L65: 0 | M65: 0 | N65: 0
A66: C2738 | B66: 45869 | C66: Cash | D66: Dine In | E66: Complimentary | I66: 636 | J66: 0 | K66: 0 | L66: 0 | M66: 0 | N66: 0
A67: C2737 | B67: 45869 | C67: Cash | D67: Dine In | E67: Complimentary | H67: Prince Vishwarkarma | I67: 4520 | J67: 0 | K67: 0 | L67: 0 | M67: 0 | N67: 0
A68: C2736 | B68: 45869 | C68: Cash | D68: Dine In | E68: Complimentary | G68: Dine in | H68: Prince Vishwarkarma | I68: 108 | J68: 0 | K68: 0 | L68: 0 | M68: 0 | N68: 0
A69: C2735 | B69: 45869 | C69: Other [upi] | D69: Dine In | E69: Complimentary | G69: Dine in | I69: 0 | J69: 0 | K69: 0 | L69: 9592 | M69: 0 | N69: 0
A70: 86803 | B70: 45869 | C70: Other [upi] | D70: Dine In | E70: Success | G70: Dine in | H70: Prashant | I70: 0 | J70: 0 | K70: 0 | L70: 1295 | M70: 0 | N70: 0
A71: 86802 | B71: 45869 | C71: Other [Amex Card] | D71: Dine In | E71: Success | F71: 2 | G71: Dine in | H71: Prince Vishwarkarma | I71: 0 | J71: 0 | K71: 0 | L71: 1558 | M71: 0 | N71: 0
A72: 86801 | B72: 45869 | C72: Other [upi] | D72: Dine In | E72: Success | F72: 2 | G72: Dine in | H72: Prashant | I72: 0 | J72: 0 | K72: 0 | L72: 867 | M72: 0 | N72: 0
A73: 86800 | B73: 45869 | C73: Other [Zomato Gold] | D73: Dine In | E73: Success | F73: 3 | G73: Dine in | H73: Prashant | I73: 0 | J73: 0 | K73: 0 | L73: 1679 | M73: 0 | N73: 0
A74: 86799 | B74: 45869 | C74: Other [Zomato Gold] | D74: Dine In | E74: Success | F74: 3 | G74: Dine in | H74: Prashant | I74: 0 | J74: 0 | K74: 0 | L74: 219 | M74: 0 | N74: 0
A75: 86798 | B75: 45869 | C75: Other [Zomato Gold] | D75: Dine In | E75: Success | G75: Dine in | H75: Prashant | I75: 0 | J75: 0 | K75: 0 | L75: 494 | M75: 0 | N75: 0
A76: 86797 | B76: 45869 | C76: Other [upi] | D76: Dine In | E76: Success | G76: Dine in | H76: Prashant | I76: 0 | J76: 0 | K76: 0 | L76: 1327 | M76: 0 | N76: 0
A77: 86796 | B77: 45869 | C77: Online | D77: Delivery(Parcel) | E77: Success | G77: Swiggy_This is it Cafe | I77: 0 | J77: 0 | K77: 0 | L77: 0 | M77: 0 | N77: 361
A78: 86795 | B78: 45869 | C78: Other [upi] | D78: Dine In | E78: Success | F78: 4 | G78: Dine in | H78: Prashant | I78: 0 | J78: 0 | K78: 0 | L78: 2064 | M78: 0 | N78: 0
A79: 86794 | B79: 45869 | C79: Other [upi] | D79: Dine In | E79: Success | G79: Dine in | H79: Prince Vishwarkarma | I79: 0 | J79: 0 | K79: 0 | L79: 307 | M79: 0 | N79: 0
A80: 86793 | B80: 45869 | C80: Other [upi] | D80: Dine In | E80: Success | G80: Dine in | H80: Prince Vishwarkarma | I80: 0 | J80: 0 | K80: 0 | L80: 438 | M80: 0 | N80: 0
A81: 86792 | B81: 45869 | C81: Online | D81: Delivery(Parcel) | E81: Success | G81: Zomato | I81: 0 | J81: 0 | K81: 0 | L81: 0 | M81: 0 | N81: 330
A82: 86791 | B82: 45869 | C82: Online | D82: Delivery(Parcel) | E82: Success | G82: Swiggy_This is it Cafe | I82: 0 | J82: 0 | K82: 0 | L82: 0 | M82: 0 | N82: 498
A83: 86790 | B83: 45869 | C83: Other [upi] | D83: Dine In | E83: Success | F83: 2 | G83: Dine in | H83: Prashant | I83: 0 | J83: 0 | K83: 0 | L83: 1496 | M83: 0 | N83: 0
A84: 86789 | B84: 45869 | C84: Online | D84: Delivery(Parcel) | E84: Success | G84: Swiggy_This is it Cafe | I84: 0 | J84: 0 | K84: 0 | L84: 0 | M84: 0 | N84: 414
A85: 86788 | B85: 45869 | C85: Other [upi] | D85: Dine In | E85: Success | G85: Dine in | H85: Prashant | I85: 0 | J85: 0 | K85: 0 | L85: 635 | M85: 0 | N85: 0
A86: 86787 | B86: 45869 | C86: Online | D86: Delivery(Parcel) | E86: Success | G86: Zomato | I86: 0 | J86: 0 | K86: 0 | L86: 0 | M86: 0 | N86: 523
A87: 86786 | B87: 45869 | C87: Online | D87: Delivery(Parcel) | E87: Success | G87: Zomato | I87: 0 | J87: 0 | K87: 0 | L87: 0 | M87: 0 | N87: 456
A88: 86785 | B88: 45869 | C88: Other [upi] | D88: Dine In | E88: Success | F88: 2 | G88: Dine in | H88: Prashant | I88: 0 | J88: 0 | K88: 0 | L88: 1239 | M88: 0 | N88: 0
A89: 86784 | B89: 45869 | C89: Online | D89: Delivery(Parcel) | E89: Success | G89: Swiggy_This is it Cafe | I89: 0 | J89: 0 | K89: 0 | L89: 0 | M89: 0 | N89: 1064
A90: 86783 | B90: 45869 | C90: Online | D90: Delivery(Parcel) | E90: Success | G90: Zomato | I90: 0 | J90: 0 | K90: 0 | L90: 0 | M90: 0 | N90: 340
A91: 86782 | B91: 45869 | C91: Online | D91: Delivery(Parcel) | E91: Success | G91: Zomato | I91: 0 | J91: 0 | K91: 0 | L91: 0 | M91: 0 | N91: 796
A92: 86781 | B92: 45869 | C92: Cash | D92: Dine In | E92: Success | F92: 5 | G92: Dine in | H92: Prashant | I92: 2751 | J92: 0 | K92: 0 | L92: 0 | M92: 0 | N92: 0
A93: 86780 | B93: 45869 | C93: Online | D93: Delivery(Parcel) | E93: Success | G93: Swiggy_This is it Cafe | I93: 0 | J93: 0 | K93: 0 | L93: 0 | M93: 0 | N93: 587
A94: 86779 | B94: 45869 | C94: Online | D94: Delivery(Parcel) | E94: Success | G94: Zomato | I94: 0 | J94: 0 | K94: 0 | L94: 0 | M94: 0 | N94: 508
A95: 86778 | B95: 45869 | C95: Other [upi] | D95: Dine In | E95: Success | G95: Dine in | H95: Prince Vishwarkarma | I95: 0 | J95: 0 | K95: 0 | L95: 569 | M95: 0 | N95: 0
A96: 86777 | B96: 45869 | C96: Other [upi] | D96: Dine In | E96: Success | F96: 2 | G96: Dine in | H96: Prince Vishwarkarma | I96: 0 | J96: 0 | K96: 0 | L96: 888 | M96: 0 | N96: 0
A97: 86776 | B97: 45869 | C97: Online | D97: Delivery(Parcel) | E97: Success | G97: Zomato | I97: 0 | J97: 0 | K97: 0 | L97: 0 | M97: 0 | N97: 225
A98: 86775 | B98: 45869 | C98: Other [upi] | D98: Dine In | E98: Success | G98: Dine in | H98: Prince Vishwarkarma | I98: 0 | J98: 0 | K98: 0 | L98: 241 | M98: 0 | N98: 0
A99: 86774 | B99: 45869 | C99: Online | D99: Delivery(Parcel) | E99: Success | G99: Zomato | I99: 0 | J99: 0 | K99: 0 | L99: 0 | M99: 0 | N99: 330
A100: 86773 | B100: 45869 | C100: Online | D100: Delivery(Parcel) | E100: Success | G100: Zomato | I100: 0 | J100: 0 | K100: 0 | L100: 0 | M100: 0 | N100: 1315
A101: 86772 | B101: 45869 | C101: Online | D101: Delivery(Parcel) | E101: Success | G101: Zomato | I101: 0 | J101: 0 | K101: 0 | L101: 0 | M101: 0 | N101: 775
A102: 86771 | B102: 45869 | C102: Other [upi] | D102: Dine In | E102: Success | G102: Dine in | H102: Prince Vishwarkarma | I102: 0 | J102: 0 | K102: 0 | L102: 263 | M102: 0 | N102: 0
A103: 86770 | B103: 45869 | C103: Part Payment | D103: Dine In | E103: Success | G103: Dine in | H103: Prince Vishwarkarma | I103: 230 | J103: 0 | K103: 0 | L103: 142 | M103: 0 | N103: 0
A104: 86769 | B104: 45869 | C104: Online | D104: Delivery(Parcel) | E104: Success | G104: Swiggy_This is it Cafe | I104: 0 | J104: 0 | K104: 0 | L104: 0 | M104: 0 | N104: 424
A105: 86768 | B105: 45869 | C105: Other [upi] | D105: Dine In | E105: Success | G105: Dine in | H105: Prince Vishwarkarma | I105: 0 | J105: 0 | K105: 0 | L105: 533 | M105: 0 | N105: 0
...

Sheet D1W1
I1: 1525 | J1: 59 | K1: 99.98 | L1: 0 | M1: 99.98 | N1: 1484.02 | O1: 74.2 | P1: 1558.216 | Q1: 1343.17 | R1: 0 | S1: 278.29 | T1: 0 | U1: 0 | V1: 0 | W1: 0 | X1: 0 | Y1: 0 | Z1: 0 | AA1: 0 | AB1: 0 | AC1: 50.08 | AD1: 328.37 | AE1: 215.04 | AF1: 0 | AG1: 215.04 | AH1: 63.96 | AI1: 0 | AJ1: 1.28 | AK1: 65.24 | AL1: 949.55 | AM1: 0 | AN1: 17.762 | AO1: 0 | AP1: 0 | AQ1: 0 | AR1: 0 | AS1: 0 | AT1: 0 | AU1: 157.33333 | AV1: 0 | AW1: 0 | AX1: 0 | AY1: 0 | AZ1: 0 | BA1: 0 | BB1: 0 | BC1: 0 | BD1: 0 | BE1: 0 | BF1: 0 | BG1: 0 | BH1: 0 | BI1: 0 | BJ1: 0 | BK1: 0 | BL1: 0 | BM1: 0 | BN1: 0 | BO1: 0 | BP1: 0 | BQ1: 0 | BR1: 0 | BS1: 0 | BT1: 0 | BU1: 0 | BV1: 0 | BW1: 0 | BX1: 0 | BY1: 0 | BZ1: 0 | CA1: 0 | CB1: 0 | CC1: 0
I2: 923695 | J2: 33137 | K2: 92340.33 | L2: 362.77 | M2: 92703.1 | N2: 864128.9 | O2: 43209.86 | P2: 907338.15 | Q2: 907337.72 | R2: 0 | S2: 156286.91 | T2: 3955 | U2: 0 | V2: 0 | W2: 0 | X2: 0 | Y2: 0 | Z2: 0 | AA2: 0 | AB2: 0 | AC2: 28841.84 | AD2: 189083.75 | AE2: 0 | AF2: 415 | AG2: 415 | AH2: 43206.34 | AI2: 0 | AJ2: 866.25 | AK2: 44072.59 | AL2: 673761.45 | AM2: 0 | AN2: 5900.627 | AO2: 0 | AP2: 0 | AQ2: 0 | AR2: 0 | AS2: 0 | AT2: 0 | AU2: 0 | AV2: 0 | AW2: 0 | AX2: 0 | AY2: 0 | AZ2: 0 | BA2: 0 | BB2: 0 | BC2: 0 | BD2: 0 | BE2: 0 | BF2: 0 | BG2: 0 | BH2: 0 | BI2: 0 | BJ2: 0 | BK2: 0 | BL2: 0 | BM2: 0 | BN2: 0 | BO2: 0 | BP2: 0 | BQ2: 0 | BR2: 0 | BS2: 0 | BT2: 0 | BU2: 0 | BV2: 0 | BW2: 0 | BX2: 0 | BY2: 0 | BZ2: 0 | CA2: 0 | CB2: 0 | CC2: 0
I3: 1091759.6 | J3: 39171.28 | K3: 109079.57 | L3: 428.0686 | M3: 109507.63 | N3: 1021423.2 | O3: 51075.191 | P3: 1072497.7 | Q3: 1072243.5 | R3: 0 | S3: 184746.94 | T3: 4666.9 | U3: 0 | V3: 0 | W3: 0 | X3: 0 | Y3: 0 | Z3: 0 | AA3: 0 | AB3: 0 | AC3: 34092.466 | AD3: 223506.3 | AE3: 253.7472 | AF3: 489.7 | AG3: 743.4472 | AH3: 51058.954 | AI3: 0 | AJ3: 1023.6854 | AK3: 52082.639 | AL3: 796158.98 | AM3: 0 | AN3: 6983.699 | AO3: 0 | AP3: 0 | AQ3: 0 | AR3: 0 | AS3: 0 | AT3: 0 | AU3: 185.65333 | AV3: 0 | AW3: 0 | AX3: 0 | AY3: 0 | AZ3: 0 | BA3: 0 | BB3: 0 | BC3: 0 | BD3: 0 | BE3: 0 | BF3: 0 | BG3: 0 | BH3: 0 | BI3: 0 | BJ3: 0 | BK3: 0 | BL3: 0 | BM3: 0 | BN3: 0 | BO3: 0 | BP3: 0 | BQ3: 0 | BR3: 0 | BS3: 0 | BT3: 0 | BU3: 0 | BV3: 0 | BW3: 0 | BX3: 0 | BY3: 0 | BZ3: 0 | CA3: 0 | CB3: 0 | CC3: 0
I4: 925220 | J4: 33196 | K4: 92440.31 | L4: 362.77 | M4: 92803.08 | N4: 865612.92 | O4: 43284.06 | P4: 908896.36 | Q4: 908680.89 | R4: 0 | S4: 156565.2 | T4: 3955 | U4: 0 | V4: 0 | W4: 0 | X4: 0 | Y4: 0 | Z4: 0 | AA4: 0 | AB4: 0 | AC4: 28891.92 | AD4: 189412.12 | AE4: 215.04 | AF4: 415 | AG4: 630.04 | AH4: 43270.3 | AI4: 0 | AJ4: 867.53 | AK4: 44137.83 | AL4: 674711 | AM4: 0 | AN4: 5918.389 | AO4: 0 | AP4: 0 | AQ4: 0 | AR4: 0 | AS4: 0 | AT4: 0 | AU4: 157.33333 | AV4: 0 | AW4: 0 | AX4: 0 | AY4: 0 | AZ4: 0 | BA4: 0 | BB4: 0 | BC4: 0 | BD4: 0 | BE4: 0 | BF4: 0 | BG4: 0 | BH4: 0 | BI4: 0 | BJ4: 0 | BK4: 0 | BL4: 0 | BM4: 0 | BN4: 0 | BO4: 0 | BP4: 0 | BQ4: 0 | BR4: 0 | BS4: 0 | BT4: 0 | BU4: 0 | BV4: 0 | BW4: 0 | BX4: 0 | BY4: 0 | BZ4: 0 | CA4: 0 | CB4: 0 | CC4: 0
A5: Order ID | B5: Parent Order ID | C5: Order Date | D5: Order Status | E5: Order Category | F5: Order Payment Type | G5: Cancelled By? | H5: Coupon type applied by customer | I5: Item Total | J5: Packaging Charges | K5: Restaurant Discounts (Promo, Freebies, Flat Off, etc.) | L5: Swiggy One Exclusive Offer Discount | M5: Restaurant Discount Share [3a+3b] | N5: Net Bill Value (before taxes) [1+2-3] | O5: GST Collected | P5: Total Customer Paid [4+5] | Q5: Commission charged on | R5: Service Fees % | S5: Commission | T5: Long Distance Charges | U5: Discount on Long Distance Fee | V5: Pocket Hero Fees | W5: Swiggy One Fees | X5: Payment Collection Charges | Y5: Restaurant Cancellation Charges | Z5: Call Center Charges | AA5: Delivery Fee sponsored by Restaurant (w/o tax) | AB5: Bolt Fees | AC5: GST on Service Fee @18% | AD5: Total Swiggy Fees [6+7+8-9+10+11+12+13+14+15+16] | AE5: Customer Cancellations | AF5: Customer Complaints | AG5: Complaint & Cancellation Charges [17+18] | AH5: GST Deduction | AI5: TCS | AJ5: TDS | AK5: Total Taxes [19+20+21] | AL5: Net Payout for Order (after taxes) [A-B-C-D] | AM5: Long Distance Order | AN5: Last Mile (in km) | AO5: MFR Accurate? | AP5: MFR Pressed? | AQ5: Coupon Code Sourced | AR5: Discount Campaign ID | AS5: Replicated Order | AT5: Base order ID | AU5: Cancellation time | AV5: Pick Up Status | AW5: Swiggy One Customer? | AX5: Pocket Hero Order?
A6: 215677732890652 | C6: 2025-09-01 11:58:52 | D6: delivered | E6: regular | I6: 160 | J6: 14 | K6: 0 | L6: 0 | M6: 0 | N6: 174 | O6: 8.7 | P6: 182.7 | Q6: 182.7 | R6: 22.0% | S6: 40.19 | T6: 0 | U6: 0 | V6: 0 | W6: 0 | X6: 0 | Y6: 0 | Z6: 0 | AA6: 0 | AB6: 0 | AC6: 7.24 | AD6: 47.43 | AE6: 0 | AF6: 0 | AG6: 0 | AH6: 8.7 | AI6: 0 | AJ6: 0.17 | AK6: 8.87 | AL6: 126.41 | AM6: No | AN6: 2.741 | AO6: Yes | AP6: No | AR6: 206500dc-ba9e-4a58-be62-bb3f830ec1f3 | AS6: No | AW6: Yes | AX6: No
A7: 215677963601856 | C7: 2025-09-01 12:02:43 | D7: delivered | E7: regular | H7: FLAVORFUL | I7: 1070 | J7: 35 | K7: 99.99 | L7: 0 | M7: 99.99 | N7: 1005.01 | O7: 50.26 | P7: 1055.268 | Q7: 1055.27 | R7: 16.0% | S7: 168.84 | T7: 0 | U7: 0 | V7: 0 | W7: 0 | X7: 0 | Y7: 0 | Z7: 0 | AA7: 0 | AB7: 0 | AC7: 30.4 | AD7: 199.24 | AE7: 0 | AF7: 0 | AG7: 0 | AH7: 50.25 | AI7: 0 | AJ7: 1.01 | AK7: 51.26 | AL7: 804.78 | AM7: No | AN7: 3.139 | AO7: Yes | AP7: No | AR7: ac0e42c3-a3b6-4eba-95c9-97e2a420b3c7,206500dc-ba9e-4a58-be62-bb3f830ec1f3,ac0e42c3-a3b6-4eba-95c9-97e2a420b3c7,206500dc-ba9e-4a58-be62-bb3f830ec1f3 | AS7: No | AW7: Yes | AX7: No
A8: 215678197728179 | C8: 2025-09-01 12:06:37 | D8: delivered | E8: regular | H8: SWIGGYIT | I8: 495 | J8: 20 | K8: 64 | L8: 0 | M8: 64 | N8: 451 | O8: 22.56 | P8: 473.56 | Q8: 473.56 | R8: 22.0% | S8: 104.18 | T8: 12 | U8: 0 | V8: 0 | W8: 0 | X8: 0 | Y8: 0 | Z8: 0 | AA8: 0 | AB8: 0 | AC8: 20.92 | AD8: 137.1 | AE8: 0 | AF8: 0 | AG8: 0 | AH8: 22.55 | AI8: 0 | AJ8: 0.45 | AK8: 23 | AL8: 313.47 | AM8: Yes | AN8: 8.596 | AO8: Yes | AP8: No | AR8: 100833489 | AS8: No | AW8: Yes | AX8: No
A9: 215678342271988 | C9: 2025-09-01 12:09:02 | D9: delivered | E9: regular | I9: 950 | J9: 30 | K9: 0 | L9: 0 | M9: 0 | N9: 980 | O9: 49 | P9: 1029 | Q9: 1029 | R9: 16.0% | S9: 164.64 | T9: 0 | U9: 0 | V9: 0 | W9: 0 | X9: 0 | Y9: 0 | Z9: 0 | AA9: 0 | AB9: 0 | AC9: 29.64 | AD9: 194.28 | AE9: 0 | AF9: 0 | AG9: 0 | AH9: 49 | AI9: 0 | AJ9: 0.98 | AK9: 49.98 | AL9: 784.74 | AM9: No | AN9: 2.541 | AO9: Yes | AP9: No | AR9: 206500dc-ba9e-4a58-be62-bb3f830ec1f3 | AS9: No | AW9: Yes | AX9: No
A10: 215678409572245 | C10: 2025-09-01 12:10:09 | D10: delivered | E10: regular | I10: 295 | J10: 15 | K10: 0 | L10: 0 | M10: 0 | N10: 310 | O10: 15.5 | P10: 325.5 | Q10: 325.5 | R10: 22.0% | S10: 71.61 | T10: 0 | U10: 0 | V10: 0 | W10: 0 | X10: 0 | Y10: 0 | Z10: 0 | AA10: 0 | AB10: 0 | AC10: 12.88 | AD10: 84.49 | AE10: 0 | AF10: 0 | AG10: 0 | AH10: 15.5 | AI10: 0 | AJ10: 0.31 | AK10: 15.81 | AL10: 225.18 | AM10: No | AN10: 2.043 | AO10: Yes | AP10: No | AR10: 206500dc-ba9e-4a58-be62-bb3f830ec1f3 | AS10: No | AW10: Yes | AX10: No
A11: 215678515758411 | C11: 2025-09-01 12:11:55 | D11: delivered | E11: regular | H11: PARTY | I11: 1365 | J11: 45 | K11: 136.5 | L11: 0 | M11: 136.5 | N11: 1273.5 | O11: 63.68 | P11: 1337.18 | Q11: 1337.18 | R11: 16.0% | S11: 213.95 | T11: 0 | U11: 0 | V11: 0 | W11: 0 | X11: 0 | Y11: 0 | Z11: 0 | AA11: 0 | AB11: 0 | AC11: 38.52 | AD11: 252.47 | AE11: 0 | AF11: 0 | AG11: 0 | AH11: 63.67 | AI11: 0 | AJ11: 1.27 | AK11: 64.94 | AL11: 1019.77 | AM11: No | AN11: 3.657 | AO11: Yes | AP11: No | AR11: 206500dc-ba9e-4a58-be62-bb3f830ec1f3,206500dc-ba9e-4a58-be62-bb3f830ec1f3 | AS11: No | AW11: Yes | AX11: No
A12: 215678655895729 | C12: 2025-09-01 12:14:15 | D12: delivered | E12: regular | H12: SWIGGYIT | I12: 495 | J12: 20 | K12: 64 | L12: 0 | M12: 64 | N12: 451 | O12: 22.56 | P12: 473.56 | Q12: 473.56 | R12: 22.0% | S12: 104.18 | T12: 0 | U12: 0 | V12: 0 | W12: 0 | X12: 0 | Y12: 0 | Z12: 0 | AA12: 0 | AB12: 0 | AC12: 18.76 | AD12: 122.94 | AE12: 0 | AF12: 0 | AG12: 0 | AH12: 22.55 | AI12: 0 | AJ12: 0.45 | AK12: 23 | AL12: 327.63 | AM12: No | AN12: 2.741 | AO12: Yes | AP12: No | AR12: 206500dc-ba9e-4a58-be62-bb3f830ec1f3,206500dc-ba9e-4a58-be62-bb3f830ec1f3 | AS12: No | AW12: Yes | AX12: No
A13: 215678880211013 | C13: 2025-09-01 12:18:00 | D13: delivered | E13: regular | H13: FLAVORFUL | I13: 880 | J13: 39 | K13: 99.99 | L13: 0 | M13: 99.99 | N13: 819.01 | O13: 40.96 | P13: 859.968 | Q13: 859.97 | R13: 20.0% | S13: 171.99 | T13: 0 | U13: 0 | V13: 0 | W13: 0 | X13: 0 | Y13: 0 | Z13: 0 | AA13: 0 | AB13: 0 | AC13: 30.96 | AD13: 202.95 | AE13: 0 | AF13: 0 | AG13: 0 | AH13: 40.95 | AI13: 0 | AJ13: 0.82 | AK13: 41.77 | AL13: 615.24 | AM13: No | AN13: 3.71 | AO13: Yes | AP13: No | AR13: 206500dc-ba9e-4a58-be62-bb3f830ec1f3,206500dc-ba9e-4a58-be62-bb3f830ec1f3 | AS13: No | AW13: Yes | AX13: No
A14: 215679064037381 | C14: 2025-09-01 12:21:04 | D14: delivered | E14: regular | H14: TRYNEW | I14: 395 | J14: 15 | K14: 64 | L14: 0 | M14: 64 | N14: 346 | O14: 17.3 | P14: 363.3 | Q14: 363.3 | R14: 22.0% | S14: 79.93 | T14: 0 | U14: 0 | V14: 0 | W14: 0 | X14: 0 | Y14: 0 | Z14: 0 | AA14: 0 | AB14: 0 | AC14: 14.38 | AD14: 94.31 | AE14: 0 | AF14: 0 | AG14: 0 | AH14: 17.3 | AI14: 0 | AJ14: 0.35 | AK14: 17.65 | AL14: 251.33 | AM14: No | AN14: 2.741 | AO14: Yes | AP14: No | AR14: 206500dc-ba9e-4a58-be62-bb3f830ec1f3,206500dc-ba9e-4a58-be62-bb3f830ec1f3 | AS14: No | AW14: Yes | AX14: No
A15: 215679187221684 | C15: 2025-09-01 12:23:07 | D15: delivered | E15: regular | H15: TRYNEW | I15: 445 | J15: 15 | K15: 64 | L15: 0 | M15: 64 | N15: 396 | O15: 19.8 | P15: 415.8 | Q15: 415.8 | R15: 22.0% | S15: 91.48 | T15: 0 | U15: 0 | V15: 0 | W15: 0 | X15: 0 | Y15: 0 | Z15: 0 | AA15: 0 | AB15: 0 | AC15: 16.46 | AD15: 107.94 | AE15: 0 | AF15: 0 | AG15: 0 | AH15: 19.8 | AI15: 0 | AJ15: 0.4 | AK15: 20.2 | AL15: 287.65 | AM15: No | AN15: 2.857 | AO15: Yes | AP15: No | AR15: 206500dc-ba9e-4a58-be62-bb3f830ec1f3,206500dc-ba9e-4a58-be62-bb3f830ec1f3 | AS15: No | AW15: Yes | AX15: No
A16: 215679212670399 | C16: 2025-09-01 12:23:32 | D16: delivered | E16: regular | H16: SWIGGYIT | I16: 295 | J16: 10 | K16: 64 | L16: 0 | M16: 64 | N16: 241 | O16: 12.06 | P16: 253.06 | Q16: 253.06 | R16: 22.0% | S16: 55.67 | T16: 0 | U16: 0 | V16: 0 | W16: 0 | X16: 0 | Y16: 0 | Z16: 0 | AA16: 0 | AB16: 0 | AC16: 10.02 | AD16: 65.69 | AE16: 0 | AF16: 0 | AG16: 0 | AH16: 12.05 | AI16: 0 | AJ16: 0.24 | AK16: 12.29 | AL16: 175.07 | AM16: No | AN16: 2.768 | AO16: Yes | AP16: No | AR16: 206500dc-ba9e-4a58-be62-bb3f830ec1f3,206500dc-ba9e-4a58-be62-bb3f830ec1f3 | AS16: No | AW16: Yes | AX16: No
A17: 215679346372023 | C17: 2025-09-01 12:25:46 | D17: delivered | E17: regular | H17: TRYNEW | I17: 445 | J17: 15 | K17: 64 | L17: 0 | M17: 64 | N17: 396 | O17: 19.8 | P17: 415.8 | Q17: 415.8 | R17: 22.0% | S17: 91.48 | T17: 7 | U17: 0 | V17: 0 | W17: 0 | X17: 0 | Y17: 0 | Z17: 0 | AA17: 0 | AB17: 0 | AC17: 17.72 | AD17: 116.2 | AE17: 0 | AF17: 0 | AG17: 0 | AH17: 19.8 | AI17: 0 | AJ17: 0.4 | AK17: 20.2 | AL17: 279.39 | AM17: Yes | AN17: 6.685 | AO17: Yes | AP17: No | AR17: 206500dc-ba9e-4a58-be62-bb3f830ec1f3,206500dc-ba9e-4a58-be62-bb3f830ec1f3 | AS17: No | AW17: Yes | AX17: No
A18: 215679415619995 | C18: 2025-09-01 12:26:55 | D18: delivered | E18: regular | I18: 870 | J18: 30 | K18: 0 | L18: 0 | M18: 0 | N18: 900 | O18: 45 | P18: 945 | Q18: 945 | R18: 16.0% | S18: 151.2 | T18: 0 | U18: 0 | V18: 0 | W18: 0 | X18: 0 | Y18: 0 | Z18: 0 | AA18: 0 | AB18: 0 | AC18: 27.22 | AD18: 178.42 | AE18: 0 | AF18: 0 | AG18: 0 | AH18: 45 | AI18: 0 | AJ18: 0.9 | AK18: 45.9 | AL18: 720.68 | AM18: No | AN18: 4.281 | AO18: Yes | AP18: No | AR18: bf7dde31-1f03-438b-8c83-4e934e8fdc40,206500dc-ba9e-4a58-be62-bb3f830ec1f3 | AS18: No | AW18: Yes | AX18: No
A19: 215679549635390 | C19: 2025-09-01 12:29:09 | D19: delivered | E19: regular | I19: 505 | J19: 22 | K19: 0 | L19: 0 | M19: 0 | N19: 527 | O19: 26.36 | P19: 553.36 | Q19: 553.36 | R19: 20.0% | S19: 110.67 | T19: 12 | U19: 0 | V19: 0 | W19: 0 | X19: 0 | Y19: 0 | Z19: 0 | AA19: 0 | AB19: 0 | AC19: 22.08 | AD19: 144.75 | AE19: 0 | AF19: 0 | AG19: 0 | AH19: 26.35 | AI19: 0 | AJ19: 0.53 | AK19: 26.88 | AL19: 381.72 | AM19: Yes | AN19: 8.282 | AO19: Yes | AP19: No | AS19: No | AW19: Yes | AX19: No
A20: 215679572043008 | C20: 2025-09-01 12:29:32 | D20: delivered | E20: regular | H20: FLAVORFUL | I20: 1195 | J20: 45 | K20: 99.98 | L20: 0 | M20: 99.98 | N20: 1140.02 | O20: 57 | P20: 1197.016 | Q20: 1197.02 | R20: 16.0% | S20: 191.52 | T20: 0 | U20: 0 | V20: 0 | W20: 0 | X20: 0 | Y20: 0 | Z20: 0 | AA20: 0 | AB20: 0 | AC20: 34.48 | AD20: 226 | AE20: 0 | AF20: 0 | AG20: 0 | AH20: 57 | AI20: 0 | AJ20: 1.14 | AK20: 58.14 | AL20: 912.89 | AM20: No | AN20: 5.009 | AO20: Yes | AP20: No | AR20: 6914cfae-bb51-40ca-99a1-0ec7555ec922,206500dc-ba9e-4a58-be62-bb3f830ec1f3,6914cfae-bb51-40ca-99a1-0ec7555ec922,206500dc-ba9e-4a58-be62-bb3f830ec1f3 | AS20: No | AW20: Yes | AX20: No
A21: 215679830114524 | C21: 2025-09-01 12:33:50 | D21: delivered | E21: regular | H21: TRYNEW | I21: 375 | J21: 15 | K21: 64 | L21: 0 | M21: 64 | N21: 326 | O21: 16.3 | P21: 342.3 | Q21: 342.3 | R21: 22.0% | S21: 75.31 | T21: 0 | U21: 0 | V21: 0 | W21: 0 | X21: 0 | Y21: 0 | Z21: 0 | AA21: 0 | AB21: 0 | AC21: 13.56 | AD21: 88.87 | AE21: 0 | AF21: 0 | AG21: 0 | AH21: 16.3 | AI21: 0 | AJ21: 0.33 | AK21: 16.63 | AL21: 236.81 | AM21: No | AN21: 3.415 | AO21: Yes | AP21: No | AR21: 206500dc-ba9e-4a58-be62-bb3f830ec1f3,206500dc-ba9e-4a58-be62-bb3f830ec1f3 | AS21: No | AW21: Yes | AX21: No
A22: 215679923956471 | C22: 2025-09-01 12:35:23 | D22: delivered | E22: regular | H22: WELCOMEBITE | I22: 275 | J22: 10 | K22: 64 | L22: 0 | M22: 64 | N22: 221 | O22: 11.06 | P22: 232.06 | Q22: 232.06 | R22: 22.0% | S22: 51.05 | T22: 0 | U22: 0 | V22: 0 | W22: 0 | X22: 0 | Y22: 0 | Z22: 0 | AA22: 0 | AB22: 0 | AC22: 9.18 | AD22: 60.23 | AE22: 0 | AF22: 0 | AG22: 0 | AH22: 11.05 | AI22: 0 | AJ22: 0.22 | AK22: 11.27 | AL22: 160.53 | AM22: No | AN22: 2.768 | AO22: Yes | AP22: No | AQ22: TRYNEW | AR22: 206500dc-ba9e-4a58-be62-bb3f830ec1f3,153b8f73-eef8-4800-a399-6e532c1bda24,206500dc-ba9e-4a58-be62-bb3f830ec1f3,153b8f73-eef8-4800-a399-6e532c1bda24 | AS22: No | AW22: Yes | AX22: No
A23: 215680160949774 | C23: 2025-09-01 12:39:20 | D23: delivered | E23: regular | H23: SWIGGYIT | I23: 575 | J23: 22 | K23: 63.99 | L23: 0 | M23: 63.99 | N23: 533.01 | O23: 26.66 | P23: 559.668 | Q23: 559.67 | R23: 20.0% | S23: 111.93 | T23: 0 | U23: 0 | V23: 0 | W23: 0 | X23: 0 | Y23: 0 | Z23: 0 | AA23: 0 | AB23: 0 | AC23: 20.14 | AD23: 132.07 | AE23: 0 | AF23: 0 | AG23: 0 | AH23: 26.65 | AI23: 0 | AJ23: 0.53 | AK23: 27.18 | AL23: 400.39 | AM23: No | AN23: 2.101 | AO23: Yes | AP23: No | AR23: 206500dc-ba9e-4a58-be62-bb3f830ec1f3,206500dc-ba9e-4a58-be62-bb3f830ec1f3 | AS23: No | AW23: Yes | AX23: No
A24: 215680429434372 | C24: 2025-09-01 12:43:49 | D24: delivered | E24: regular | H24: SWIGGYIT | I24: 495 | J24: 15 | K24: 64 | L24: 0 | M24: 64 | N24: 446 | O24: 22.3 | P24: 468.3 | Q24: 468.3 | R24: 22.0% | S24: 103.03 | T24: 0 | U24: 0 | V24: 0 | W24: 0 | X24: 0 | Y24: 0 | Z24: 0 | AA24: 0 | AB24: 0 | AC24: 18.54 | AD24: 121.57 | AE24: 0 | AF24: 0 | AG24: 0 | AH24: 22.3 | AI24: 0 | AJ24: 0.45 | AK24: 22.75 | AL24: 323.97 | AM24: No | AN24: 2.752 | AO24: Yes | AP24: No | AR24: d2721a30-5138-4b0f-8bfb-f14ce57ac577,d2721a30-5138-4b0f-8bfb-f14ce57ac577 | AS24: No | AW24: Yes | AX24: No
A25: 215680536650949 | C25: 2025-09-01 12:45:36 | D25: delivered | E25: regular | I25: 1020 | J25: 30 | K25: 0 | L25: 0 | M25: 0 | N25: 1050 | O25: 52.5 | P25: 1102.5 | Q25: 1102.5 | R25: 16.0% | S25: 176.4 | T25: 0 | U25: 0 | V25: 0 | W25: 0 | X25: 0 | Y25: 0 | Z25: 0 | AA25: 0 | AB25: 0 | AC25: 31.76 | AD25: 208.16 | AE25: 0 | AF25: 0 | AG25: 0 | AH25: 52.5 | AI25: 0 | AJ25: 1.05 | AK25: 53.55 | AL25: 840.81 | AM25: No | AN25: 3.676 | AO25: Yes | AP25: No | AR25: 206500dc-ba9e-4a58-be62-bb3f830ec1f3 | AS25: No | AW25: Yes | AX25: No
A26: 215680787260929 | C26: 2025-09-01 12:49:47 | D26: delivered | E26: regular | I26: 595 | J26: 20 | K26: 0 | L26: 0 | M26: 0 | N26: 615 | O26: 30.76 | P26: 645.76 | Q26: 645.76 | R26: 20.0% | S26: 129.15 | T26: 7 | U26: 0 | V26: 0 | W26: 0 | X26: 0 | Y26: 0 | Z26: 0 | AA26: 0 | AB26: 0 | AC26: 24.5 | AD26: 160.65 | AE26: 0 | AF26: 0 | AG26: 0 | AH26: 30.75 | AI26: 0 | AJ26: 0.61 | AK26: 31.36 | AL26: 453.72 | AM26: Yes | AN26: 7.65 | AO26: Yes | AP26: No | AR26: ce57407d-6f5b-456c-8493-63de62e4740e | AS26: No | AW26: Yes | AX26: No
A27: 215680909672216 | C27: 2025-09-01 12:51:49 | D27: delivered | E27: regular | H27: SWIGGYIT | I27: 495 | J27: 20 | K27: 64 | L27: 0 | M27: 64 | N27: 451 | O27: 22.56 | P27: 473.56 | Q27: 473.56 | R27: 22.0% | S27: 104.18 | T27: 0 | U27: 0 | V27: 0 | W27: 0 | X27: 0 | Y27: 0 | Z27: 0 | AA27: 0 | AB27: 0 | AC27: 18.76 | AD27: 122.94 | AE27: 0 | AF27: 0 | AG27: 0 | AH27: 22.55 | AI27: 0 | AJ27: 0.45 | AK27: 23 | AL27: 327.63 | AM27: No | AN27: 4 | AO27: Yes | AP27: No | AR27: 206500dc-ba9e-4a58-be62-bb3f830ec1f3,206500dc-ba9e-4a58-be62-bb3f830ec1f3 | AS27: No | AW27: Yes | AX27: No
A28: 215681008896589 | C28: 2025-09-01 12:53:28 | D28: delivered | E28: regular | H28: TRYNEW | I28: 445 | J28: 15 | K28: 64 | L28: 0 | M28: 64 | N28: 396 | O28: 19.8 | P28: 415.8 | Q28: 415.8 | R28: 22.0% | S28: 91.48 | T28: 0 | U28: 0 | V28: 0 | W28: 0 | X28: 0 | Y28: 0 | Z28: 0 | AA28: 0 | AB28: 0 | AC28: 16.46 | AD28: 107.94 | AE28: 0 | AF28: 0 | AG28: 0 | AH28: 19.8 | AI28: 0 | AJ28: 0.4 | AK28: 20.2 | AL28: 287.65 | AM28: No | AN28: 4.129 | AO28: Yes | AP28: No | AR28: 206500dc-ba9e-4a58-be62-bb3f830ec1f3,206500dc-ba9e-4a58-be62-bb3f830ec1f3 | AS28: No | AW28: Yes | AX28: No
A29: 215681350514143 | C29: 2025-09-01 12:59:10 | D29: delivered | E29: regular | H29: FLAVORFUL | I29: 1115 | J29: 40 | K29: 99.98 | L29: 0 | M29: 99.98 | N29: 1055.02 | O29: 52.76 | P29: 1107.776 | Q29: 1107.78 | R29: 16.0% | S29: 177.24 | T29: 0 | U29: 0 | V29: 0 | W29: 0 | X29: 0 | Y29: 0 | Z29: 0 | AA29: 0 | AB29: 0 | AC29: 31.9 | AD29: 209.14 | AE29: 0 | AF29: 0 | AG29: 0 | AH29: 52.75 | AI29: 0 | AJ29: 1.06 | AK29: 53.81 | AL29: 844.81 | AM29: No | AN29: 3.503 | AO29: Yes | AP29: No | AR29: 206500dc-ba9e-4a58-be62-bb3f830ec1f3,206500dc-ba9e-4a58-be62-bb3f830ec1f3 | AS29: No | AW29: Yes | AX29: No
A30: 215681433971231 | C30: 2025-09-01 13:00:33 | D30: delivered | E30: regular | H30: SWIGGYIT | I30: 345 | J30: 15 | K30: 64 | L30: 0 | M30: 64 | N30: 296 | O30: 14.8 | P30: 310.8 | Q30: 310.8 | R30: 22.0% | S30: 68.38 | T30: 7 | U30: 0 | V30: 0 | W30: 0 | X30: 0 | Y30: 0 | Z30: 0 | AA30: 0 | AB30: 0 | AC30: 13.56 | AD30: 88.94 | AE30: 0 | AF30: 0 | AG30: 0 | AH30: 14.8 | AI30: 0 | AJ30: 0.3 | AK30: 15.1 | AL30: 206.75 | AM30: Yes | AN30: 6.543 | AO30: Yes | AP30: No | AR30: 206500dc-ba9e-4a58-be62-bb3f830ec1f3,206500dc-ba9e-4a58-be62-bb3f830ec1f3 | AS30: No | AW30: Yes | AX30: No
A31: 215681503976527 | C31: 2025-09-01 13:01:43 | D31: delivered | E31: regular | H31: FLAVORFUL | I31: 950 | J31: 35 | K31: 99.99 | L31: 0 | M31: 99.99 | N31: 885.01 | O31: 44.26 | P31: 929.268 | Q31: 929.27 | R31: 16.0% | S31: 148.68 | T31: 0 | U31: 0 | V31: 0 | W31: 0 | X31: 0 | Y31: 0 | Z31: 0 | AA31: 0 | AB31: 0 | AC31: 26.76 | AD31: 175.44 | AE31: 0 | AF31: 0 | AG31: 0 | AH31: 44.25 | AI31: 0 | AJ31: 0.89 | AK31: 45.14 | AL31: 708.68 | AM31: No | AN31: 5.103 | AO31: Yes | AP31: No | AR31: 419540c2-a8bc-4570-96b4-d4a769aa36da,206500dc-ba9e-4a58-be62-bb3f830ec1f3,419540c2-a8bc-4570-96b4-d4a769aa36da,206500dc-ba9e-4a58-be62-bb3f830ec1f3 | AS31: No | AW31: Yes | AX31: No
A32: 215681683200756 | C32: 2025-09-01 13:04:43 | D32: delivered | E32: regular | H32: SWIGGYIT | I32: 495 | J32: 15 | K32: 64 | L32: 0 | M32: 64 | N32: 446 | O32: 22.3 | P32: 468.3 | Q32: 468.3 | R32: 22.0% | S32: 103.03 | T32: 0 | U32: 0 | V32: 0 | W32: 0 | X32: 0 | Y32: 0 | Z32: 0 | AA32: 0 | AB32: 0 | AC32: 18.54 | AD32: 121.57 | AE32: 0 | AF32: 0 | AG32: 0 | AH32: 22.3 | AI32: 0 | AJ32: 0.45 | AK32: 22.75 | AL32: 323.97 | AM32: No | AN32: 2.741 | AO32: Yes | AP32: No | AR32: 206500dc-ba9e-4a58-be62-bb3f830ec1f3,206500dc-ba9e-4a58-be62-bb3f830ec1f3 | AS32: No | AW32: Yes | AX32: No
A33: 215681766589401 | C33: 2025-09-01 13:06:06 | D33: delivered | E33: regular | H33: TRYNEW | I33: 495 | J33: 15 | K33: 64 | L33: 0 | M33: 64 | N33: 446 | O33: 22.3 | P33: 468.3 | Q33: 468.3 | R33: 22.0% | S33: 103.03 | T33: 0 | U33: 0 | V33: 0 | W33: 0 | X33: 0 | Y33: 0 | Z33: 0 | AA33: 0 | AB33: 0 | AC33: 18.54 | AD33: 121.57 | AE33: 0 | AF33: 0 | AG33: 0 | AH33: 22.3 | AI33: 0 | AJ33: 0.45 | AK33: 22.75 | AL33: 323.97 | AM33: No | AN33: 4.799 | AO33: Yes | AP33: No | AR33: 206500dc-ba9e-4a58-be62-bb3f830ec1f3,206500dc-ba9e-4a58-be62-bb3f830ec1f3 | AS33: No | AW33: Yes | AX33: No
A34: 215682015822241 | C34: 2025-09-01 13:10:15 | D34: delivered | E34: regular | H34: SWIGGYIT | I34: 395 | J34: 15 | K34: 64 | L34: 0 | M34: 64 | N34: 346 | O34: 17.3 | P34: 363.3 | Q34: 363.3 | R34: 22.0% | S34: 79.93 | T34: 0 | U34: 0 | V34: 0 | W34: 0 | X34: 0 | Y34: 0 | Z34: 0 | AA34: 0 | AB34: 0 | AC34: 14.38 | AD34: 94.31 | AE34: 0 | AF34: 0 | AG34: 0 | AH34: 17.3 | AI34: 0 | AJ34: 0.35 | AK34: 17.65 | AL34: 251.33 | AM34: No | AN34: 4.811 | AO34: Yes | AP34: No | AR34: 3d863974-48e1-4952-bcd2-ba7e746255af,206500dc-ba9e-4a58-be62-bb3f830ec1f3,3d863974-48e1-4952-bcd2-ba7e746255af,206500dc-ba9e-4a58-be62-bb3f830ec1f3 | AS34: No | AW34: Yes | AX34: No
A35: 215682027608451 | C35: 2025-09-01 13:10:27 | D35: delivered | E35: regular | H35: SWIGGYIT | I35: 475 | J35: 15 | K35: 64 | L35: 0 | M35: 64 | N35: 426 | O35: 21.3 | P35: 447.3 | Q35: 447.3 | R35: 22.0% | S35: 98.41 | T35: 0 | U35: 0 | V35: 0 | W35: 0 | X35: 0 | Y35: 0 | Z35: 0 | AA35: 0 | AB35: 0 | AC35: 17.72 | AD35: 116.13 | AE35: 0 | AF35: 0 | AG35: 0 | AH35: 21.3 | AI35: 0 | AJ35: 0.43 | AK35: 21.73 | AL35: 309.46 | AM35: No | AN35: 2.901 | AO35: Yes | AP35: No | AR35: 206500dc-ba9e-4a58-be62-bb3f830ec1f3,206500dc-ba9e-4a58-be62-bb3f830ec1f3 | AS35: No | AW35: Yes | AX35: No
A36: 215682147110116 | C36: 2025-09-01 13:12:27 | D36: delivered | E36: regular | H36: TRYNEW | I36: 625 | J36: 29 | K36: 64 | L36: 0 | M36: 64 | N36: 590 | O36: 29.5 | P36: 619.5 | Q36: 619.5 | R36: 20.0% | S36: 123.9 | T36: 0 | U36: 0 | V36: 0 | W36: 0 | X36: 0 | Y36: 0 | Z36: 0 | AA36: 0 | AB36: 0 | AC36: 22.3 | AD36: 146.2 | AE36: 0 | AF36: 0 | AG36: 0 | AH36: 29.5 | AI36: 0 | AJ36: 0.59 | AK36: 30.09 | AL36: 443.21 | AM36: No | AN36: 2.223 | AO36: Yes | AP36: No | AR36: 206500dc-ba9e-4a58-be62-bb3f830ec1f3,206500dc-ba9e-4a58-be62-bb3f830ec1f3 | AS36: No | AW36: Yes | AX36: No
A37: 215682384869780 | C37: 2025-09-01 13:16:24 | D37: delivered | E37: regular | H37: PARTY | I37: 1940 | J37: 81 | K37: 194 | L37: 0 | M37: 194 | N37: 1827 | O37: 91.36 | P37: 1918.36 | Q37: 1918.34 | R37: 14.0% | S37: 268.57 | T37: 0 | U37: 0 | V37: 0 | W37: 0 | X37: 0 | Y37: 0 | Z37: 0 | AA37: 0 | AB37: 0 | AC37: 48.34 | AD37: 316.91 | AE37: 0 | AF37: 0 | AG37: 0 | AH37: 91.35 | AI37: 0 | AJ37: 1.83 | AK37: 93.18 | AL37: 1508.26 | AM37: No | AN37: 2.857 | AO37: Yes | AP37: No | AR37: 206500dc-ba9e-4a58-be62-bb3f830ec1f3,206500dc-ba9e-4a58-be62-bb3f830ec1f3 | AS37: No | AW37: Yes | AX37: No
A38: 215682407670759 | C38: 2025-09-01 13:16:47 | D38: delivered | E38: regular | H38: TRYNEW | I38: 345 | J38: 15 | K38: 64 | L38: 0 | M38: 64 | N38: 296 | O38: 14.8 | P38: 310.8 | Q38: 310.8 | R38: 22.0% | S38: 68.38 | T38: 0 | U38: 0 | V38: 0 | W38: 0 | X38: 0 | Y38: 0 | Z38: 0 | AA38: 0 | AB38: 0 | AC38: 12.3 | AD38: 80.68 | AE38: 0 | AF38: 0 | AG38: 0 | AH38: 14.8 | AI38: 0 | AJ38: 0.3 | AK38: 15.1 | AL38: 215.01 | AM38: No | AN38: 1.856 | AO38: Yes | AP38: No | AR38: 206500dc-ba9e-4a58-be62-bb3f830ec1f3,206500dc-ba9e-4a58-be62-bb3f830ec1f3 | AS38: No | AW38: Yes | AX38: No
... A44: 215683603479812 | C44: 2025-09-01 13:36:43 | D44: delivered | E44: regular | H44: SWIGGYIT | I44: 595 | J44: 20 | K44: 64 | L44: 0 | M44: 64 | N44: 551 | O44: 27.56 | P44: 578.56 | Q44: 578.56 | R44: 20.0% | S44: 115.71 | T44: 7 | U44: 0 | V44: 0 | W44: 0 | X44: 0 | Y44: 0 | Z44: 0 | AA44: 0 | AB44: 0 | AC44: 22.08 | AD44: 144.79 | AE44: 0 | AF44: 0 | AG44: 0 | AH44: 27.55 | AI44: 0 | AJ44: 0.55 | AK44: 28.1 | AL44: 405.64 | AM44: Yes | AN44: 6.885 | AO44: Yes | AP44: No | AR44: 206500dc-ba9e-4a58-be62-bb3f830ec1f3,206500dc-ba9e-4a58-be62-bb3f830ec1f3 | AS44: No | AW44: Yes | AX44: No
A45: 215683732142747 | C45: 2025-09-01 13:38:52 | D45: delivered | E45: regular | I45: 915 | J45: 35 | K45: 0 | L45: 0 | M45: 0 | N45: 950 | O45: 47.5 | P45: 997.5 | Q45: 997.5 | R45: 16.0% | S45: 159.6 | T45: 0 | U45: 0 | V45: 0 | W45: 0 | X45: 0 | Y45: 0 | Z45: 0 | AA45: 0 | AB45: 0 | AC45: 28.72 | AD45: 188.32 | AE45: 0 | AF45: 0 | AG45: 0 | AH45: 47.5 | AI45: 0 | AJ45: 0.95 | AK45: 48.45 | AL45: 760.71 | AM45: No | AN45: 3.536 | AO45: Yes | AP45: No | AS45: No | AW45: No | AX45: No
A46: 215683744328843 | C46: 2025-09-01 13:39:04 | D46: delivered | E46: regular | H46: SWIGGYIT | I46: 475 | J46: 15 | K46: 64 | L46: 0 | M46: 64 | N46: 426 | O46: 21.3 | P46: 447.3 | Q46: 447.3 | R46: 22.0% | S46: 98.41 | T46: 0 | U46: 0 | V46: 0 | W46: 0 | X46: 0 | Y46: 0 | Z46: 0 | AA46: 0 | AB46: 0 | AC46: 17.72 | AD46: 116.13 | AE46: 0 | AF46: 0 | AG46: 0 | AH46: 21.3 | AI46: 0 | AJ46: 0.43 | AK46: 21.73 | AL46: 309.46 | AM46: No | AN46: 3.989 | AO46: Yes | AP46: No | AR46: 206500dc-ba9e-4a58-be62-bb3f830ec1f3,206500dc-ba9e-4a58-be62-bb3f830ec1f3 | AS46: No | AW46: Yes | AX46: No
A47: 215684060413883 | C47: 2025-09-01 13:44:20 | D47: delivered | E47: regular | I47: 625 | J47: 27 | K47: 0 | L47: 0 | M47: 0 | N47: 652 | O47: 32.6 | P47: 684.6 | Q47: 684.6 | R47: 20.0% | S47: 136.92 | T47: 0 | U47: 0 | V47: 0 | W47: 0 | X47: 0 | Y47: 0 | Z47: 0 | AA47: 0 | AB47: 0 | AC47: 24.64 | AD47: 161.56 | AE47: 0 | AF47: 0 | AG47: 0 | AH47: 32.6 | AI47: 0 | AJ47: 0.65 | AK47: 33.25 | AL47: 489.77 | AM47: No | AN47: 3.557 | AO47: Yes | AP47: No | AR47: 206500dc-ba9e-4a58-be62-bb3f830ec1f3 | AS47: No | AW47: Yes | AX47: No
A48: 215684728622662 | C48: 2025-09-01 13:55:28 | D48: delivered | E48: regular | I48: 1145 | J48: 40 | K48: 0 | L48: 0 | M48: 0 | N48: 1185 | O48: 59.26 | P48: 1244.26 | Q48: 1244.24 | R48: 16.0% | S48: 199.08 | T48: 0 | U48: 0 | V48: 0 | W48: 0 | X48: 0 | Y48: 0 | Z48: 0 | AA48: 0 | AB48: 0 | AC48: 35.84 | AD48: 234.92 | AE48: 0 | AF48: 0 | AG48: 0 | AH48: 59.25 | AI48: 0 | AJ48: 1.19 | AK48: 60.44 | AL48: 948.91 | AM48: No | AN48: 3.415 | AO48: Yes | AP48: No | AR48: 206500dc-ba9e-4a58-be62-bb3f830ec1f3 | AS48: No | AW48: Yes | AX48: No
A49: 215684815435477 | C49: 2025-09-01 13:56:55 | D49: delivered | E49: regular | H49: MISSEDYOU | I49: 375 | J49: 15 | K49: 64 | L49: 0 | M49: 64 | N49: 326 | O49: 16.3 | P49: 342.3 | Q49: 342.3 | R49: 22.0% | S49: 75.31 | T49: 7 | U49: 0 | V49: 0 | W49: 0 | X49: 0 | Y49: 0 | Z49: 0 | AA49: 0 | AB49: 0 | AC49: 14.82 | AD49: 97.13 | AE49: 0 | AF49: 0 | AG49: 0 | AH49: 16.3 | AI49: 0 | AJ49: 0.33 | AK49: 16.63 | AL49: 228.55 | AM49: Yes | AN49: 6.72 | AO49: Yes | AP49: No | AR49: 206500dc-ba9e-4a58-be62-bb3f830ec1f3,206500dc-ba9e-4a58-be62-bb3f830ec1f3 | AS49: No | AW49: Yes | AX49: No
A50: 215684907850997 | C50: 2025-09-01 13:58:27 | D50: delivered | E50: regular | H50: SWIGGYIT | I50: 375 | J50: 15 | K50: 64 | L50: 0 | M50: 64 | N50: 326 | O50: 16.3 | P50: 342.3 | Q50: 342.3 | R50: 22.0% | S50: 75.31 | T50: 0 | U50: 0 | V50: 0 | W50: 0 | X50: 0 | Y50: 0 | Z50: 0 | AA50: 0 | AB50: 0 | AC50: 13.56 | AD50: 88.87 | AE50: 0 | AF50: 0 | AG50: 0 | AH50: 16.3 | AI50: 0 | AJ50: 0.33 | AK50: 16.63 | AL50: 236.81 | AM50: No | AN50: 2.768 | AO50: Yes | AP50: No | AR50: 206500dc-ba9e-4a58-be62-bb3f830ec1f3,206500dc-ba9e-4a58-be62-bb3f830ec1f3 | AS50: No | AW50: Yes | AX50: No
A51: 215685618796938 | C51: 2025-09-01 14:10:18 | D51: delivered | E51: regular | H51: FLAVORFUL | I51: 870 | J51: 30 | K51: 99.99 | L51: 0 | M51: 99.99 | N51: 800.01 | O51: 40 | P51: 840.008 | Q51: 840.01 | R51: 20.0% | S51: 168 | T51: 7 | U51: 0 | V51: 0 | W51: 0 | X51: 0 | Y51: 0 | Z51: 0 | AA51: 0 | AB51: 0 | AC51: 31.5 | AD51: 206.5 | AE51: 0 | AF51: 0 | AG51: 0 | AH51: 40 | AI51: 0 | AJ51: 0.8 | AK51: 40.8 | AL51: 592.71 | AM51: Yes | AN51: 7.667 | AO51: Yes | AP51: No | AR51: 564212ca-80fb-49c7-b365-ac0f010102de,564212ca-80fb-49c7-b365-ac0f010102de | AS51: No | AW51: Yes | AX51: No
A52: 215685636819399 | C52: 2025-09-01 14:10:36 | D52: delivered | E52: regular | H52: PARTY | I52: 1565 | J52: 55 | K52: 156.5 | L52: 0 | M52: 156.5 | N52: 1463.5 | O52: 73.18 | P52: 1536.68 | Q52: 1536.68 | R52: 14.0% | S52: 215.14 | T52: 7 | U52: 0 | V52: 0 | W52: 0 | X52: 0 | Y52: 0 | Z52: 0 | AA52: 0 | AB52: 0 | AC52: 39.98 | AD52: 262.12 | AE52: 0 | AF52: 0 | AG52: 0 | AH52: 73.17 | AI52: 0 | AJ52: 1.46 | AK52: 74.63 | AL52: 1199.91 | AM52: Yes | AN52: 6.409 | AO52: Yes | AP52: No | AR52: 3798b377-5b2f-42d4-92e5-f8db02853c33,206500dc-ba9e-4a58-be62-bb3f830ec1f3,3798b377-5b2f-42d4-92e5-f8db02853c33,206500dc-ba9e-4a58-be62-bb3f830ec1f3 | AS52: No | AW52: Yes | AX52: No
A53: 215685823863787 | C53: 2025-09-01 14:13:43 | D53: delivered | E53: regular | H53: FLAVORFUL | I53: 1250 | J53: 58 | K53: 100 | L53: 0 | M53: 100 | N53: 1208 | O53: 60.4 | P53: 1268.4 | Q53: 1268.4 | R53: 16.0% | S53: 202.94 | T53: 7 | U53: 0 | V53: 0 | W53: 0 | X53: 0 | Y53: 0 | Z53: 0 | AA53: 0 | AB53: 0 | AC53: 37.78 | AD53: 247.72 | AE53: 0 | AF53: 0 | AG53: 0 | AH53: 60.4 | AI53: 0 | AJ53: 1.21 | AK53: 61.61 | AL53: 959.05 | AM53: Yes | AN53: 7.015 | AO53: Yes | AP53: No | AR53: 206500dc-ba9e-4a58-be62-bb3f830ec1f3,206500dc-ba9e-4a58-be62-bb3f830ec1f3 | AS53: No | AW53: Yes | AX53: No
A54: 215685835297528 | C54: 2025-09-01 14:13:55 | D54: delivered | E54: regular | I54: 1365 | J54: 50 | K54: 0 | L54: 0 | M54: 0 | N54: 1415 | O54: 70.76 | P54: 1485.76 | Q54: 1485.76 | R54: 14.0% | S54: 208.01 | T54: 0 | U54: 0 | V54: 0 | W54: 0 | X54: 0 | Y54: 0 | Z54: 0 | AA54: 0 | AB54: 0 | AC54: 37.44 | AD54: 245.45 | AE54: 0 | AF54: 0 | AG54: 0 | AH54: 70.75 | AI54: 0 | AJ54: 1.42 | AK54: 72.17 | AL54: 1168.13 | AM54: No | AN54: 4.281 | AO54: Yes | AP54: No | AR54: 153b8f73-eef8-4800-a399-6e532c1bda24 | AS54: No | AW54: No | AX54: No
A55: 215685997129351 | C55: 2025-09-01 14:16:37 | D55: delivered | E55: regular | I55: 345 | J55: 15 | K55: 0 | L55: 0 | M55: 0 | N55: 360 | O55: 18 | P55: 378 | Q55: 378 | R55: 22.0% | S55: 83.16 | T55: 0 | U55: 0 | V55: 0 | W55: 0 | X55: 0 | Y55: 0 | Z55: 0 | AA55: 0 | AB55: 0 | AC55: 14.96 | AD55: 98.12 | AE55: 0 | AF55: 0 | AG55: 0 | AH55: 18 | AI55: 0 | AJ55: 0.36 | AK55: 18.36 | AL55: 261.5 | AM55: No | AN55: 2.211 | AO55: Yes | AP55: No | AR55: cd8e96af-c10d-4ef3-bd5c-810d79dfe252,206500dc-ba9e-4a58-be62-bb3f830ec1f3 | AS55: No | AW55: Yes | AX55: No
A56: 215686226395280 | C56: 2025-09-01 14:20:26 | D56: delivered | E56: regular | H56: TRYNEW | I56: 295 | J56: 15 | K56: 64 | L56: 0 | M56: 64 | N56: 246 | O56: 12.3 | P56: 258.3 | Q56: 258.3 | R56: 22.0% | S56: 56.83 | T56: 0 | U56: 0 | V56: 0 | W56: 0 | X56: 0 | Y56: 0 | Z56: 0 | AA56: 0 | AB56: 0 | AC56: 10.22 | AD56: 67.05 | AE56: 0 | AF56: 0 | AG56: 0 | AH56: 12.3 | AI56: 0 | AJ56: 0.25 | AK56: 12.55 | AL56: 178.68 | AM56: No | AN56: 2.176 | AO56: Yes | AP56: No | AR56: 206500dc-ba9e-4a58-be62-bb3f830ec1f3,206500dc-ba9e-4a58-be62-bb3f830ec1f3 | AS56: No | AW56: Yes | AX56: No
A57: 215686387231763 | C57: 2025-09-01 14:23:07 | D57: delivered | E57: regular | H57: MISSEDYOU | I57: 545 | J57: 20 | K57: 64 | L57: 0 | M57: 64 | N57: 501 | O57: 25.06 | P57: 526.06 | Q57: 526.06 | R57: 20.0% | S57: 105.21 | T57: 0 | U57: 0 | V57: 0 | W57: 0 | X57: 0 | Y57: 0 | Z57: 0 | AA57: 0 | AB57: 0 | AC57: 18.94 | AD57: 124.15 | AE57: 0 | AF57: 0 | AG57: 0 | AH57: 25.05 | AI57: 0 | AJ57: 0.5 | AK57: 25.55 | AL57: 376.35 | AM57: No | AN57: 4.49 | AO57: Yes | AP57: No | AR57: 206500dc-ba9e-4a58-be62-bb3f830ec1f3,206500dc-ba9e-4a58-be62-bb3f830ec1f3 | AS57: No | AW57: Yes | AX57: No
A58: 215686788158128 | C58: 2025-09-01 14:29:48 | D58: delivered | E58: regular | H58: PARTY | I58: 1415 | J58: 66 | K58: 141.5 | L58: 0 | M58: 141.5 | N58: 1339.5 | O58: 66.98 | P58: 1406.48 | Q58: 1406.48 | R58: 14.0% | S58: 196.91 | T58: 0 | U58: 0 | V58: 0 | W58: 0 | X58: 0 | Y58: 0 | Z58: 0 | AA58: 0 | AB58: 0 | AC58: 35.44 | AD58: 232.35 | AE58: 0 | AF58: 0 | AG58: 0 | AH58: 66.97 | AI58: 0 | AJ58: 1.34 | AK58: 68.31 | AL58: 1105.8 | AM58: No | AN58: 4.23 | AO58: Yes | AP58: No | AR58: 751ca523-f256-4b1e-b5d3-d1fe8bc09fce,206500dc-ba9e-4a58-be62-bb3f830ec1f3,751ca523-f256-4b1e-b5d3-d1fe8bc09fce,206500dc-ba9e-4a58-be62-bb3f830ec1f3 | AS58: No | AW58: Yes | AX58: No
A59: 215686870165597 | C59: 2025-09-01 14:31:10 | D59: delivered | E59: regular | I59: 445 | J59: 15 | K59: 0 | L59: 0 | M59: 0 | N59: 460 | O59: 23 | P59: 483 | Q59: 483 | R59: 22.0% | S59: 106.26 | T59: 7 | U59: 0 | V59: 0 | W59: 0 | X59: 0 | Y59: 0 | Z59: 0 | AA59: 0 | AB59: 0 | AC59: 20.38 | AD59: 133.64 | AE59: 0 | AF59: 0 | AG59: 0 | AH59: 23 | AI59: 0 | AJ59: 0.46 | AK59: 23.46 | AL59: 325.88 | AM59: Yes | AN59: 6.409 | AO59: Yes | AP59: No | AR59: 206500dc-ba9e-4a58-be62-bb3f830ec1f3 | AS59: No | AW59: Yes | AX59: No
A60: 215688236720550 | C60: 2025-09-01 14:53:56 | D60: delivered | E60: regular | H60: TRYNEW | I60: 345 | J60: 15 | K60: 64 | L60: 0 | M60: 64 | N60: 296 | O60: 14.8 | P60: 310.8 | Q60: 310.8 | R60: 22.0% | S60: 68.38 | T60: 0 | U60: 0 | V60: 0 | W60: 0 | X60: 0 | Y60: 0 | Z60: 0 | AA60: 0 | AB60: 0 | AC60: 12.3 | AD60: 80.68 | AE60: 0 | AF60: 0 | AG60: 0 | AH60: 14.8 | AI60: 0 | AJ60: 0.3 | AK60: 15.1 | AL60: 215.01 | AM60: No | AN60: 4.39 | AO60: Yes | AP60: No | AR60: 100833489 | AS60: No | AW60: No | AX60: No
A61: 215688830144331 | C61: 2025-09-01 15:03:50 | D61: delivered | E61: regular | H61: SWIGGYIT | I61: 295 | J61: 15 | K61: 64 | L61: 0 | M61: 64 | N61: 246 | O61: 12.3 | P61: 258.3 | Q61: 258.3 | R61: 22.0% | S61: 56.83 | T61: 7 | U61: 0 | V61: 0 | W61: 0 | X61: 0 | Y61: 0 | Z61: 0 | AA61: 0 | AB61: 0 | AC61: 11.48 | AD61: 75.31 | AE61: 0 | AF61: 0 | AG61: 0 | AH61: 12.3 | AI61: 0 | AJ61: 0.25 | AK61: 12.55 | AL61: 170.42 | AM61: Yes | AN61: 6.691 | AO61: Yes | AP61: No | AR61: 206500dc-ba9e-4a58-be62-bb3f830ec1f3,206500dc-ba9e-4a58-be62-bb3f830ec1f3 | AS61: No | AW61: Yes | AX61: No
A62: 215689816015497 | C62: 2025-09-01 15:20:16 | D62: delivered | E62: regular | H62: SWIGGYIT | I62: 425 | J62: 15 | K62: 64 | L62: 0 | M62: 64 | N62: 376 | O62: 18.8 | P62: 394.8 | Q62: 394.8 | R62: 22.0% | S62: 86.86 | T62: 0 | U62: 0 | V62: 0 | W62: 0 | X62: 0 | Y62: 0 | Z62: 0 | AA62: 0 | AB62: 0 | AC62: 15.64 | AD62: 102.5 | AE62: 0 | AF62: 0 | AG62: 0 | AH62: 18.8 | AI62: 0 | AJ62: 0.38 | AK62: 19.18 | AL62: 273.14 | AM62: No | AN62: 2.244 | AO62: Yes | AP62: No | AR62: 206500dc-ba9e-4a58-be62-bb3f830ec1f3,206500dc-ba9e-4a58-be62-bb3f830ec1f3 | AS62: No | AW62: Yes | AX62: No
A63: 215692107958383 | C63: 2025-09-01 15:58:27 | D63: delivered | E63: regular | H63: SWIGGYIT | I63: 375 | J63: 15 | K63: 64 | L63: 0 | M63: 64 | N63: 326 | O63: 16.3 | P63: 342.3 | Q63: 342.3 | R63: 22.0% | S63: 75.31 | T63: 0 | U63: 0 | V63: 0 | W63: 0 | X63: 0 | Y63: 0 | Z63: 0 | AA63: 0 | AB63: 0 | AC63: 13.56 | AD63: 88.87 | AE63: 0 | AF63: 0 | AG63: 0 | AH63: 16.3 | AI63: 0 | AJ63: 0.33 | AK63: 16.63 | AL63: 236.81 | AM63: No | AN63: 2.449 | AO63: Yes | AP63: No | AR63: 206500dc-ba9e-4a58-be62-bb3f830ec1f3,206500dc-ba9e-4a58-be62-bb3f830ec1f3 | AS63: No | AW63: Yes | AX63: No
A64: 215692157724515 | C64: 2025-09-01 15:59:17 | D64: delivered | E64: regular | H64: FLAVORFUL | I64: 1140 | J64: 35 | K64: 99.99 | L64: 0 | M64: 99.99 | N64: 1075.01 | O64: 53.76 | P64: 1128.768 | Q64: 1128.77 | R64: 16.0% | S64: 180.6 | T64: 0 | U64: 0 | V64: 0 | W64: 0 | X64: 0 | Y64: 0 | Z64: 0 | AA64: 0 | AB64: 0 | AC64: 32.5 | AD64: 213.1 | AE64: 0 | AF64: 0 | AG64: 0 | AH64: 53.75 | AI64: 0 | AJ64: 1.08 | AK64: 54.83 | AL64: 860.82 | AM64: No | AN64: 3.989 | AO64: Yes | AP64: No | AR64: df730911-9d6e-45a7-a2a2-390df1bc81bd,206500dc-ba9e-4a58-be62-bb3f830ec1f3,df730911-9d6e-45a7-a2a2-390df1bc81bd,206500dc-ba9e-4a58-be62-bb3f830ec1f3 | AS64: No | AW64: Yes | AX64: No
A65: 215692490057460 | C65: 2025-09-01 16:04:50 | D65: delivered | E65: regular | H65: SWIGGYIT | I65: 375 | J65: 15 | K65: 64 | L65: 0 | M65: 64 | N65: 326 | O65: 16.3 | P65: 342.3 | Q65: 342.3 | R65: 22.0% | S65: 75.31 | T65: 7 | U65: 0 | V65: 0 | W65: 0 | X65: 0 | Y65: 0 | Z65: 0 | AA65: 0 | AB65: 0 | AC65: 14.82 | AD65: 97.13 | AE65: 0 | AF65: 0 | AG65: 0 | AH65: 16.3 | AI65: 0 | AJ65: 0.33 | AK65: 16.63 | AL65: 228.55 | AM65: Yes | AN65: 6.499 | AO65: Yes | AP65: No | AR65: 206500dc-ba9e-4a58-be62-bb3f830ec1f3,206500dc-ba9e-4a58-be62-bb3f830ec1f3 | AS65: No | AW65: Yes | AX65: No
A66: 215692755419411 | C66: 2025-09-01 16:09:15 | D66: delivered | E66: regular | H66: ORDERON | I66: 495 | J66: 15 | K66: 64 | L66: 0 | M66: 64 | N66: 446 | O66: 22.3 | P66: 468.3 | Q66: 468.3 | R66: 22.0% | S66: 103.03 | T66: 0 | U66: 0 | V66: 0 | W66: 0 | X66: 0 | Y66: 0 | Z66: 0 | AA66: 0 | AB66: 0 | AC66: 18.54 | AD66: 121.57 | AE66: 0 | AF66: 0 | AG66: 0 | AH66: 22.3 | AI66: 0 | AJ66: 0.45 | AK66: 22.75 | AL66: 323.97 | AM66: No | AN66: 4.222 | AO66: Yes | AP66: No | AQ66: SWIGGYIT | AR66: 206500dc-ba9e-4a58-be62-bb3f830ec1f3,206500dc-ba9e-4a58-be62-bb3f830ec1f3 | AS66: No | AW66: Yes | AX66: No
A67: 215693405556021 | C67: 2025-09-01 16:20:05 | D67: delivered | E67: regular | H67: ORDERON | I67: 495 | J67: 15 | K67: 64 | L67: 0 | M67: 64 | N67: 446 | O67: 22.3 | P67: 468.3 | Q67: 468.3 | R67: 22.0% | S67: 103.03 | T67: 0 | U67: 0 | V67: 0 | W67: 0 | X67: 0 | Y67: 0 | Z67: 0 | AA67: 0 | AB67: 0 | AC67: 18.54 | AD67: 121.57 | AE67: 0 | AF67: 0 | AG67: 0 | AH67: 22.3 | AI67: 0 | AJ67: 0.45 | AK67: 22.75 | AL67: 323.97 | AM67: No | AN67: 5.833 | AO67: Yes | AP67: No | AQ67: MISSEDYOU | AR67: 206500dc-ba9e-4a58-be62-bb3f830ec1f3,206500dc-ba9e-4a58-be62-bb3f830ec1f3 | AS67: No | AW67: Yes | AX67: No
A68: 215693936685167 | C68: 2025-09-01 16:28:56 | D68: delivered | E68: regular | H68: TRYNEW | I68: 275 | J68: 10 | K68: 64 | L68: 0 | M68: 64 | N68: 221 | O68: 11.06 | P68: 232.06 | Q68: 232.06 | R68: 22.0% | S68: 51.05 | T68: 0 | U68: 0 | V68: 0 | W68: 0 | X68: 0 | Y68: 0 | Z68: 0 | AA68: 0 | AB68: 0 | AC68: 9.18 | AD68: 60.23 | AE68: 0 | AF68: 0 | AG68: 0 | AH68: 11.05 | AI68: 0 | AJ68: 0.22 | AK68: 11.27 | AL68: 160.53 | AM68: No | AN68: 2.351 | AO68: Yes | AP68: No | AR68: 206500dc-ba9e-4a58-be62-bb3f830ec1f3,206500dc-ba9e-4a58-be62-bb3f830ec1f3 | AS68: No | AW68: Yes | AX68: No
A69: 215694472577355 | C69: 2025-09-01 16:37:52 | D69: delivered | E69: regular | H69: SWIGGYIT | I69: 445 | J69: 15 | K69: 64 | L69: 0 | M69: 64 | N69: 396 | O69: 19.8 | P69: 415.8 | Q69: 415.8 | R69: 22.0% | S69: 91.48 | T69: 0 | U69: 0 | V69: 0 | W69: 0 | X69: 0 | Y69: 0 | Z69: 0 | AA69: 0 | AB69: 0 | AC69: 16.46 | AD69: 107.94 | AE69: 0 | AF69: 0 | AG69: 0 | AH69: 19.8 | AI69: 0 | AJ69: 0.4 | AK69: 20.2 | AL69: 287.65 | AM69: No | AN69: 3.099 | AO69: Yes | AP69: No | AR69: 51fbbd5a-16ac-44d7-8a39-2e8817ba773c,206500dc-ba9e-4a58-be62-bb3f830ec1f3,51fbbd5a-16ac-44d7-8a39-2e8817ba773c,206500dc-ba9e-4a58-be62-bb3f830ec1f3 | AS69: No | AW69: Yes | AX69: No
A70: 215694888110491 | C70: 2025-09-01 16:44:48 | D70: delivered | E70: regular | H70: PARTY | I70: 2625 | J70: 85 | K70: 262.5 | L70: 0 | M70: 262.5 | N70: 2447.5 | O70: 122.38 | P70: 2569.88 | Q70: 2569.88 | R70: 12.0% | S70: 308.39 | T70: 0 | U70: 0 | V70: 0 | W70: 0 | X70: 0 | Y70: 0 | Z70: 0 | AA70: 0 | AB70: 0 | AC70: 55.52 | AD70: 363.91 | AE70: 0 | AF70: 0 | AG70: 0 | AH70: 122.38 | AI70: 0 | AJ70: 2.45 | AK70: 124.83 | AL70: 2081.16 | AM70: No | AN70: 4.727 | AO70: Yes | AP70: No | AR70: 206500dc-ba9e-4a58-be62-bb3f830ec1f3,206500dc-ba9e-4a58-be62-bb3f830ec1f3 | AS70: No | AW70: Yes | AX70: No
A71: 215694979464744 | C71: 2025-09-01 16:46:19 | D71: delivered | E71: regular | H71: FLAVORFUL | I71: 720 | J71: 25 | K71: 99.99 | L71: 0 | M71: 99.99 | N71: 645.01 | O71: 32.26 | P71: 677.268 | Q71: 677.27 | R71: 20.0% | S71: 135.45 | T71: 0 | U71: 0 | V71: 0 | W71: 0 | X71: 0 | Y71: 0 | Z71: 0 | AA71: 0 | AB71: 0 | AC71: 24.38 | AD71: 159.83 | AE71: 0 | AF71: 0 | AG71: 0 | AH71: 32.25 | AI71: 0 | AJ71: 0.65 | AK71: 32.9 | AL71: 484.53 | AM71: No | AN71: 2.741 | AO71: Yes | AP71: No | AR71: 206500dc-ba9e-4a58-be62-bb3f830ec1f3,206500dc-ba9e-4a58-be62-bb3f830ec1f3 | AS71: No | AW71: Yes | AX71: No
A72: 215695977142284 | C72: 2025-09-01 17:02:57 | D72: delivered | E72: regular | H72: MISSEDYOU | I72: 345 | J72: 15 | K72: 64 | L72: 0 | M72: 64 | N72: 296 | O72: 14.8 | P72: 310.8 | Q72: 310.8 | R72: 22.0% | S72: 68.38 | T72: 0 | U72: 0 | V72: 0 | W72: 0 | X72: 0 | Y72: 0 | Z72: 0 | AA72: 0 | AB72: 0 | AC72: 12.3 | AD72: 80.68 | AE72: 0 | AF72: 0 | AG72: 0 | AH72: 14.8 | AI72: 0 | AJ72: 0.3 | AK72: 15.1 | AL72: 215.01 | AM72: No | AN72: 5.975 | AO72: Yes | AP72: No | AR72: 206500dc-ba9e-4a58-be62-bb3f830ec1f3,206500dc-ba9e-4a58-be62-bb3f830ec1f3 | AS72: No | AW72: Yes | AX72: No
A73: 215695998230961 | C73: 2025-09-01 17:03:18 | D73: delivered | E73: regular | H73: MISSEDYOU | I73: 295 | J73: 15 | K73: 64 | L73: 0 | M73: 64 | N73: 246 | O73: 12.3 | P73: 258.3 | Q73: 258.3 | R73: 22.0% | S73: 56.83 | T73: 0 | U73: 0 | V73: 0 | W73: 0 | X73: 0 | Y73: 0 | Z73: 0 | AA73: 0 | AB73: 0 | AC73: 10.22 | AD73: 67.05 | AE73: 0 | AF73: 0 | AG73: 0 | AH73: 12.3 | AI73: 0 | AJ73: 0.25 | AK73: 12.55 | AL73: 178.68 | AM73: No | AN73: 2.341 | AO73: Yes | AP73: No | AR73: 206500dc-ba9e-4a58-be62-bb3f830ec1f3,206500dc-ba9e-4a58-be62-bb3f830ec1f3 | AS73: No | AW73: Yes | AX73: No
A74: 215696207764528 | C74: 2025-09-01 17:06:47 | D74: delivered | E74: regular | H74: SWIGGYIT | I74: 275 | J74: 10 | K74: 64 | L74: 0 | M74: 64 | N74: 221 | O74: 11.06 | P74: 232.06 | Q74: 232.06 | R74: 22.0% | S74: 51.05 | T74: 30 | U74: 0 | V74: 0 | W74: 0 | X74: 0 | Y74: 0 | Z74: 0 | AA74: 0 | AB74: 0 | AC74: 14.58 | AD74: 95.63 | AE74: 0 | AF74: 0 | AG74: 0 | AH74: 11.05 | AI74: 0 | AJ74: 0.22 | AK74: 11.27 | AL74: 125.13 | AM74: Yes | AN74: 14.135 | AO74: Yes | AP74: No | AR74: 100833489 | AS74: No | AW74: Yes | AX74: No
A75: 215696373621868 | C75: 2025-09-01 17:09:33 | D75: delivered | E75: regular | H75: SWIGGYIT | I75: 375 | J75: 15 | K75: 64 | L75: 0 | M75: 64 | N75: 326 | O75: 16.3 | P75: 342.3 | Q75: 342.3 | R75: 22.0% | S75: 75.31 | T75: 12 | U75: 0 | V75: 0 | W75: 0 | X75: 0 | Y75: 0 | Z75: 0 | AA75: 0 | AB75: 0 | AC75: 15.72 | AD75: 103.03 | AE75: 0 | AF75: 0 | AG75: 0 | AH75: 16.3 | AI75: 0 | AJ75: 0.33 | AK75: 16.63 | AL75: 222.65 | AM75: Yes | AN75: 8.672 | AO75: Yes | AP75: No | AR75: 100833489 | AS75: No | AW75: Yes | AX75: No
A76: 215696811939300 | C76: 2025-09-01 17:16:51 | D76: delivered | E76: regular | I76: 850 | J76: 30 | K76: 0 | L76: 0 | M76: 0 | N76: 880 | O76: 44 | P76: 924 | Q76: 924 | R76: 16.0% | S76: 147.84 | T76: 0 | U76: 0 | V76: 0 | W76: 0 | X76: 0 | Y76: 0 | Z76: 0 | AA76: 0 | AB76: 0 | AC76: 26.62 | AD76: 174.46 | AE76: 0 | AF76: 0 | AG76: 0 | AH76: 44 | AI76: 0 | AJ76: 0.88 | AK76: 44.88 | AL76: 704.68 | AM76: No | AN76: 4.82 | AO76: Yes | AP76: No | AS76: No | AW76: No | AX76: No
A77: 215697035612170 | C77: 2025-09-01 17:20:35 | D77: delivered | E77: regular | H77: TRYNEW | I77: 295 | J77: 15 | K77: 64 | L77: 0 | M77: 64 | N77: 246 | O77: 12.3 | P77: 258.3 | Q77: 258.3 | R77: 22.0% | S77: 56.83 | T77: 0 | U77: 0 | V77: 0 | W77: 0 | X77: 0 | Y77: 0 | Z77: 0 | AA77: 0 | AB77: 0 | AC77: 10.22 | AD77: 67.05 | AE77: 0 | AF77: 0 | AG77: 0 | AH77: 12.3 | AI77: 0 | AJ77: 0.25 | AK77: 12.55 | AL77: 178.68 | AM77: No | AN77: 1.659 | AO77: Yes | AP77: No | AR77: 13dc3f91-8171-4d92-8f62-99875d62318b,13dc3f91-8171-4d92-8f62-99875d62318b | AS77: No | AW77: Yes | AX77: No
A78: 215697337583959 | C78: 2025-09-01 17:25:37 | D78: delivered | E78: regular | H78: ORDERON | I78: 475 | J78: 15 | K78: 64 | L78: 0 | M78: 64 | N78: 426 | O78: 21.3 | P78: 447.3 | Q78: 447.3 | R78: 22.0% | S78: 98.41 | T78: 7 | U78: 0 | V78: 0 | W78: 0 | X78: 0 | Y78: 0 | Z78: 0 | AA78: 0 | AB78: 0 | AC78: 18.98 | AD78: 124.39 | AE78: 0 | AF78: 0 | AG78: 0 | AH78: 21.3 | AI78: 0 | AJ78: 0.43 | AK78: 21.73 | AL78: 301.2 | AM78: Yes | AN78: 6.779 | AO78: Yes | AP78: No | AQ78: SWIGGYIT | AR78: 526ebf5e-3297-4a2d-a9bf-24774b182fa0,206500dc-ba9e-4a58-be62-bb3f830ec1f3,526ebf5e-3297-4a2d-a9bf-24774b182fa0,206500dc-ba9e-4a58-be62-bb3f830ec1f3 | AS78: No | AW78: Yes | AX78: No
A79: 215697943157788 | C79: 2025-09-01 17:35:43 | D79: delivered | E79: regular | H79: SWIGGYIT | I79: 645 | J79: 20 | K79: 64 | L79: 0 | M79: 64 | N79: 601 | O79: 30.06 | P79: 631.06 | Q79: 631.06 | R79: 20.0% | S79: 126.21 | T79: 0 | U79: 0 | V79: 0 | W79: 0 | X79: 0 | Y79: 0 | Z79: 0 | AA79: 0 | AB79: 0 | AC79: 22.72 | AD79: 148.93 | AE79: 0 | AF79: 0 | AG79: 0 | AH79: 30.05 | AI79: 0 | AJ79: 0.6 | AK79: 30.65 | AL79: 451.47 | AM79: No | AN79: 2.741 | AO79: Yes | AP79: No | AR79: 21e51313-2fc5-43ae-b291-6bf8df17bb71,206500dc-ba9e-4a58-be62-bb3f830ec1f3,21e51313-2fc5-43ae-b291-6bf8df17bb71,206500dc-ba9e-4a58-be62-bb3f830ec1f3 | AS79: No | AW79: Yes | AX79: No
A80: 215697960220752 | C80: 2025-09-01 17:36:00 | D80: delivered | E80: regular | H80: TRYNEW | I80: 375 | J80: 15 | K80: 64 | L80: 0 | M80: 64 | N80: 326 | O80: 16.3 | P80: 342.3 | Q80: 342.3 | R80: 22.0% | S80: 75.31 | T80: 0 | U80: 0 | V80: 0 | W80: 0 | X80: 0 | Y80: 0 | Z80: 0 | AA80: 0 | AB80: 0 | AC80: 13.56 | AD80: 88.87 | AE80: 0 | AF80: 0 | AG80: 0 | AH80: 16.3 | AI80: 0 | AJ80: 0.33 | AK80: 16.63 | AL80: 236.81 | AM80: No | AN80: 4.36 | AO80: Yes | AP80: No | AR80: 206500dc-ba9e-4a58-be62-bb3f830ec1f3,206500dc-ba9e-4a58-be62-bb3f830ec1f3 | AS80: No | AW80: Yes | AX80: No
A81: 215699210598511 | C81: 2025-09-01 17:56:50 | D81: delivered | E81: regular | I81: 770 | J81: 30 | K81: 0 | L81: 0 | M81: 0 | N81: 800 | O81: 40 | P81: 840 | Q81: 840 | R81: 20.0% | S81: 168 | T81: 0 | U81: 0 | V81: 0 | W81: 0 | X81: 0 | Y81: 0 | Z81: 0 | AA81: 0 | AB81: 0 | AC81: 30.24 | AD81: 198.24 | AE81: 0 | AF81: 0 | AG81: 0 | AH81: 40 | AI81: 0 | AJ81: 0.8 | AK81: 40.8 | AL81: 600.96 | AM81: No | AN81: 2.785 | AO81: Yes | AP81: No | AR81: 91d421d7-6c8b-48e9-8dc4-197444878a42,206500dc-ba9e-4a58-be62-bb3f830ec1f3 | AS81: No | AW81: Yes | AX81: No
A82: 215699434789030 | C82: 2025-09-01 18:00:34 | D82: delivered | E82: regular | H82: FLAVORFUL | I82: 1070 | J82: 35 | K82: 99.99 | L82: 0 | M82: 99.99 | N82: 1005.01 | O82: 50.26 | P82: 1055.268 | Q82: 1055.27 | R82: 16.0% | S82: 168.84 | T82: 0 | U82: 0 | V82: 0 | W82: 0 | X82: 0 | Y82: 0 | Z82: 0 | AA82: 0 | AB82: 0 | AC82: 30.4 | AD82: 199.24 | AE82: 0 | AF82: 0 | AG82: 0 | AH82: 50.25 | AI82: 0 | AJ82: 1.01 | AK82: 51.26 | AL82: 804.78 | AM82: No | AN82: 4.222 | AO82: Yes | AP82: No | AR82: 206500dc-ba9e-4a58-be62-bb3f830ec1f3,206500dc-ba9e-4a58-be62-bb3f830ec1f3 | AS82: No | AW82: Yes | AX82: No
A83: 215699729592154 | C83: 2025-09-01 18:05:29 | D83: delivered | E83: regular | H83: SWIGGYIT | I83: 670 | J83: 25 | K83: 63.99 | L83: 0 | M83: 63.99 | N83: 631.01 | O83: 31.56 | P83: 662.568 | Q83: 662.57 | R83: 20.0% | S83: 132.51 | T83: 0 | U83: 0 | V83: 0 | W83: 0 | X83: 0 | Y83: 0 | Z83: 0 | AA83: 0 | AB83: 0 | AC83: 23.86 | AD83: 156.37 | AE83: 0 | AF83: 0 | AG83: 0 | AH83: 31.55 | AI83: 0 | AJ83: 0.63 | AK83: 32.18 | AL83: 474.03 | AM83: No | AN83: 3.415 | AO83: Yes | AP83: No | AR83: f79c6b1b-ea67-4db3-b8b5-92621d1803d9,206500dc-ba9e-4a58-be62-bb3f830ec1f3,f79c6b1b-ea67-4db3-b8b5-92621d1803d9,206500dc-ba9e-4a58-be62-bb3f830ec1f3 | AS83: No | AW83: Yes | AX83: No
A84: 215700082657344 | C84: 2025-09-01 18:11:22 | D84: delivered | E84: regular | H84: FLAVORFUL | I84: 890 | J84: 30 | K84: 100 | L84: 0 | M84: 100 | N84: 820 | O84: 41 | P84: 861 | Q84: 861 | R84: 20.0% | S84: 172.2 | T84: 30 | U84: 0 | V84: 0 | W84: 0 | X84: 0 | Y84: 0 | Z84: 0 | AA84: 0 | AB84: 0 | AC84: 36.4 | AD84: 238.6 | AE84: 0 | AF84: 0 | AG84: 0 | AH84: 41 | AI84: 0 | AJ84: 0.82 | AK84: 41.82 | AL84: 580.58 | AM84: Yes | AN84: 15.498 | AO84: Yes | AP84: No | AR84: 103197863 | AS84: No | AW84: No | AX84: No
A85: 215700380175007 | C85: 2025-09-01 18:16:20 | D85: delivered | E85: regular | H85: FLAVORFUL | I85: 720 | J85: 30 | K85: 99.99 | L85: 0 | M85: 99.99 | N85: 650.01 | O85: 32.5 | P85: 682.508 | Q85: 682.51 | R85: 20.0% | S85: 136.5 | T85: 0 | U85: 0 | V85: 0 | W85: 0 | X85: 0 | Y85: 0 | Z85: 0 | AA85: 0 | AB85: 0 | AC85: 24.58 | AD85: 161.08 | AE85: 0 | AF85: 0 | AG85: 0 | AH85: 32.5 | AI85: 0 | AJ85: 0.65 | AK85: 33.15 | AL85: 488.3 | AM85: No | AN85: 3.336 | AO85: Yes | AP85: No | AR85: 206500dc-ba9e-4a58-be62-bb3f830ec1f3,206500dc-ba9e-4a58-be62-bb3f830ec1f3 | AS85: No | AW85: Yes | AX85: No
A86: 215700807998918 | C86: 2025-09-01 18:23:27 | D86: delivered | E86: regular | I86: 555 | J86: 15 | K86: 0 | L86: 0 | M86: 0 | N86: 570 | O86: 28.5 | P86: 598.5 | Q86: 598.5 | R86: 20.0% | S86: 119.7 | T86: 0 | U86: 0 | V86: 0 | W86: 0 | X86: 0 | Y86: 0 | Z86: 0 | AA86: 0 | AB86: 0 | AC86: 21.54 | AD86: 141.24 | AE86: 0 | AF86: 0 | AG86: 0 | AH86: 28.5 | AI86: 0 | AJ86: 0.57 | AK86: 29.07 | AL86: 428.17 | AM86: No | AN86: 4.361 | AO86: Yes | AP86: No | AS86: No | AW86: No | AX86: No
A87: 215701220137835 | C87: 2025-09-01 18:30:20 | D87: delivered | E87: regular | H87: PARTY | I87: 1460 | J87: 55 | K87: 146 | L87: 0 | M87: 146 | N87: 1369 | O87: 68.46 | P87: 1437.46 | Q87: 1437.46 | R87: 14.0% | S87: 201.24 | T87: 30 | U87: 0 | V87: 0 | W87: 0 | X87: 0 | Y87: 0 | Z87: 0 | AA87: 0 | AB87: 0 | AC87: 41.62 | AD87: 272.86 | AE87: 0 | AF87: 0 | AG87: 0 | AH87: 68.45 | AI87: 0 | AJ87: 1.37 | AK87: 69.82 | AL87: 1094.77 | AM87: Yes | AN87: 15.265 | AO87: Yes | AP87: No | AR87: 87080508 | AS87: No | AW87: Yes | AX87: No
A88: 215701727610151 | C88: 2025-09-01 18:38:47 | D88: delivered | E88: regular | H88: FLAVORFUL | I88: 770 | J88: 25 | K88: 99.99 | L88: 0 | M88: 99.99 | N88: 695.01 | O88: 34.76 | P88: 729.768 | Q88: 729.77 | R88: 20.0% | S88: 145.95 | T88: 0 | U88: 0 | V88: 0 | W88: 0 | X88: 0 | Y88: 0 | Z88: 0 | AA88: 0 | AB88: 0 | AC88: 26.28 | AD88: 172.23 | AE88: 0 | AF88: 0 | AG88: 0 | AH88: 34.75 | AI88: 0 | AJ88: 0.7 | AK88: 35.45 | AL88: 522.1 | AM88: No | AN88: 3.989 | AO88: Yes | AP88: No | AR88: 206500dc-ba9e-4a58-be62-bb3f830ec1f3,206500dc-ba9e-4a58-be62-bb3f830ec1f3 | AS88: No | AW88: Yes | AX88: No
A89: 215701919511215 | C89: 2025-09-01 18:41:59 | D89: delivered | E89: regular | H89: SWIGGYIT | I89: 345 | J89: 15 | K89: 64 | L89: 0 | M89: 64 | N89: 296 | O89: 14.8 | P89: 310.8 | Q89: 310.8 | R89: 22.0% | S89: 68.38 | T89: 0 | U89: 0 | V89: 0 | W89: 0 | X89: 0 | Y89: 0 | Z89: 0 | AA89: 0 | AB89: 0 | AC89: 12.3 | AD89: 80.68 | AE89: 0 | AF89: 0 | AG89: 0 | AH89: 14.8 | AI89: 0 | AJ89: 0.3 | AK89: 15.1 | AL89: 215.01 | AM89: No | AN89: 3.989 | AO89: Yes | AP89: No | AR89: 206500dc-ba9e-4a58-be62-bb3f830ec1f3,206500dc-ba9e-4a58-be62-bb3f830ec1f3 | AS89: No | AW89: Yes | AX89: No
A90: 215701982768554 | C90: 2025-09-01 18:43:02 | D90: delivered | E90: regular | H90: PARTY | I90: 1590 | J90: 60 | K90: 159 | L90: 0 | M90: 159 | N90: 1491 | O90: 74.56 | P90: 1565.56 | Q90: 1565.54 | R90: 14.0% | S90: 219.18 | T90: 7 | U90: 0 | V90: 0 | W90: 0 | X90: 0 | Y90: 0 | Z90: 0 | AA90: 0 | AB90: 0 | AC90: 40.72 | AD90: 266.9 | AE90: 0 | AF90: 0 | AG90: 0 | AH90: 74.55 | AI90: 0 | AJ90: 1.49 | AK90: 76.04 | AL90: 1222.63 | AM90: Yes | AN90: 6.699 | AO90: Yes | AP90: No | AR90: 206500dc-ba9e-4a58-be62-bb3f830ec1f3,206500dc-ba9e-4a58-be62-bb3f830ec1f3 | AS90: No | AW90: Yes | AX90: No
A91: 215702353466476 | C91: 2025-09-01 18:49:13 | D91: delivered | E91: regular | H91: TRYNEW | I91: 495 | J91: 15 | K91: 64 | L91: 0 | M91: 64 | N91: 446 | O91: 22.3 | P91: 468.3 | Q91: 468.3 | R91: 22.0% | S91: 103.03 | T91: 0 | U91: 0 | V91: 0 | W91: 0 | X91: 0 | Y91: 0 | Z91: 0 | AA91: 0 | AB91: 0 | AC91: 18.54 | AD91: 121.57 | AE91: 0 | AF91: 0 | AG91: 0 | AH91: 22.3 | AI91: 0 | AJ91: 0.45 | AK91: 22.75 | AL91: 323.97 | AM91: No | AN91: 2.901 | AO91: Yes | AP91: No | AR91: a7660225-e158-498b-8e8c-03a1390223e6,a7660225-e158-498b-8e8c-03a1390223e6 | AS91: No | AW91: Yes | AX91: No
A92: 215702359210932 | C92: 2025-09-01 18:49:19 | D92: delivered | E92: regular | H92: FLAVORFUL | I92: 840 | J92: 35 | K92: 99.99 | L92: 0 | M92: 99.99 | N92: 775.01 | O92: 38.76 | P92: 813.768 | Q92: 813.77 | R92: 20.0% | S92: 162.75 | T92: 0 | U92: 0 | V92: 0 | W92: 0 | X92: 0 | Y92: 0 | Z92: 0 | AA92: 0 | AB92: 0 | AC92: 29.3 | AD92: 192.05 | AE92: 0 | AF92: 0 | AG92: 0 | AH92: 38.75 | AI92: 0 | AJ92: 0.78 | AK92: 39.53 | AL92: 582.19 | AM92: No | AN92: 3.989 | AO92: Yes | AP92: No | AR92: 206500dc-ba9e-4a58-be62-bb3f830ec1f3,206500dc-ba9e-4a58-be62-bb3f830ec1f3 | AS92: No | AW92: Yes | AX92: No
A93: 215702596425430 | C93: 2025-09-01 18:53:16 | D93: delivered | E93: regular | H93: ORDERON | I93: 495 | J93: 15 | K93: 64 | L93: 0 | M93: 64 | N93: 446 | O93: 22.3 | P93: 468.3 | Q93: 468.3 | R93: 22.0% | S93: 103.03 | T93: 30 | U93: 0 | V93: 0 | W93: 0 | X93: 0 | Y93: 0 | Z93: 0 | AA93: 0 | AB93: 0 | AC93: 23.94 | AD93: 156.97 | AE93: 0 | AF93: 0 | AG93: 0 | AH93: 22.3 | AI93: 0 | AJ93: 0.45 | AK93: 22.75 | AL93: 288.57 | AM93: Yes | AN93: 15.145 | AO93: Yes | AP93: No | AQ93: TRYNEW | AR93: 100833489 | AS93: No | AW93: Yes | AX93: No
A94: 215702609601558 | C94: 2025-09-01 18:53:29 | D94: delivered | E94: regular | H94: ORDERON | I94: 375 | J94: 15 | K94: 64 | L94: 0 | M94: 64 | N94: 326 | O94: 16.3 | P94: 342.3 | Q94: 342.3 | R94: 22.0% | S94: 75.31 | T94: 30 | U94: 0 | V94: 0 | W94: 0 | X94: 0 | Y94: 0 | Z94: 0 | AA94: 0 | AB94: 0 | AC94: 18.96 | AD94: 124.27 | AE94: 0 | AF94: 0 | AG94: 0 | AH94: 16.3 | AI94: 0 | AJ94: 0.33 | AK94: 16.63 | AL94: 201.41 | AM94: Yes | AN94: 12.51 | AO94: Yes | AP94: No | AQ94: TRYNEW | AR94: 100833489 | AS94: No | AW94: Yes | AX94: No
A95: 215702980863172 | C95: 2025-09-01 18:59:40 | D95: delivered | E95: regular | H95: MISSEDYOU | I95: 275 | J95: 10 | K95: 64 | L95: 0 | M95: 64 | N95: 221 | O95: 11.06 | P95: 232.06 | Q95: 232.06 | R95: 22.0% | S95: 51.05 | T95: 0 | U95: 0 | V95: 0 | W95: 0 | X95: 0 | Y95: 0 | Z95: 0 | AA95: 0 | AB95: 0 | AC95: 9.18 | AD95: 60.23 | AE95: 0 | AF95: 0 | AG95: 0 | AH95: 11.05 | AI95: 0 | AJ95: 0.22 | AK95: 11.27 | AL95: 160.53 | AM95: No | AN95: 4.058 | AO95: Yes | AP95: No | AR95: 100833489 | AS95: No | AW95: No | AX95: No
A96: 215703078033892 | C96: 2025-09-01 19:01:18 | D96: delivered | E96: regular | H96: ORDERON | I96: 445 | J96: 15 | K96: 64 | L96: 0 | M96: 64 | N96: 396 | O96: 19.8 | P96: 415.8 | Q96: 415.8 | R96: 22.0% | S96: 91.48 | T96: 0 | U96: 0 | V96: 0 | W96: 0 | X96: 0 | Y96: 0 | Z96: 0 | AA96: 0 | AB96: 0 | AC96: 16.46 | AD96: 107.94 | AE96: 0 | AF96: 0 | AG96: 0 | AH96: 19.8 | AI96: 0 | AJ96: 0.4 | AK96: 20.2 | AL96: 287.65 | AM96: No | AN96: 4.967 | AO96: Yes | AP96: No | AQ96: SWIGGYIT | AR96: 206500dc-ba9e-4a58-be62-bb3f830ec1f3,206500dc-ba9e-4a58-be62-bb3f830ec1f3 | AS96: No | AW96: Yes | AX96: No
A97: 215703089237638 | C97: 2025-09-01 19:01:29 | D97: delivered | E97: regular | H97: FLAVORFUL | I97: 1120 | J97: 42 | K97: 99.99 | L97: 0 | M97: 99.99 | N97: 1062.01 | O97: 53.1 | P97: 1115.108 | Q97: 1115.11 | R97: 16.0% | S97: 178.42 | T97: 20 | U97: 0 | V97: 0 | W97: 0 | X97: 0 | Y97: 0 | Z97: 0 | AA97: 0 | AB97: 0 | AC97: 35.72 | AD97: 234.14 | AE97: 0 | AF97: 0 | AG97: 0 | AH97: 53.1 | AI97: 0 | AJ97: 1.06 | AK97: 54.16 | AL97: 826.81 | AM97: Yes | AN97: 11.139 | AO97: Yes | AP97: No | AR97: 103197863 | AS97: No | AW97: Yes | AX97: No
A98: 215703230417539 | C98: 2025-09-01 19:03:50 | D98: delivered | E98: regular | H98: PARTY | I98: 1300 | J98: 50 | K98: 129.99 | L98: 0 | M98: 129.99 | N98: 1220.01 | O98: 61 | P98: 1281.01 | Q98: 1281.01 | R98: 16.0% | S98: 204.96 | T98: 0 | U98: 0 | V98: 0 | W98: 0 | X98: 0 | Y98: 0 | Z98: 0 | AA98: 0 | AB98: 0 | AC98: 36.9 | AD98: 241.86 | AE98: 0 | AF98: 0 | AG98: 0 | AH98: 61 | AI98: 0 | AJ98: 1.22 | AK98: 62.22 | AL98: 976.95 | AM98: No | AN98: 5.828 | AO98: Yes | AP98: No | AR98: 206500dc-ba9e-4a58-be62-bb3f830ec1f3,206500dc-ba9e-4a58-be62-bb3f830ec1f3 | AS98: No | AW98: Yes | AX98: No
A99: 215703381628456 | C99: 2025-09-01 19:06:21 | D99: delivered | E99: regular | H99: FLAVORFUL | I99: 740 | J99: 30 | K99: 99.99 | L99: 0 | M99: 99.99 | N99: 670.01 | O99: 33.5 | P99: 703.508 | Q99: 703.51 | R99: 20.0% | S99: 140.7 | T99: 12 | U99: 0 | V99: 0 | W99: 0 | X99: 0 | Y99: 0 | Z99: 0 | AA99: 0 | AB99: 0 | AC99: 27.48 | AD99: 180.18 | AE99: 0 | AF99: 0 | AG99: 0 | AH99: 33.5 | AI99: 0 | AJ99: 0.67 | AK99: 34.17 | AL99: 489.14 | AM99: Yes | AN99: 9.631 | AO99: Yes | AP99: No | AR99: 103197863 | AS99: No | AW99: Yes | AX99: No
A100: 215703554179949 | C100: 2025-09-01 19:09:14 | D100: delivered | E100: regular | H100: ORDERON | I100: 295 | J100: 15 | K100: 64 | L100: 0 | M100: 64 | N100: 246 | O100: 12.3 | P100: 258.3 | Q100: 258.3 | R100: 22.0% | S100: 56.83 | T100: 0 | U100: 0 | V100: 0 | W100: 0 | X100: 0 | Y100: 0 | Z100: 0 | AA100: 0 | AB100: 0 | AC100: 10.22 | AD100: 67.05 | AE100: 0 | AF100: 0 | AG100: 0 | AH100: 12.3 | AI100: 0 | AJ100: 0.25 | AK100: 12.55 | AL100: 178.68 | AM100: No | AN100: 2.398 | AO100: Yes | AP100: No | AQ100: TRYNEW | AR100: 206500dc-ba9e-4a58-be62-bb3f830ec1f3,206500dc-ba9e-4a58-be62-bb3f830ec1f3 | AS100: No | AW100: Yes | AX100: No
A101: 215703735988618 | C101: 2025-09-01 19:12:15 | D101: delivered | E101: regular | H101: PARTY | I101: 1255 | J101: 54 | K101: 125.5 | L101: 0 | M101: 125.5 | N101: 1183.5 | O101: 59.18 | P101: 1242.68 | Q101: 1242.68 | R101: 16.0% | S101: 198.83 | T101: 7 | U101: 0 | V101: 0 | W101: 0 | X101: 0 | Y101: 0 | Z101: 0 | AA101: 0 | AB101: 0 | AC101: 37.04 | AD101: 242.87 | AE101: 0 | AF101: 0 | AG101: 0 | AH101: 59.17 | AI101: 0 | AJ101: 1.18 | AK101: 60.35 | AL101: 939.43 | AM101: Yes | AN101: 6.885 | AO101: Yes | AP101: No | AR101: 206500dc-ba9e-4a58-be62-bb3f830ec1f3,206500dc-ba9e-4a58-be62-bb3f830ec1f3 | AS101: No | AW101: Yes | AX101: No
A102: 215703786074172 | C102: 2025-09-01 19:13:06 | D102: delivered | E102: regular | H102: SWIGGYIT | I102: 245 | J102: 10 | K102: 64 | L102: 0 | M102: 64 | N102: 191 | O102: 9.56 | P102: 200.56 | Q102: 200.56 | R102: 22.0% | S102: 44.12 | T102: 0 | U102: 0 | V102: 0 | W102: 0 | X102: 0 | Y102: 0 | Z102: 0 | AA102: 0 | AB102: 0 | AC102: 7.94 | AD102: 52.06 | AE102: 0 | AF102: 0 | AG102: 0 | AH102: 9.55 | AI102: 0 | AJ102: 0.19 | AK102: 9.74 | AL102: 138.75 | AM102: No | AN102: 3.657 | AO102: Yes | AP102: No | AR102: 206500dc-ba9e-4a58-be62-bb3f830ec1f3,206500dc-ba9e-4a58-be62-bb3f830ec1f3 | AS102: No | AW102: Yes | AX102: No
A103: 215704080611884 | C103: 2025-09-01 19:18:00 | D103: delivered | E103: regular | H103: SWIGGYIT | I103: 445 | J103: 15 | K103: 64 | L103: 0 | M103: 64 | N103: 396 | O103: 19.8 | P103: 415.8 | Q103: 415.8 | R103: 22.0% | S103: 91.48 | T103: 0 | U103: 0 | V103: 0 | W103: 0 | X103: 0 | Y103: 0 | Z103: 0 | AA103: 0 | AB103: 0 | AC103: 16.46 | AD103: 107.94 | AE103: 0 | AF103: 0 | AG103: 0 | AH103: 19.8 | AI103: 0 | AJ103: 0.4 | AK103: 20.2 | AL103: 287.65 | AM103: No | AN103: 3.096 | AO103: Yes | AP103: No | AR103: 913f4cba-09fa-45a8-8de5-041a6e801657,206500dc-ba9e-4a58-be62-bb3f830ec1f3,913f4cba-09fa-45a8-8de5-041a6e801657,206500dc-ba9e-4a58-be62-bb3f830ec1f3 | AS103: No | AW103: Yes | AX103: No
A104: 215704108883058 | C104: 2025-09-01 19:18:28 | D104: delivered | E104: regular | I104: 1525 | J104: 50 | K104: 0 | L104: 0 | M104: 0 | N104: 1575 | O104: 78.76 | P104: 1653.76 | Q104: 1653.76 | R104: 14.0% | S104: 231.53 | T104: 0 | U104: 0 | V104: 0 | W104: 0 | X104: 0 | Y104: 0 | Z104: 0 | AA104: 0 | AB104: 0 | AC104: 41.68 | AD104: 273.21 | AE104: 0 | AF104: 0 | AG104: 0 | AH104: 78.75 | AI104: 0 | AJ104: 1.57 | AK104: 80.32 | AL104: 1300.22 | AM104: No | AN104: 2.741 | AO104: Yes | AP104: No | AR104: 206500dc-ba9e-4a58-be62-bb3f830ec1f3 | AS104: No | AW104: Yes | AX104: No
A105: 215704139049574 | C105: 2025-09-01 19:18:59 | D105: delivered | E105: regular | H105: SWIGGYIT | I105: 525 | J105: 20 | K105: 64 | L105: 0 | M105: 64 | N105: 481 | O105: 24.06 | P105: 505.06 | Q105: 505.06 | R105: 20.0% | S105: 101.01 | T105: 0 | U105: 0 | V105: 0 | W105: 0 | X105: 0 | Y105: 0 | Z105: 0 | AA105: 0 | AB105: 0 | AC105: 18.18 | AD105: 119.19 | AE105: 0 | AF105: 0 | AG105: 0 | AH105: 24.05 | AI105: 0 | AJ105: 0.48 | AK105: 24.53 | AL105: 361.33 | AM105: No | AN105: 2.326 | AO105: Yes | AP105: No | AR105: 206500dc-ba9e-4a58-be62-bb3f830ec1f3,206500dc-ba9e-4a58-be62-bb3f830ec1f3 | AS105: No | AW105: Yes | AX105: No
...

Sheet D2W1
A1: Adjustments this week
A2: Adjustment Type | B2: Total Amount | C2: Settled Amount | D2: Outstanding Amount | E2: Period From | F2: Period To | G2: Invoice Number | H2: Remarks
A3: CPC Ads | B3: ₹-6128.920000000001 | C3: ₹-6128.92 | D3: ₹0.0 | E3: 2025-09-01 | F3: 2025-09-06 | G3: 250910FS36005533 | H3: CPC Ads for service period 01 September 2025 to 06 September 2025
A4: CPC Ads | B4: ₹-7384.440000000001 | C4: ₹-7384.44 | D4: ₹0.0 | E4: 2025-09-01 | F4: 2025-09-06 | G4: 250910FS36005533 | H4: CPC Ads for service period 01 September 2025 to 06 September 2025
A5: CPC Ads | B5: ₹-6574.960000000001 | C5: ₹-6574.96 | D5: ₹0.0 | E5: 2025-09-01 | F5: 2025-09-06 | G5: 250910FS36005533 | H5: CPC Ads for service period 01 September 2025 to 06 September 2025
A6: CPC Ads | B6: ₹-6128.920000000001 | C6: ₹-6128.92 | D6: ₹0.0 | E6: 2025-09-01 | F6: 2025-09-06 | G6: 250910FS36005533 | H6: CPC Ads for service period 01 September 2025 to 06 September 2025
A7: CPC Ads | B7: ₹-6872.320000000001 | C7: ₹-6872.32 | D7: ₹0.0 | E7: 2025-09-01 | F7: 2025-09-06 | G7: 250910FS36005533 | H7: CPC Ads for service period 01 September 2025 to 06 September 2025
A8: CPC Ads | B8: ₹-6574.960000000001 | C8: ₹-6574.96 | D8: ₹0.0 | E8: 2025-09-01 | F8: 2025-09-06 | G8: 250910FS36005533 | H8: CPC Ads for service period 01 September 2025 to 06 September 2025
A10: Adjustments from previous week
A11: Adjusment Type | B11: Total Amount | C11: Settled Amount | D11: Outstanding Amount | E11: Period From | F11: Period To | G11: Invoice Number | H11: Remarks
A13: Total Adjustments | B13: ₹-39664.52 | C13: ₹-39664.52 | D13: ₹0.0

Sheet D1W2
I1: 7905 | J1: 260 | K1: 676.99 | L1: 0 | M1: 676.99 | N1: 7488.01 | O1: 293.7 | P1: 7781.708 | Q1: 4280.282 | R1: 0 | S1: 413.61 | T1: 0 | U1: 0 | V1: 0 | W1: 0 | X1: 0 | Y1: 0 | Z1: 0 | AA1: 0 | AB1: 0 | AC1: 74.46 | AD1: 488.07 | AE1: 3469.09 | AF1: 0 | AG1: 3469.09 | AH1: 205.36 | AI1: 0 | AJ1: 1.94 | AK1: 207.3 | AL1: 3617.21 | AM1: 0 | AN1: 55.996 | AO1: 0 | AP1: 0 | AQ1: 0 | AR1: 0 | AS1: 0 | AT1: 0 | AU1: 387.05 | AV1: 0 | AW1: 0 | AX1: 0 | AY1: 0 | AZ1: 0 | BA1: 0 | BB1: 0 | BC1: 0 | BD1: 0 | BE1: 0 | BF1: 0 | BG1: 0 | BH1: 0 | BI1: 0 | BJ1: 0 | BK1: 0 | BL1: 0 | BM1: 0 | BN1: 0 | BO1: 0 | BP1: 0 | BQ1: 0 | BR1: 0 | BS1: 0 | BT1: 0 | BU1: 0 | BV1: 0 | BW1: 0 | BX1: 0 | BY1: 0 | BZ1: 0 | CA1: 0 | CB1: 0 | CC1: 0
I2: 1061160 | J2: 38491 | K2: 107304.54 | L2: 2104.83 | M2: 109409.37 | N2: 990241.63 | O2: 49515.96 | P2: 1039756.9 | Q2: 1039756.6 | R2: 0 | S2: 182814.11 | T2: 4850 | U2: 0 | V2: 0 | W2: 0 | X2: 0 | Y2: 0 | Z2: 0 | AA2: 0 | AB2: 0 | AC2: 33777.42 | AD2: 221441.53 | AE2: 0 | AF2: 4174 | AG2: 4174 | AH2: 49511.86 | AI2: 0 | AJ2: 992.68 | AK2: 50504.54 | AL2: 763629.92 | AM2: 0 | AN2: 7068.814 | AO2: 0 | AP2: 0 | AQ2: 0 | AR2: 0 | AS2: 0 | AT2: 0 | AU2: 0 | AV2: 0 | AW2: 0 | AX2: 0 | AY2: 0 | AZ2: 0 | BA2: 0 | BB2: 0 | BC2: 0 | BD2: 0 | BE2: 0 | BF2: 0 | BG2: 0 | BH2: 0 | BI2: 0 | BJ2: 0 | BK2: 0 | BL2: 0 | BM2: 0 | BN2: 0 | BO2: 0 | BP2: 0 | BQ2: 0 | BR2: 0 | BS2: 0 | BT2: 0 | BU2: 0 | BV2: 0 | BW2: 0 | BX2: 0 | BY2: 0 | BZ2: 0 | CA2: 0 | CB2: 0 | CC2: 0
I3: 1261496.7 | J3: 45726.18 | K3: 127418.21 | L3: 2483.6994 | M3: 129901.9 | N3: 1177321 | O3: 58775.399 | P3: 1236095.5 | Q3: 1231963.5 | R3: 0 | S3: 216208.71 | T3: 5723 | U3: 0 | V3: 0 | W3: 0 | X3: 0 | Y3: 0 | Z3: 0 | AA3: 0 | AB3: 0 | AC3: 39945.218 | AD3: 261876.93 | AE3: 4093.5262 | AF3: 4925.32 | AG3: 9018.8462 | AH3: 58666.32 | AI3: 0 | AJ3: 1173.6516 | AK3: 59839.971 | AL3: 905351.61 | AM3: 0 | AN3: 8407.2758 | AO3: 0 | AP3: 0 | AQ3: 0 | AR3: 0 | AS3: 0 | AT3: 0 | AU3: 456.719 | AV3: 0 | AW3: 0 | AX3: 0 | AY3: 0 | AZ3: 0 | BA3: 0 | BB3: 0 | BC3: 0 | BD3: 0 | BE3: 0 | BF3: 0 | BG3: 0 | BH3: 0 | BI3: 0 | BJ3: 0 | BK3: 0 | BL3: 0 | BM3: 0 | BN3: 0 | BO3: 0 | BP3: 0 | BQ3: 0 | BR3: 0 | BS3: 0 | BT3: 0 | BU3: 0 | BV3: 0 | BW3: 0 | BX3: 0 | BY3: 0 | BZ3: 0 | CA3: 0 | CB3: 0 | CC3: 0
I4: 1069065 | J4: 38751 | K4: 107981.53 | L4: 2104.83 | M4: 110086.36 | N4: 997729.64 | O4: 49809.66 | P4: 1047538.6 | Q4: 1044036.8 | R4: 0 | S4: 183227.72 | T4: 4850 | U4: 0 | V4: 0 | W4: 0 | X4: 0 | Y4: 0 | Z4: 0 | AA4: 0 | AB4: 0 | AC4: 33851.88 | AD4: 221929.6 | AE4: 3469.09 | AF4: 4174 | AG4: 7643.09 | AH4: 49717.22 | AI4: 0 | AJ4: 994.62 | AK4: 50711.84 | AL4: 767247.13 | AM4: 0 | AN4: 7124.81 | AO4: 0 | AP4: 0 | AQ4: 0 | AR4: 0 | AS4: 0 | AT4: 0 | AU4: 387.05 | AV4: 0 | AW4: 0 | AX4: 0 | AY4: 0 | AZ4: 0 | BA4: 0 | BB4: 0 | BC4: 0 | BD4: 0 | BE4: 0 | BF4: 0 | BG4: 0 | BH4: 0 | BI4: 0 | BJ4: 0 | BK4: 0 | BL4: 0 | BM4: 0 | BN4: 0 | BO4: 0 | BP4: 0 | BQ4: 0 | BR4: 0 | BS4: 0 | BT4: 0 | BU4: 0 | BV4: 0 | BW4: 0 | BX4: 0 | BY4: 0 | BZ4: 0 | CA4: 0 | CB4: 0 | CC4: 0
A5: Order ID | B5: Parent Order ID | C5: Order Date | D5: Order Status | E5: Order Category | F5: Order Payment Type | G5: Cancelled By? | H5: Coupon type applied by customer | I5: Item Total | J5: Packaging Charges | K5: Restaurant Discounts (Promo, Freebies, Flat Off, etc.) | L5: Swiggy One Exclusive Offer Discount | M5: Restaurant Discount Share [3a+3b] | N5: Net Bill Value (before taxes) [1+2-3] | O5: GST Collected | P5: Total Customer Paid [4+5] | Q5: Commission charged on | R5: Service Fees % | S5: Commission | T5: Long Distance Charges | U5: Discount on Long Distance Fee | V5: Pocket Hero Fees | W5: Swiggy One Fees | X5: Payment Collection Charges | Y5: Restaurant Cancellation Charges | Z5: Call Center Charges | AA5: Delivery Fee sponsored by Restaurant (w/o tax) | AB5: Bolt Fees | AC5: GST on Service Fee @18% | AD5: Total Swiggy Fees [6+7+8-9+10+11+12+13+14+15+16] | AE5: Customer Cancellations | AF5: Customer Complaints | AG5: Complaint & Cancellation Charges [17+18] | AH5: GST Deduction | AI5: TCS | AJ5: TDS | AK5: Total Taxes [19+20+21] | AL5: Net Payout for Order (after taxes) [A-B-C-D] | AM5: Long Distance Order | AN5: Last Mile (in km) | AO5: MFR Accurate? | AP5: MFR Pressed? | AQ5: Coupon Code Sourced | AR5: Discount Campaign ID | AS5: Replicated Order | AT5: Base order ID | AU5: Cancellation time | AV5: Pick Up Status | AW5: Swiggy One Customer? | AX5: Pocket Hero Order?
A6: 216195415833927 | C6: 2025-09-07 11:46:55 | D6: delivered | E6: regular | H6: ORDERON | I6: 445 | J6: 15 | K6: 64 | L6: 0 | M6: 64 | N6: 396 | O6: 19.8 | P6: 415.8 | Q6: 415.8 | R6: 22.0% | S6: 91.48 | T6: 20 | U6: 0 | V6: 0 | W6: 0 | X6: 0 | Y6: 0 | Z6: 0 | AA6: 0 | AB6: 0 | AC6: 20.06 | AD6: 131.54 | AE6: 0 | AF6: 0 | AG6: 0 | AH6: 19.8 | AI6: 0 | AJ6: 0.4 | AK6: 20.2 | AL6: 264.05 | AM6: Yes | AN6: 10.584 | AO6: Yes | AP6: No | AQ6: SWIGGYIT | AR6: 100833489 | AS6: No | AW6: Yes | AX6: No
A7: 216195624955525 | C7: 2025-09-07 11:50:24 | D7: delivered | E7: regular | H7: MISSEDYOU | I7: 545 | J7: 20 | K7: 64 | L7: 0 | M7: 64 | N7: 501 | O7: 25.06 | P7: 526.06 | Q7: 526.06 | R7: 20.0% | S7: 105.21 | T7: 0 | U7: 0 | V7: 0 | W7: 0 | X7: 0 | Y7: 0 | Z7: 0 | AA7: 0 | AB7: 0 | AC7: 18.94 | AD7: 124.15 | AE7: 0 | AF7: 0 | AG7: 0 | AH7: 25.05 | AI7: 0 | AJ7: 0.5 | AK7: 25.55 | AL7: 376.35 | AM7: No | AN7: 3.221 | AO7: Yes | AP7: No | AR7: 206500dc-ba9e-4a58-be62-bb3f830ec1f3,206500dc-ba9e-4a58-be62-bb3f830ec1f3 | AS7: No | AW7: Yes | AX7: No
A8: 216196251207859 | C8: 2025-09-07 12:00:51 | D8: delivered | E8: regular | H8: MISSEDYOU | I8: 595 | J8: 20 | K8: 64 | L8: 0 | M8: 64 | N8: 551 | O8: 27.56 | P8: 578.56 | Q8: 578.56 | R8: 20.0% | S8: 115.71 | T8: 0 | U8: 0 | V8: 0 | W8: 0 | X8: 0 | Y8: 0 | Z8: 0 | AA8: 0 | AB8: 0 | AC8: 20.82 | AD8: 136.53 | AE8: 0 | AF8: 0 | AG8: 0 | AH8: 27.55 | AI8: 0 | AJ8: 0.55 | AK8: 28.1 | AL8: 413.9 | AM8: No | AN8: 1.736 | AO8: Yes | AP8: No | AR8: 206500dc-ba9e-4a58-be62-bb3f830ec1f3,206500dc-ba9e-4a58-be62-bb3f830ec1f3 | AS8: No | AW8: Yes | AX8: No
A9: 216196318782234 | C9: 2025-09-07 12:01:58 | D9: delivered | E9: regular | H9: FLAVORFUL | I9: 795 | J9: 20 | K9: 100 | L9: 0 | M9: 100 | N9: 715 | O9: 35.76 | P9: 750.76 | Q9: 750.76 | R9: 20.0% | S9: 150.15 | T9: 7 | U9: 0 | V9: 0 | W9: 0 | X9: 0 | Y9: 0 | Z9: 0 | AA9: 0 | AB9: 0 | AC9: 28.28 | AD9: 185.43 | AE9: 0 | AF9: 0 | AG9: 0 | AH9: 35.75 | AI9: 0 | AJ9: 0.71 | AK9: 36.46 | AL9: 528.84 | AM9: Yes | AN9: 7.14 | AO9: Yes | AP9: No | AR9: 206500dc-ba9e-4a58-be62-bb3f830ec1f3,206500dc-ba9e-4a58-be62-bb3f830ec1f3 | AS9: No | AW9: Yes | AX9: No
A10: 216196319730615 | C10: 2025-09-07 12:01:59 | D10: delivered | E10: regular | H10: TOPUPOFFER | I10: 1070 | J10: 40 | K10: 63.99 | L10: 0 | M10: 63.99 | N10: 1046.01 | O10: 52.3 | P10: 1098.308 | Q10: 1098.31 | R10: 16.0% | S10: 175.73 | T10: 12 | U10: 0 | V10: 0 | W10: 0 | X10: 0 | Y10: 0 | Z10: 0 | AA10: 0 | AB10: 0 | AC10: 33.8 | AD10: 221.53 | AE10: 0 | AF10: 0 | AG10: 0 | AH10: 52.3 | AI10: 0 | AJ10: 1.05 | AK10: 53.35 | AL10: 823.45 | AM10: Yes | AN10: 8.672 | AO10: Yes | AP10: No | AQ10: SWIGGYIT | AR10: 100833489 | AS10: No | AW10: Yes | AX10: No
A11: 216196369395491 | C11: 2025-09-07 12:02:49 | D11: delivered | E11: regular | H11: FLAVORFUL | I11: 1070 | J11: 35 | K11: 99.99 | L11: 0 | M11: 99.99 | N11: 1005.01 | O11: 50.26 | P11: 1055.268 | Q11: 1055.27 | R11: 16.0% | S11: 168.84 | T11: 12 | U11: 0 | V11: 0 | W11: 0 | X11: 0 | Y11: 0 | Z11: 0 | AA11: 0 | AB11: 0 | AC11: 32.56 | AD11: 213.4 | AE11: 0 | AF11: 0 | AG11: 0 | AH11: 50.25 | AI11: 0 | AJ11: 1.01 | AK11: 51.26 | AL11: 790.62 | AM11: Yes | AN11: 8.357 | AO11: Yes | AP11: No | AR11: 103197863 | AS11: No | AW11: Yes | AX11: No
A12: 216196370342633 | C12: 2025-09-07 12:02:50 | D12: delivered | E12: regular | H12: PARTY | I12: 3720 | J12: 130 | K12: 372 | L12: 0 | M12: 372 | N12: 3478 | O12: 173.9 | P12: 3651.9 | Q12: 3651.9 | R12: 10.0% | S12: 365.19 | T12: 0 | U12: 0 | V12: 0 | W12: 0 | X12: 0 | Y12: 0 | Z12: 0 | AA12: 0 | AB12: 0 | AC12: 65.74 | AD12: 430.93 | AE12: 0 | AF12: 0 | AG12: 0 | AH12: 173.9 | AI12: 0 | AJ12: 3.48 | AK12: 177.38 | AL12: 3043.61 | AM12: No | AN12: 2.165 | AO12: Yes | AP12: No | AR12: 206500dc-ba9e-4a58-be62-bb3f830ec1f3,206500dc-ba9e-4a58-be62-bb3f830ec1f3 | AS12: No | AW12: Yes | AX12: No
A13: 216196398579170 | C13: 2025-09-07 12:03:18 | D13: delivered | E13: regular | H13: PARTY | I13: 2505 | J13: 101 | K13: 250.5 | L13: 0 | M13: 250.5 | N13: 2355.5 | O13: 117.78 | P13: 2473.28 | Q13: 2473.28 | R13: 12.0% | S13: 296.79 | T13: 0 | U13: 0 | V13: 0 | W13: 0 | X13: 0 | Y13: 0 | Z13: 0 | AA13: 0 | AB13: 0 | AC13: 53.42 | AD13: 350.21 | AE13: 0 | AF13: 0 | AG13: 0 | AH13: 117.78 | AI13: 0 | AJ13: 2.36 | AK13: 120.14 | AL13: 2002.93 | AM13: No | AN13: 4.025 | AO13: Yes | AP13: No | AR13: 206500dc-ba9e-4a58-be62-bb3f830ec1f3,206500dc-ba9e-4a58-be62-bb3f830ec1f3 | AS13: No | AW13: Yes | AX13: No
A14: 216196406085506 | C14: 2025-09-07 12:03:26 | D14: delivered | E14: regular | I14: 750 | J14: 30 | K14: 0 | L14: 0 | M14: 0 | N14: 780 | O14: 39 | P14: 819 | Q14: 819 | R14: 20.0% | S14: 163.8 | T14: 0 | U14: 0 | V14: 0 | W14: 0 | X14: 0 | Y14: 0 | Z14: 0 | AA14: 0 | AB14: 0 | AC14: 29.48 | AD14: 193.28 | AE14: 0 | AF14: 0 | AG14: 0 | AH14: 39 | AI14: 0 | AJ14: 0.78 | AK14: 39.78 | AL14: 585.94 | AM14: No | AN14: 2.887 | AO14: Yes | AP14: No | AS14: No | AW14: No | AX14: No
A15: 216196418755888 | C15: 2025-09-07 12:03:38 | D15: delivered | E15: regular | H15: SWIGGYIT | I15: 345 | J15: 15 | K15: 64 | L15: 0 | M15: 64 | N15: 296 | O15: 14.8 | P15: 310.8 | Q15: 310.8 | R15: 22.0% | S15: 68.38 | T15: 0 | U15: 0 | V15: 0 | W15: 0 | X15: 0 | Y15: 0 | Z15: 0 | AA15: 0 | AB15: 0 | AC15: 12.3 | AD15: 80.68 | AE15: 0 | AF15: 0 | AG15: 0 | AH15: 14.8 | AI15: 0 | AJ15: 0.3 | AK15: 15.1 | AL15: 215.01 | AM15: No | AN15: 2.743 | AO15: Yes | AP15: No | AR15: 206500dc-ba9e-4a58-be62-bb3f830ec1f3,206500dc-ba9e-4a58-be62-bb3f830ec1f3 | AS15: No | AW15: Yes | AX15: No
A16: 216196471990903 | C16: 2025-09-07 12:04:31 | D16: delivered | E16: regular | H16: FLAVORFUL | I16: 825 | J16: 30 | K16: 100 | L16: 0 | M16: 100 | N16: 755 | O16: 37.76 | P16: 792.76 | Q16: 792.76 | R16: 20.0% | S16: 158.55 | T16: 0 | U16: 0 | V16: 0 | W16: 0 | X16: 0 | Y16: 0 | Z16: 0 | AA16: 0 | AB16: 0 | AC16: 28.54 | AD16: 187.09 | AE16: 0 | AF16: 0 | AG16: 0 | AH16: 37.75 | AI16: 0 | AJ16: 0.76 | AK16: 38.51 | AL16: 567.16 | AM16: No | AN16: 5.859 | AO16: Yes | AP16: No | AR16: 7976c1a5-d80d-4bad-a312-f735df2858c3,206500dc-ba9e-4a58-be62-bb3f830ec1f3,7976c1a5-d80d-4bad-a312-f735df2858c3,206500dc-ba9e-4a58-be62-bb3f830ec1f3 | AS16: No | AW16: Yes | AX16: No
A17: 216196518619326 | C17: 2025-09-07 12:05:18 | D17: delivered | E17: regular | H17: PARTY | I17: 1945 | J17: 87 | K17: 194.49 | L17: 0 | M17: 194.49 | N17: 1837.51 | O17: 91.88 | P17: 1929.39 | Q17: 1929.39 | R17: 14.0% | S17: 270.11 | T17: 20 | U17: 0 | V17: 0 | W17: 0 | X17: 0 | Y17: 0 | Z17: 0 | AA17: 0 | AB17: 0 | AC17: 52.22 | AD17: 342.33 | AE17: 0 | AF17: 0 | AG17: 0 | AH17: 91.88 | AI17: 0 | AJ17: 1.84 | AK17: 93.72 | AL17: 1493.35 | AM17: Yes | AN17: 10.01 | AO17: Yes | AP17: No | AR17: 78720640-9ebb-4bdb-aeb3-f0b02bf107f9,78720640-9ebb-4bdb-aeb3-f0b02bf107f9 | AS17: No | AW17: Yes | AX17: No
A18: 216196579210130 | C18: 2025-09-07 12:06:19 | D18: delivered | E18: regular | H18: FLAVORFUL | I18: 920 | J18: 30 | K18: 99.99 | L18: 0 | M18: 99.99 | N18: 850.01 | O18: 42.5 | P18: 892.508 | Q18: 892.51 | R18: 20.0% | S18: 178.5 | T18: 0 | U18: 0 | V18: 0 | W18: 0 | X18: 0 | Y18: 0 | Z18: 0 | AA18: 0 | AB18: 0 | AC18: 32.12 | AD18: 210.62 | AE18: 0 | AF18: 0 | AG18: 0 | AH18: 42.5 | AI18: 0 | AJ18: 0.85 | AK18: 43.35 | AL18: 638.52 | AM18: No | AN18: 4.281 | AO18: Yes | AP18: No | AR18: fd29a353-a54e-4102-af9f-990652bb4307,206500dc-ba9e-4a58-be62-bb3f830ec1f3,fd29a353-a54e-4102-af9f-990652bb4307,206500dc-ba9e-4a58-be62-bb3f830ec1f3 | AS18: No | AW18: Yes | AX18: No
A19: 216196714829195 | C19: 2025-09-07 12:08:34 | D19: delivered | E19: regular | H19: MISSEDYOU | I19: 295 | J19: 10 | K19: 64 | L19: 0 | M19: 64 | N19: 241 | O19: 12.06 | P19: 253.06 | Q19: 253.06 | R19: 22.0% | S19: 55.67 | T19: 0 | U19: 0 | V19: 0 | W19: 0 | X19: 0 | Y19: 0 | Z19: 0 | AA19: 0 | AB19: 0 | AC19: 10.02 | AD19: 65.69 | AE19: 0 | AF19: 0 | AG19: 0 | AH19: 12.05 | AI19: 0 | AJ19: 0.24 | AK19: 12.29 | AL19: 175.07 | AM19: No | AN19: 4.222 | AO19: Yes | AP19: No | AR19: 4fc9bd84-de3b-4bdf-b4f7-c54bff9d5933,206500dc-ba9e-4a58-be62-bb3f830ec1f3,4fc9bd84-de3b-4bdf-b4f7-c54bff9d5933,206500dc-ba9e-4a58-be62-bb3f830ec1f3 | AS19: No | AW19: Yes | AX19: No
A20: 216196732802628 | C20: 2025-09-07 12:08:52 | D20: delivered | E20: regular | H20: FLAVORFUL | I20: 940 | J20: 40 | K20: 99.99 | L20: 0 | M20: 99.99 | N20: 880.01 | O20: 44 | P20: 924.008 | Q20: 924.01 | R20: 16.0% | S20: 147.84 | T20: 0 | U20: 0 | V20: 0 | W20: 0 | X20: 0 | Y20: 0 | Z20: 0 | AA20: 0 | AB20: 0 | AC20: 26.62 | AD20: 174.46 | AE20: 0 | AF20: 0 | AG20: 0 | AH20: 44 | AI20: 0 | AJ20: 0.88 | AK20: 44.88 | AL20: 704.69 | AM20: No | AN20: 4.776 | AO20: Yes | AP20: No | AR20: 9796c340-c9d6-4524-b5da-766c3e300b97,206500dc-ba9e-4a58-be62-bb3f830ec1f3,9796c340-c9d6-4524-b5da-766c3e300b97,206500dc-ba9e-4a58-be62-bb3f830ec1f3 | AS20: No | AW20: Yes | AX20: No
A21: 216196824736131 | C21: 2025-09-07 12:10:24 | D21: delivered | E21: regular | H21: FLAVORFUL | I21: 795 | J21: 32 | K21: 99.98 | L21: 0 | M21: 99.98 | N21: 727.02 | O21: 36.36 | P21: 763.376 | Q21: 763.38 | R21: 20.0% | S21: 152.68 | T21: 7 | U21: 0 | V21: 0 | W21: 0 | X21: 0 | Y21: 0 | Z21: 0 | AA21: 0 | AB21: 0 | AC21: 28.74 | AD21: 188.42 | AE21: 0 | AF21: 0 | AG21: 0 | AH21: 36.35 | AI21: 0 | AJ21: 0.73 | AK21: 37.08 | AL21: 537.86 | AM21: Yes | AN21: 6.048 | AO21: Yes | AP21: No | AR21: 206500dc-ba9e-4a58-be62-bb3f830ec1f3,206500dc-ba9e-4a58-be62-bb3f830ec1f3 | AS21: No | AW21: Yes | AX21: No
A22: 216196905727095 | C22: 2025-09-07 12:11:45 | D22: cancelled | E22: regular | F22: cash | G22: CUSTOMER | H22: FLAVORFUL | I22: 970 | J22: 30 | K22: 99.99 | L22: 0 | M22: 99.99 | N22: 900.01 | O22: 0 | P22: 900.008 | Q22: 360.004 | R22: 0% | S22: 0 | T22: 0 | U22: 0 | V22: 0 | W22: 0 | X22: 0 | Y22: 0 | Z22: 0 | AA22: 0 | AB22: 0 | AC22: 0 | AD22: 0 | AE22: 522 | AF22: 0 | AG22: 522 | AH22: 18 | AI22: 0 | AJ22: 0 | AK22: 18 | AL22: 360 | AM22: No | AN22: 2.844 | AO22: Yes | AP22: No | AR22: 206500dc-ba9e-4a58-be62-bb3f830ec1f3,206500dc-ba9e-4a58-be62-bb3f830ec1f3 | AS22: No | AU22: 4.8333333 | AV22: not picked up | AW22: Yes | AX22: No
A23: 216196909738695 | C23: 2025-09-07 12:11:49 | D23: delivered | E23: regular | I23: 1330 | J23: 60 | K23: 0 | L23: 0 | M23: 0 | N23: 1390 | O23: 69.5 | P23: 1459.5 | Q23: 1459.5 | R23: 14.0% | S23: 204.33 | T23: 0 | U23: 0 | V23: 0 | W23: 0 | X23: 0 | Y23: 0 | Z23: 0 | AA23: 0 | AB23: 0 | AC23: 36.78 | AD23: 241.11 | AE23: 0 | AF23: 0 | AG23: 0 | AH23: 69.5 | AI23: 0 | AJ23: 1.39 | AK23: 70.89 | AL23: 1147.5 | AM23: No | AN23: 2.27 | AO23: Yes | AP23: No | AR23: 206500dc-ba9e-4a58-be62-bb3f830ec1f3 | AS23: No | AW23: Yes | AX23: No
A24: 216196944851388 | C24: 2025-09-07 12:12:24 | D24: delivered | E24: regular | H24: FLAVORFUL | I24: 700 | J24: 25 | K24: 99.99 | L24: 0 | M24: 99.99 | N24: 625.01 | O24: 31.26 | P24: 656.268 | Q24: 656.27 | R24: 20.0% | S24: 131.25 | T24: 7 | U24: 0 | V24: 0 | W24: 0 | X24: 0 | Y24: 0 | Z24: 0 | AA24: 0 | AB24: 0 | AC24: 24.88 | AD24: 163.13 | AE24: 0 | AF24: 0 | AG24: 0 | AH24: 31.25 | AI24: 0 | AJ24: 0.63 | AK24: 31.88 | AL24: 461.24 | AM24: Yes | AN24: 6.994 | AO24: Yes | AP24: No | AR24: 206500dc-ba9e-4a58-be62-bb3f830ec1f3,206500dc-ba9e-4a58-be62-bb3f830ec1f3 | AS24: No | AW24: Yes | AX24: No
A25: 216197135373699 | C25: 2025-09-07 12:15:35 | D25: delivered | E25: regular | H25: ORDERON | I25: 870 | J25: 30 | K25: 63.99 | L25: 0 | M25: 63.99 | N25: 836.01 | O25: 41.8 | P25: 877.808 | Q25: 877.81 | R25: 20.0% | S25: 175.56 | T25: 0 | U25: 0 | V25: 0 | W25: 0 | X25: 0 | Y25: 0 | Z25: 0 | AA25: 0 | AB25: 0 | AC25: 31.6 | AD25: 207.16 | AE25: 0 | AF25: 0 | AG25: 0 | AH25: 41.8 | AI25: 0 | AJ25: 0.84 | AK25: 42.64 | AL25: 628.01 | AM25: No | AN25: 4.856 | AO25: Yes | AP25: No | AQ25: TRYNEW | AR25: 206500dc-ba9e-4a58-be62-bb3f830ec1f3,206500dc-ba9e-4a58-be62-bb3f830ec1f3 | AS25: No | AW25: Yes | AX25: No
A26: 216197157340789 | C26: 2025-09-07 12:15:57 | D26: delivered | E26: regular | H26: FLAVORFUL | I26: 950 | J26: 30 | K26: 100 | L26: 0 | M26: 100 | N26: 880 | O26: 44 | P26: 924 | Q26: 924 | R26: 16.0% | S26: 147.84 | T26: 20 | U26: 0 | V26: 0 | W26: 0 | X26: 0 | Y26: 0 | Z26: 0 | AA26: 0 | AB26: 0 | AC26: 30.22 | AD26: 198.06 | AE26: 0 | AF26: 0 | AG26: 0 | AH26: 44 | AI26: 0 | AJ26: 0.88 | AK26: 44.88 | AL26: 681.08 | AM26: Yes | AN26: 10.792 | AO26: Yes | AP26: No | AR26: 103197863 | AS26: No | AW26: No | AX26: No
A27: 216197191255412 | C27: 2025-09-07 12:16:31 | D27: delivered | E27: regular | H27: FLAVORFUL | I27: 1595 | J27: 50 | K27: 99.99 | L27: 0 | M27: 99.99 | N27: 1545.01 | O27: 77.26 | P27: 1622.268 | Q27: 1622.27 | R27: 14.0% | S27: 227.12 | T27: 0 | U27: 0 | V27: 0 | W27: 0 | X27: 0 | Y27: 0 | Z27: 0 | AA27: 0 | AB27: 0 | AC27: 40.88 | AD27: 268 | AE27: 0 | AF27: 0 | AG27: 0 | AH27: 77.25 | AI27: 0 | AJ27: 1.55 | AK27: 78.8 | AL27: 1275.46 | AM27: No | AN27: 2.165 | AO27: Yes | AP27: No | AR27: ed64217b-6261-4e79-9ff8-375bd1222e13,206500dc-ba9e-4a58-be62-bb3f830ec1f3,ed64217b-6261-4e79-9ff8-375bd1222e13,206500dc-ba9e-4a58-be62-bb3f830ec1f3 | AS27: No | AW27: Yes | AX27: No
A28: 216197279576110 | C28: 2025-09-07 12:17:59 | D28: delivered | E28: regular | H28: FLAVORFUL | I28: 985 | J28: 45 | K28: 99.99 | L28: 0 | M28: 99.99 | N28: 930.01 | O28: 46.5 | P28: 976.508 | Q28: 976.51 | R28: 16.0% | S28: 156.24 | T28: 7 | U28: 0 | V28: 0 | W28: 0 | X28: 0 | Y28: 0 | Z28: 0 | AA28: 0 | AB28: 0 | AC28: 29.38 | AD28: 192.62 | AE28: 0 | AF28: 0 | AG28: 0 | AH28: 46.5 | AI28: 0 | AJ28: 0.93 | AK28: 47.43 | AL28: 736.46 | AM28: Yes | AN28: 7.483 | AO28: Yes | AP28: No | AR28: 103197863 | AS28: No | AW28: Yes | AX28: No
A29: 216197283352604 | C29: 2025-09-07 12:18:03 | D29: delivered | E29: regular | H29: MISSEDYOU | I29: 395 | J29: 15 | K29: 64 | L29: 0 | M29: 64 | N29: 346 | O29: 17.3 | P29: 363.3 | Q29: 363.3 | R29: 22.0% | S29: 79.93 | T29: 0 | U29: 0 | V29: 0 | W29: 0 | X29: 0 | Y29: 0 | Z29: 0 | AA29: 0 | AB29: 0 | AC29: 14.38 | AD29: 94.31 | AE29: 0 | AF29: 0 | AG29: 0 | AH29: 17.3 | AI29: 0 | AJ29: 0.35 | AK29: 17.65 | AL29: 251.33 | AM29: No | AN29: 3.415 | AO29: Yes | AP29: No | AR29: 206500dc-ba9e-4a58-be62-bb3f830ec1f3,206500dc-ba9e-4a58-be62-bb3f830ec1f3 | AS29: No | AW29: Yes | AX29: No
A30: 216197376823580 | C30: 2025-09-07 12:19:36 | D30: delivered | E30: regular | H30: MISSEDYOU | I30: 495 | J30: 15 | K30: 64 | L30: 0 | M30: 64 | N30: 446 | O30: 22.3 | P30: 468.3 | Q30: 468.3 | R30: 22.0% | S30: 103.03 | T30: 0 | U30: 0 | V30: 0 | W30: 0 | X30: 0 | Y30: 0 | Z30: 0 | AA30: 0 | AB30: 0 | AC30: 18.54 | AD30: 121.57 | AE30: 0 | AF30: 0 | AG30: 0 | AH30: 22.3 | AI30: 0 | AJ30: 0.45 | AK30: 22.75 | AL30: 323.97 | AM30: No | AN30: 2.844 | AO30: Yes | AP30: No | AR30: 206500dc-ba9e-4a58-be62-bb3f830ec1f3,206500dc-ba9e-4a58-be62-bb3f830ec1f3 | AS30: No | AW30: Yes | AX30: No
A31: 216197390407542 | C31: 2025-09-07 12:19:50 | D31: delivered | E31: regular | H31: TRYNEW | I31: 345 | J31: 15 | K31: 64 | L31: 0 | M31: 64 | N31: 296 | O31: 14.8 | P31: 310.8 | Q31: 310.8 | R31: 22.0% | S31: 68.38 | T31: 0 | U31: 0 | V31: 0 | W31: 0 | X31: 0 | Y31: 0 | Z31: 0 | AA31: 0 | AB31: 0 | AC31: 12.3 | AD31: 80.68 | AE31: 0 | AF31: 0 | AG31: 0 | AH31: 14.8 | AI31: 0 | AJ31: 0.3 | AK31: 15.1 | AL31: 215.01 | AM31: No | AN31: 3.336 | AO31: Yes | AP31: No | AR31: 206500dc-ba9e-4a58-be62-bb3f830ec1f3,206500dc-ba9e-4a58-be62-bb3f830ec1f3 | AS31: No | AW31: Yes | AX31: No
A32: 216197391830379 | C32: 2025-09-07 12:19:51 | D32: delivered | E32: regular | I32: 2255 | J32: 80 | K32: 0 | L32: 0 | M32: 0 | N32: 2335 | O32: 116.76 | P32: 2451.76 | Q32: 2451.76 | R32: 12.0% | S32: 294.21 | T32: 12 | U32: 0 | V32: 0 | W32: 0 | X32: 0 | Y32: 0 | Z32: 0 | AA32: 0 | AB32: 0 | AC32: 55.12 | AD32: 361.33 | AE32: 0 | AF32: 0 | AG32: 0 | AH32: 116.75 | AI32: 0 | AJ32: 2.33 | AK32: 119.08 | AL32: 1971.34 | AM32: Yes | AN32: 9.292 | AO32: Yes | AP32: No | AS32: No | AW32: Yes | AX32: No
A33: 216197407461270 | C33: 2025-09-07 12:20:07 | D33: delivered | E33: regular | I33: 475 | J33: 15 | K33: 0 | L33: 0 | M33: 0 | N33: 490 | O33: 24.5 | P33: 514.5 | Q33: 514.5 | R33: 20.0% | S33: 102.9 | T33: 0 | U33: 0 | V33: 0 | W33: 0 | X33: 0 | Y33: 0 | Z33: 0 | AA33: 0 | AB33: 0 | AC33: 18.52 | AD33: 121.42 | AE33: 0 | AF33: 0 | AG33: 0 | AH33: 24.5 | AI33: 0 | AJ33: 0.49 | AK33: 24.99 | AL33: 368.09 | AM33: No | AN33: 2.887 | AO33: Yes | AP33: No | AR33: 3fb9a3ee-ec74-411a-8c4a-3b77452b2816,206500dc-ba9e-4a58-be62-bb3f830ec1f3 | AS33: No | AW33: Yes | AX33: No
A34: 216197499037508 | C34: 2025-09-07 12:21:39 | D34: delivered | E34: regular | H34: SWIGGYIT | I34: 395 | J34: 15 | K34: 64 | L34: 0 | M34: 64 | N34: 346 | O34: 17.3 | P34: 363.3 | Q34: 363.3 | R34: 22.0% | S34: 79.93 | T34: 20 | U34: 0 | V34: 0 | W34: 0 | X34: 0 | Y34: 0 | Z34: 0 | AA34: 0 | AB34: 0 | AC34: 17.98 | AD34: 117.91 | AE34: 0 | AF34: 0 | AG34: 0 | AH34: 17.3 | AI34: 0 | AJ34: 0.35 | AK34: 17.65 | AL34: 227.73 | AM34: Yes | AN34: 11.881 | AO34: Yes | AP34: No | AR34: 100833489 | AS34: No | AW34: Yes | AX34: No
A35: 216197509433281 | C35: 2025-09-07 12:21:49 | D35: delivered | E35: regular | H35: SWIGGYIT | I35: 295 | J35: 15 | K35: 64 | L35: 0 | M35: 64 | N35: 246 | O35: 12.3 | P35: 258.3 | Q35: 258.3 | R35: 22.0% | S35: 56.83 | T35: 0 | U35: 0 | V35: 0 | W35: 0 | X35: 0 | Y35: 0 | Z35: 0 | AA35: 0 | AB35: 0 | AC35: 10.22 | AD35: 67.05 | AE35: 0 | AF35: 0 | AG35: 0 | AH35: 12.3 | AI35: 0 | AJ35: 0.25 | AK35: 12.55 | AL35: 178.68 | AM35: No | AN35: 3.555 | AO35: Yes | AP35: No | AR35: 206500dc-ba9e-4a58-be62-bb3f830ec1f3,206500dc-ba9e-4a58-be62-bb3f830ec1f3 | AS35: No | AW35: Yes | AX35: No
A36: 216197624992695 | C36: 2025-09-07 12:23:44 | D36: delivered | E36: regular | H36: FLAVORFUL | I36: 795 | J36: 20 | K36: 100 | L36: 0 | M36: 100 | N36: 715 | O36: 35.76 | P36: 750.76 | Q36: 750.76 | R36: 20.0% | S36: 150.15 | T36: 0 | U36: 0 | V36: 0 | W36: 0 | X36: 0 | Y36: 0 | Z36: 0 | AA36: 0 | AB36: 0 | AC36: 27.02 | AD36: 177.17 | AE36: 0 | AF36: 0 | AG36: 0 | AH36: 35.75 | AI36: 0 | AJ36: 0.71 | AK36: 36.46 | AL36: 537.1 | AM36: No | AN36: 4.727 | AO36: Yes | AP36: No | AR36: 206500dc-ba9e-4a58-be62-bb3f830ec1f3,206500dc-ba9e-4a58-be62-bb3f830ec1f3 | AS36: No | AW36: Yes | AX36: No
A37: 216197701155703 | C37: 2025-09-07 12:25:01 | D37: delivered | E37: regular | H37: SWIGGYIT | I37: 595 | J37: 20 | K37: 64 | L37: 0 | M37: 64 | N37: 551 | O37: 27.56 | P37: 578.56 | Q37: 578.56 | R37: 20.0% | S37: 115.71 | T37: 0 | U37: 0 | V37: 0 | W37: 0 | X37: 0 | Y37: 0 | Z37: 0 | AA37: 0 | AB37: 0 | AC37: 20.82 | AD37: 136.53 | AE37: 0 | AF37: 0 | AG37: 0 | AH37: 27.55 | AI37: 0 | AJ37: 0.55 | AK37: 28.1 | AL37: 413.9 | AM37: No | AN37: 3.676 | AO37: Yes | AP37: No | AR37: 206500dc-ba9e-4a58-be62-bb3f830ec1f3,206500dc-ba9e-4a58-be62-bb3f830ec1f3 | AS37: No | AW37: Yes | AX37: No
A38: 216197714716248 | C38: 2025-09-07 12:25:14 | D38: delivered | E38: regular | H38: TRYNEW | I38: 445 | J38: 15 | K38: 64 | L38: 0 | M38: 64 | N38: 396 | O38: 19.8 | P38: 415.8 | Q38: 415.8 | R38: 22.0% | S38: 91.48 | T38: 0 | U38: 0 | V38: 0 | W38: 0 | X38: 0 | Y38: 0 | Z38: 0 | AA38: 0 | AB38: 0 | AC38: 16.46 | AD38: 107.94 | AE38: 0 | AF38: 0 | AG38: 0 | AH38: 19.8 | AI38: 0 | AJ38: 0.4 | AK38: 20.2 | AL38: 287.65 | AM38: No | AN38: 4.206 | AO38: Yes | AP38: No | AR38: 206500dc-ba9e-4a58-be62-bb3f830ec1f3,206500dc-ba9e-4a58-be62-bb3f830ec1f3 | AS38: No | AW38: Yes | AX38: No
A39: 216197744156310 | C39: 2025-09-07 12:25:44 | D39: delivered | E39: regular | H39: FLAVORFUL | I39: 850 | J39: 30 | K39: 99.99 | L39: 0 | M39: 99.99 | N39: 780.01 | O39: 39 | P39: 819.008 | Q39: 819.01 | R39: 20.0% | S39: 163.8 | T39: 7 | U39: 0 | V39: 0 | W39: 0 | X39: 0 | Y39: 0 | Z39: 0 | AA39: 0 | AB39: 0 | AC39: 30.74 | AD39: 201.54 | AE39: 0 | AF39: 0 | AG39: 0 | AH39: 39 | AI39: 0 | AJ39: 0.78 | AK39: 39.78 | AL39: 577.68 | AM39: Yes | AN39: 6.081 | AO39: Yes | AP39: No | AR39: 1ee99cfa-d879-4c22-818c-87ec68ac59fb,206500dc-ba9e-4a58-be62-bb3f830ec1f3,1ee99cfa-d879-4c22-818c-87ec68ac59fb,206500dc-ba9e-4a58-be62-bb3f830ec1f3 | AS39: No | AW39: Yes | AX39: No
A40: 216197866575606 | C40: 2025-09-07 12:27:46 | D40: delivered | E40: regular | I40: 495 | J40: 15 | K40: 0 | L40: 0 | M40: 0 | N40: 510 | O40: 25.5 | P40: 535.5 | Q40: 535.5 | R40: 20.0% | S40: 107.1 | T40: 30 | U40: 0 | V40: 0 | W40: 0 | X40: 0 | Y40: 0 | Z40: 0 | AA40: 0 | AB40: 0 | AC40: 24.68 | AD40: 161.78 | AE40: 0 | AF40: 0 | AG40: 0 | AH40: 25.5 | AI40: 0 | AJ40: 0.51 | AK40: 26.01 | AL40: 347.71 | AM40: Yes | AN40: 13.572 | AO40: Yes | AP40: No | AS40: No | AW40: No | AX40: No
A41: 216197902217227 | C41: 2025-09-07 12:28:22 | D41: delivered | E41: regular | I41: 2220 | J41: 70 | K41: 0 | L41: 0 | M41: 0 | N41: 2290 | O41: 114.5 | P41: 2404.5 | Q41: 2404.5 | R41: 12.0% | S41: 288.54 | T41: 30 | U41: 0 | V41: 0 | W41: 0 | X41: 0 | Y41: 0 | Z41: 0 | AA41: 0 | AB41: 0 | AC41: 57.34 | AD41: 375.88 | AE41: 0 | AF41: 0 | AG41: 0 | AH41: 114.5 | AI41: 0 | AJ41: 2.29 | AK41: 116.79 | AL41: 1911.83 | AM41: Yes | AN41: 13.519 | AO41: Yes | AP41: No | AS41: No | AW41: No | AX41: No
A42: 216197974850379 | C42: 2025-09-07 12:29:34 | D42: delivered | E42: regular | H42: PARTY | I42: 1890 | J42: 77 | K42: 189 | L42: 0 | M42: 189 | N42: 1778 | O42: 88.9 | P42: 1866.9 | Q42: 1866.9 | R42: 14.0% | S42: 261.37 | T42: 0 | U42: 0 | V42: 0 | W42: 0 | X42: 0 | Y42: 0 | Z42: 0 | AA42: 0 | AB42: 0 | AC42: 47.04 | AD42: 308.41 | AE42: 0 | AF42: 283 | AG42: 283 | AH42: 88.9 | AI42: 0 | AJ42: 1.78 | AK42: 90.68 | AL42: 1184.8 | AM42: No | AN42: 5.182 | AO42: Yes | AP42: No | AR42: b7a7c44d-6f0c-4301-be7e-fd1c61ddc821,206500dc-ba9e-4a58-be62-bb3f830ec1f3,b7a7c44d-6f0c-4301-be7e-fd1c61ddc821,206500dc-ba9e-4a58-be62-bb3f830ec1f3 | AS42: No | AW42: Yes | AX42: No
A43: 216197993869288 | C43: 2025-09-07 12:29:53 | D43: delivered | E43: regular | I43: 1595 | J43: 50 | K43: 0 | L43: 0 | M43: 0 | N43: 1645 | O43: 82.26 | P43: 1727.26 | Q43: 1727.24 | R43: 14.0% | S43: 241.81 | T43: 0 | U43: 0 | V43: 0 | W43: 0 | X43: 0 | Y43: 0 | Z43: 0 | AA43: 0 | AB43: 0 | AC43: 43.52 | AD43: 285.33 | AE43: 0 | AF43: 0 | AG43: 0 | AH43: 82.25 | AI43: 0 | AJ43: 1.65 | AK43: 83.9 | AL43: 1358.01 | AM43: No | AN43: 4.964 | AO43: Yes | AP43: No | AR43: 206500dc-ba9e-4a58-be62-bb3f830ec1f3 | AS43: No | AW43: Yes | AX43: No
A44: 216198011667901 | C44: 2025-09-07 12:30:11 | D44: cancelled | E44: regular | F44: prepaid | G44: SWIGGY | H44: FLAVORFUL | I44: 875 | J44: 20 | K44: 100 | L44: 0 | M44: 100 | N44: 795 | O44: 39.76 | P44: 834.76 | Q44: 834.76 | R44: 20.0% | S44: 166.95 | T44: 0 | U44: 0 | V44: 0 | W44: 0 | X44: 0 | Y44: 0 | Z44: 0 | AA44: 0 | AB44: 0 | AC44: 30.06 | AD44: 197.01 | AE44: 0 | AF44: 0 | AG44: 0 | AH44: 39.75 | AI44: 0 | AJ44: 0.8 | AK44: 40.55 | AL44: 597.2 | AM44: No | AN44: 7.12 | AO44: Yes | AP44: Yes | AR44: 103197863 | AS44: No | AU44: 68.65 | AV44: picked up | AW44: Yes | AX44: No
A45: 216198035251615 | C45: 2025-09-07 12:30:35 | D45: delivered | E45: regular | I45: 670 | J45: 25 | K45: 0 | L45: 0 | M45: 0 | N45: 695 | O45: 34.76 | P45: 729.76 | Q45: 729.76 | R45: 20.0% | S45: 145.95 | T45: 7 | U45: 0 | V45: 0 | W45: 0 | X45: 0 | Y45: 0 | Z45: 0 | AA45: 0 | AB45: 0 | AC45: 27.54 | AD45: 180.49 | AE45: 0 | AF45: 0 | AG45: 0 | AH45: 34.75 | AI45: 0 | AJ45: 0.7 | AK45: 35.45 | AL45: 513.83 | AM45: Yes | AN45: 7.576 | AO45: Yes | AP45: No | AS45: No | AW45: No | AX45: No
A46: 216198085214201 | C46: 2025-09-07 12:31:25 | D46: delivered | E46: regular | H46: SWIGGYIT | I46: 375 | J46: 15 | K46: 64 | L46: 0 | M46: 64 | N46: 326 | O46: 16.3 | P46: 342.3 | Q46: 342.3 | R46: 22.0% | S46: 75.31 | T46: 0 | U46: 0 | V46: 0 | W46: 0 | X46: 0 | Y46: 0 | Z46: 0 | AA46: 0 | AB46: 0 | AC46: 13.56 | AD46: 88.87 | AE46: 0 | AF46: 0 | AG46: 0 | AH46: 16.3 | AI46: 0 | AJ46: 0.33 | AK46: 16.63 | AL46: 236.81 | AM46: No | AN46: 5.856 | AO46: Yes | AP46: No | AR46: 206500dc-ba9e-4a58-be62-bb3f830ec1f3,206500dc-ba9e-4a58-be62-bb3f830ec1f3 | AS46: No | AW46: Yes | AX46: No
A47: 216198122202778 | C47: 2025-09-07 12:32:02 | D47: delivered | E47: regular | H47: FLAVORFUL | I47: 1245 | J47: 45 | K47: 99.99 | L47: 0 | M47: 99.99 | N47: 1190.01 | O47: 59.5 | P47: 1249.508 | Q47: 1249.51 | R47: 16.0% | S47: 199.92 | T47: 30 | U47: 0 | V47: 0 | W47: 0 | X47: 0 | Y47: 0 | Z47: 0 | AA47: 0 | AB47: 0 | AC47: 41.38 | AD47: 271.3 | AE47: 0 | AF47: 0 | AG47: 0 | AH47: 59.5 | AI47: 0 | AJ47: 1.19 | AK47: 60.69 | AL47: 917.5 | AM47: Yes | AN47: 13.273 | AO47: Yes | AP47: No | AR47: 103197863 | AS47: No | AW47: Yes | AX47: No
A48: 216198129577145 | C48: 2025-09-07 12:32:09 | D48: delivered | E48: regular | H48: TRYNEW | I48: 620 | J48: 25 | K48: 63.99 | L48: 0 | M48: 63.99 | N48: 581.01 | O48: 29.06 | P48: 610.068 | Q48: 610.07 | R48: 20.0% | S48: 122.01 | T48: 0 | U48: 0 | V48: 0 | W48: 0 | X48: 0 | Y48: 0 | Z48: 0 | AA48: 0 | AB48: 0 | AC48: 21.96 | AD48: 143.97 | AE48: 0 | AF48: 0 | AG48: 0 | AH48: 29.05 | AI48: 0 | AJ48: 0.58 | AK48: 29.63 | AL48: 436.46 | AM48: No | AN48: 4.113 | AO48: Yes | AP48: No | AR48: 206500dc-ba9e-4a58-be62-bb3f830ec1f3,206500dc-ba9e-4a58-be62-bb3f830ec1f3 | AS48: No | AW48: Yes | AX48: No
A49: 216198224016448 | C49: 2025-09-07 12:33:44 | D49: delivered | E49: regular | H49: PARTY | I49: 1840 | J49: 60 | K49: 183.99 | L49: 0 | M49: 183.99 | N49: 1716.01 | O49: 85.8 | P49: 1801.81 | Q49: 1801.81 | R49: 14.0% | S49: 252.25 | T49: 0 | U49: 0 | V49: 0 | W49: 0 | X49: 0 | Y49: 0 | Z49: 0 | AA49: 0 | AB49: 0 | AC49: 45.4 | AD49: 297.65 | AE49: 0 | AF49: 0 | AG49: 0 | AH49: 85.8 | AI49: 0 | AJ49: 1.72 | AK49: 87.52 | AL49: 1416.64 | AM49: No | AN49: 2.165 | AO49: Yes | AP49: No | AR49: 206500dc-ba9e-4a58-be62-bb3f830ec1f3,206500dc-ba9e-4a58-be62-bb3f830ec1f3 | AS49: No | AW49: Yes | AX49: No
A50: 216198228079035 | C50: 2025-09-07 12:33:48 | D50: delivered | E50: regular | H50: SWIGGYIT | I50: 225 | J50: 10 | K50: 64 | L50: 0 | M50: 64 | N50: 171 | O50: 8.56 | P50: 179.56 | Q50: 179.56 | R50: 22.0% | S50: 39.5 | T50: 0 | U50: 0 | V50: 0 | W50: 0 | X50: 0 | Y50: 0 | Z50: 0 | AA50: 0 | AB50: 0 | AC50: 7.1 | AD50: 46.6 | AE50: 0 | AF50: 0 | AG50: 0 | AH50: 8.55 | AI50: 0 | AJ50: 0.17 | AK50: 8.72 | AL50: 124.21 | AM50: No | AN50: 3.415 | AO50: Yes | AP50: No | AR50: 206500dc-ba9e-4a58-be62-bb3f830ec1f3,206500dc-ba9e-4a58-be62-bb3f830ec1f3 | AS50: No | AW50: Yes | AX50: No
A51: 216198261532958 | C51: 2025-09-07 12:34:21 | D51: delivered | E51: regular | H51: SWIGGYIT | I51: 475 | J51: 15 | K51: 64 | L51: 0 | M51: 64 | N51: 426 | O51: 21.3 | P51: 447.3 | Q51: 447.3 | R51: 22.0% | S51: 98.41 | T51: 0 | U51: 0 | V51: 0 | W51: 0 | X51: 0 | Y51: 0 | Z51: 0 | AA51: 0 | AB51: 0 | AC51: 17.72 | AD51: 116.13 | AE51: 0 | AF51: 0 | AG51: 0 | AH51: 21.3 | AI51: 0 | AJ51: 0.43 | AK51: 21.73 | AL51: 309.46 | AM51: No | AN51: 4.454 | AO51: Yes | AP51: No | AR51: 206500dc-ba9e-4a58-be62-bb3f830ec1f3,206500dc-ba9e-4a58-be62-bb3f830ec1f3 | AS51: No | AW51: Yes | AX51: No
A52: 216198293760515 | C52: 2025-09-07 12:34:53 | D52: delivered | E52: regular | H52: ORDERON | I52: 525 | J52: 20 | K52: 64 | L52: 0 | M52: 64 | N52: 481 | O52: 24.06 | P52: 505.06 | Q52: 505.06 | R52: 20.0% | S52: 101.01 | T52: 20 | U52: 0 | V52: 0 | W52: 0 | X52: 0 | Y52: 0 | Z52: 0 | AA52: 0 | AB52: 0 | AC52: 21.78 | AD52: 142.79 | AE52: 0 | AF52: 0 | AG52: 0 | AH52: 24.05 | AI52: 0 | AJ52: 0.48 | AK52: 24.53 | AL52: 337.73 | AM52: Yes | AN52: 11.139 | AO52: Yes | AP52: No | AQ52: MISSEDYOU | AR52: d11683aa-dfb1-4154-bd6a-e0af7fd1697f,d11683aa-dfb1-4154-bd6a-e0af7fd1697f | AS52: No | AW52: No | AX52: No
A53: 216198332202832 | C53: 2025-09-07 12:35:32 | D53: delivered | E53: regular | I53: 445 | J53: 15 | K53: 0 | L53: 0 | M53: 0 | N53: 460 | O53: 23 | P53: 483 | Q53: 483 | R53: 22.0% | S53: 106.26 | T53: 0 | U53: 0 | V53: 0 | W53: 0 | X53: 0 | Y53: 0 | Z53: 0 | AA53: 0 | AB53: 0 | AC53: 19.12 | AD53: 125.38 | AE53: 0 | AF53: 0 | AG53: 0 | AH53: 23 | AI53: 0 | AJ53: 0.46 | AK53: 23.46 | AL53: 334.14 | AM53: No | AN53: 3.503 | AO53: Yes | AP53: No | AS53: No | AW53: No | AX53: No
A54: 216198370551644 | C54: 2025-09-07 12:36:10 | D54: delivered | E54: regular | H54: PARTY | I54: 1310 | J54: 50 | K54: 131 | L54: 0 | M54: 131 | N54: 1229 | O54: 61.46 | P54: 1290.46 | Q54: 1290.46 | R54: 16.0% | S54: 206.47 | T54: 0 | U54: 0 | V54: 0 | W54: 0 | X54: 0 | Y54: 0 | Z54: 0 | AA54: 0 | AB54: 0 | AC54: 37.16 | AD54: 243.63 | AE54: 0 | AF54: 0 | AG54: 0 | AH54: 61.45 | AI54: 0 | AJ54: 1.23 | AK54: 62.68 | AL54: 984.14 | AM54: No | AN54: 2.743 | AO54: Yes | AP54: No | AR54: 206500dc-ba9e-4a58-be62-bb3f830ec1f3,206500dc-ba9e-4a58-be62-bb3f830ec1f3 | AS54: No | AW54: Yes | AX54: No
A55: 216198424171561 | C55: 2025-09-07 12:37:04 | D55: delivered | E55: regular | H55: TRYNEW | I55: 640 | J55: 25 | K55: 63.99 | L55: 0 | M55: 63.99 | N55: 601.01 | O55: 30.06 | P55: 631.068 | Q55: 631.07 | R55: 20.0% | S55: 126.21 | T55: 0 | U55: 0 | V55: 0 | W55: 0 | X55: 0 | Y55: 0 | Z55: 0 | AA55: 0 | AB55: 0 | AC55: 22.72 | AD55: 148.93 | AE55: 0 | AF55: 0 | AG55: 0 | AH55: 30.05 | AI55: 0 | AJ55: 0.6 | AK55: 30.65 | AL55: 451.48 | AM55: No | AN55: 4.5 | AO55: Yes | AP55: No | AR55: 206500dc-ba9e-4a58-be62-bb3f830ec1f3,206500dc-ba9e-4a58-be62-bb3f830ec1f3 | AS55: No | AW55: Yes | AX55: No
A56: 216198451060843 | C56: 2025-09-07 12:37:31 | D56: delivered | E56: regular | H56: FLAVORFUL | I56: 740 | J56: 30 | K56: 99.99 | L56: 0 | M56: 99.99 | N56: 670.01 | O56: 33.5 | P56: 703.508 | Q56: 703.51 | R56: 20.0% | S56: 140.7 | T56: 0 | U56: 0 | V56: 0 | W56: 0 | X56: 0 | Y56: 0 | Z56: 0 | AA56: 0 | AB56: 0 | AC56: 25.32 | AD56: 166.02 | AE56: 0 | AF56: 0 | AG56: 0 | AH56: 33.5 | AI56: 0 | AJ56: 0.67 | AK56: 34.17 | AL56: 503.3 | AM56: No | AN56: 4.611 | AO56: Yes | AP56: No | AR56: 103197863 | AS56: No | AW56: No | AX56: No
A57: 216198467286392 | C57: 2025-09-07 12:37:47 | D57: delivered | E57: regular | H57: SWIGGYIT | I57: 475 | J57: 15 | K57: 64 | L57: 0 | M57: 64 | N57: 426 | O57: 21.3 | P57: 447.3 | Q57: 447.3 | R57: 22.0% | S57: 98.41 | T57: 7 | U57: 0 | V57: 0 | W57: 0 | X57: 0 | Y57: 0 | Z57: 0 | AA57: 0 | AB57: 0 | AC57: 18.98 | AD57: 124.39 | AE57: 0 | AF57: 0 | AG57: 0 | AH57: 21.3 | AI57: 0 | AJ57: 0.43 | AK57: 21.73 | AL57: 301.2 | AM57: Yes | AN57: 6.409 | AO57: Yes | AP57: No | AR57: 206500dc-ba9e-4a58-be62-bb3f830ec1f3,206500dc-ba9e-4a58-be62-bb3f830ec1f3 | AS57: No | AW57: Yes | AX57: No
A58: 216198482920694 | C58: 2025-09-07 12:38:02 | D58: delivered | E58: regular | I58: 1370 | J58: 35 | K58: 0 | L58: 0 | M58: 0 | N58: 1405 | O58: 70.26 | P58: 1475.26 | Q58: 1475.24 | R58: 14.0% | S58: 206.53 | T58: 0 | U58: 0 | V58: 0 | W58: 0 | X58: 0 | Y58: 0 | Z58: 0 | AA58: 0 | AB58: 0 | AC58: 37.18 | AD58: 243.71 | AE58: 0 | AF58: 0 | AG58: 0 | AH58: 70.25 | AI58: 0 | AJ58: 1.41 | AK58: 71.66 | AL58: 1159.89 | AM58: No | AN58: 4.088 | AO58: Yes | AP58: No | AR58: 206500dc-ba9e-4a58-be62-bb3f830ec1f3 | AS58: No | AW58: Yes | AX58: No
A59: 216198500507982 | C59: 2025-09-07 12:38:20 | D59: delivered | E59: regular | H59: SWIGGYIT | I59: 295 | J59: 15 | K59: 64 | L59: 0 | M59: 64 | N59: 246 | O59: 12.3 | P59: 258.3 | Q59: 258.3 | R59: 22.0% | S59: 56.83 | T59: 0 | U59: 0 | V59: 0 | W59: 0 | X59: 0 | Y59: 0 | Z59: 0 | AA59: 0 | AB59: 0 | AC59: 10.22 | AD59: 67.05 | AE59: 0 | AF59: 0 | AG59: 0 | AH59: 12.3 | AI59: 0 | AJ59: 0.25 | AK59: 12.55 | AL59: 178.68 | AM59: No | AN59: 3.989 | AO59: Yes | AP59: No | AR59: 206500dc-ba9e-4a58-be62-bb3f830ec1f3,206500dc-ba9e-4a58-be62-bb3f830ec1f3 | AS59: No | AW59: Yes | AX59: No
A60: 216198533888312 | C60: 2025-09-07 12:38:53 | D60: delivered | E60: regular | H60: PARTY | I60: 1385 | J60: 50 | K60: 138.5 | L60: 0 | M60: 138.5 | N60: 1296.5 | O60: 64.82 | P60: 1361.32 | Q60: 1361.32 | R60: 16.0% | S60: 217.81 | T60: 30 | U60: 0 | V60: 0 | W60: 0 | X60: 0 | Y60: 0 | Z60: 0 | AA60: 0 | AB60: 0 | AC60: 44.6 | AD60: 292.41 | AE60: 0 | AF60: 0 | AG60: 0 | AH60: 64.83 | AI60: 0 | AJ60: 1.3 | AK60: 66.13 | AL60: 1002.78 | AM60: Yes | AN60: 14.135 | AO60: Yes | AP60: No | AR60: 87080508 | AS60: No | AW60: Yes | AX60: No
A61: 216198670760730 | C61: 2025-09-07 12:41:10 | D61: delivered | E61: regular | H61: SWIGGYIT | I61: 445 | J61: 15 | K61: 64 | L61: 0 | M61: 64 | N61: 396 | O61: 19.8 | P61: 415.8 | Q61: 415.8 | R61: 22.0% | S61: 91.48 | T61: 0 | U61: 0 | V61: 0 | W61: 0 | X61: 0 | Y61: 0 | Z61: 0 | AA61: 0 | AB61: 0 | AC61: 16.46 | AD61: 107.94 | AE61: 0 | AF61: 0 | AG61: 0 | AH61: 19.8 | AI61: 0 | AJ61: 0.4 | AK61: 20.2 | AL61: 287.65 | AM61: No | AN61: 2.165 | AO61: Yes | AP61: No | AR61: f776f640-9e8b-4f8c-a153-d77c7538447e,206500dc-ba9e-4a58-be62-bb3f830ec1f3,f776f640-9e8b-4f8c-a153-d77c7538447e,206500dc-ba9e-4a58-be62-bb3f830ec1f3 | AS61: No | AW61: Yes | AX61: No
A62: 216198688553238 | C62: 2025-09-07 12:41:28 | D62: delivered | E62: regular | H62: SWIGGYIT | I62: 395 | J62: 15 | K62: 64 | L62: 0 | M62: 64 | N62: 346 | O62: 17.3 | P62: 363.3 | Q62: 363.3 | R62: 22.0% | S62: 79.93 | T62: 0 | U62: 0 | V62: 0 | W62: 0 | X62: 0 | Y62: 0 | Z62: 0 | AA62: 0 | AB62: 0 | AC62: 14.38 | AD62: 94.31 | AE62: 0 | AF62: 0 | AG62: 0 | AH62: 17.3 | AI62: 0 | AJ62: 0.35 | AK62: 17.65 | AL62: 251.33 | AM62: No | AN62: 3.415 | AO62: Yes | AP62: No | AR62: fd082c63-89d4-49ff-99de-81affc94fd81,206500dc-ba9e-4a58-be62-bb3f830ec1f3,fd082c63-89d4-49ff-99de-81affc94fd81,206500dc-ba9e-4a58-be62-bb3f830ec1f3 | AS62: No | AW62: Yes | AX62: No
A63: 216198706345913 | C63: 2025-09-07 12:41:46 | D63: cancelled | E63: regular | F63: prepaid | G63: CUSTOMER | H63: SWIGGYIT | I63: 245 | J63: 10 | K63: 64 | L63: 0 | M63: 64 | N63: 191 | O63: 9.56 | P63: 200.56 | Q63: 80.224 | R63: 0% | S63: 0 | T63: 0 | U63: 0 | V63: 0 | W63: 0 | X63: 0 | Y63: 0 | Z63: 0 | AA63: 0 | AB63: 0 | AC63: 0 | AD63: 0 | AE63: 120.33 | AF63: 0 | AG63: 120.33 | AH63: 3.82 | AI63: 0 | AJ63: 0 | AK63: 3.82 | AL63: 76.4 | AM63: No | AN63: 2.743 | AO63: Yes | AP63: No | AR63: 27efe065-ebb2-41a5-8f35-085082b55720,206500dc-ba9e-4a58-be62-bb3f830ec1f3,27efe065-ebb2-41a5-8f35-085082b55720,206500dc-ba9e-4a58-be62-bb3f830ec1f3 | AS63: No | AU63: 15.083333 | AV63: not picked up | AW63: Yes | AX63: No
A64: 216198843322885 | C64: 2025-09-07 12:44:03 | D64: delivered | E64: regular | I64: 345 | J64: 15 | K64: 0 | L64: 0 | M64: 0 | N64: 360 | O64: 18 | P64: 378 | Q64: 378 | R64: 22.0% | S64: 83.16 | T64: 0 | U64: 0 | V64: 0 | W64: 0 | X64: 0 | Y64: 0 | Z64: 0 | AA64: 0 | AB64: 0 | AC64: 14.96 | AD64: 98.12 | AE64: 0 | AF64: 0 | AG64: 0 | AH64: 18 | AI64: 0 | AJ64: 0.36 | AK64: 18.36 | AL64: 261.5 | AM64: No | AN64: 3.723 | AO64: Yes | AP64: No | AR64: 206500dc-ba9e-4a58-be62-bb3f830ec1f3 | AS64: No | AW64: Yes | AX64: No
A65: 216199019534365 | C65: 2025-09-07 12:46:59 | D65: delivered | E65: regular | H65: FLAVORFUL | I65: 1020 | J65: 35 | K65: 99.99 | L65: 0 | M65: 99.99 | N65: 955.01 | O65: 47.76 | P65: 1002.768 | Q65: 1002.77 | R65: 16.0% | S65: 160.44 | T65: 7 | U65: 0 | V65: 0 | W65: 0 | X65: 0 | Y65: 0 | Z65: 0 | AA65: 0 | AB65: 0 | AC65: 30.14 | AD65: 197.58 | AE65: 0 | AF65: 0 | AG65: 0 | AH65: 47.75 | AI65: 0 | AJ65: 0.96 | AK65: 48.71 | AL65: 756.48 | AM65: Yes | AN65: 6.546 | AO65: Yes | AP65: No | AR65: 206500dc-ba9e-4a58-be62-bb3f830ec1f3,206500dc-ba9e-4a58-be62-bb3f830ec1f3 | AS65: No | AW65: Yes | AX65: No
A66: 216199019599933 | C66: 2025-09-07 12:46:59 | D66: delivered | E66: regular | H66: SWIGGYIT | I66: 495 | J66: 15 | K66: 64 | L66: 0 | M66: 64 | N66: 446 | O66: 22.3 | P66: 468.3 | Q66: 468.3 | R66: 22.0% | S66: 103.03 | T66: 12 | U66: 0 | V66: 0 | W66: 0 | X66: 0 | Y66: 0 | Z66: 0 | AA66: 0 | AB66: 0 | AC66: 20.7 | AD66: 135.73 | AE66: 0 | AF66: 0 | AG66: 0 | AH66: 22.3 | AI66: 0 | AJ66: 0.45 | AK66: 22.75 | AL66: 309.81 | AM66: Yes | AN66: 8.042 | AO66: Yes | AP66: No | AR66: 100833489 | AS66: No | AW66: Yes | AX66: No
A67: 216199035093616 | C67: 2025-09-07 12:47:15 | D67: delivered | E67: regular | H67: FLAVORFUL | I67: 920 | J67: 30 | K67: 99.99 | L67: 0 | M67: 99.99 | N67: 850.01 | O67: 42.5 | P67: 892.508 | Q67: 892.51 | R67: 20.0% | S67: 178.5 | T67: 7 | U67: 0 | V67: 0 | W67: 0 | X67: 0 | Y67: 0 | Z67: 0 | AA67: 0 | AB67: 0 | AC67: 33.4 | AD67: 218.9 | AE67: 0 | AF67: 0 | AG67: 0 | AH67: 42.5 | AI67: 0 | AJ67: 0.85 | AK67: 43.35 | AL67: 630.26 | AM67: Yes | AN67: 7.65 | AO67: Yes | AP67: No | AR67: 103197863 | AS67: No | AW67: Yes | AX67: No
A68: 216199059885259 | C68: 2025-09-07 12:47:39 | D68: delivered | E68: regular | H68: SWIGGYIT | I68: 345 | J68: 15 | K68: 64 | L68: 0 | M68: 64 | N68: 296 | O68: 14.8 | P68: 310.8 | Q68: 310.8 | R68: 22.0% | S68: 68.38 | T68: 12 | U68: 0 | V68: 0 | W68: 0 | X68: 0 | Y68: 0 | Z68: 0 | AA68: 0 | AB68: 0 | AC68: 14.46 | AD68: 94.84 | AE68: 0 | AF68: 0 | AG68: 0 | AH68: 14.8 | AI68: 0 | AJ68: 0.3 | AK68: 15.1 | AL68: 200.85 | AM68: Yes | AN68: 9.303 | AO68: Yes | AP68: No | AR68: 100833489 | AS68: No | AW68: Yes | AX68: No
A69: 216199182397868 | C69: 2025-09-07 12:49:42 | D69: delivered | E69: regular | H69: SWIGGYIT | I69: 345 | J69: 15 | K69: 64 | L69: 0 | M69: 64 | N69: 296 | O69: 14.8 | P69: 310.8 | Q69: 310.8 | R69: 22.0% | S69: 68.38 | T69: 0 | U69: 0 | V69: 0 | W69: 0 | X69: 0 | Y69: 0 | Z69: 0 | AA69: 0 | AB69: 0 | AC69: 12.3 | AD69: 80.68 | AE69: 0 | AF69: 0 | AG69: 0 | AH69: 14.8 | AI69: 0 | AJ69: 0.3 | AK69: 15.1 | AL69: 215.01 | AM69: No | AN69: 2.418 | AO69: Yes | AP69: No | AR69: 206500dc-ba9e-4a58-be62-bb3f830ec1f3,206500dc-ba9e-4a58-be62-bb3f830ec1f3 | AS69: No | AW69: Yes | AX69: No
A70: 216199192206697 | C70: 2025-09-07 12:49:52 | D70: delivered | E70: regular | H70: SWIGGYIT | I70: 395 | J70: 15 | K70: 64 | L70: 0 | M70: 64 | N70: 346 | O70: 17.3 | P70: 363.3 | Q70: 363.3 | R70: 22.0% | S70: 79.93 | T70: 0 | U70: 0 | V70: 0 | W70: 0 | X70: 0 | Y70: 0 | Z70: 0 | AA70: 0 | AB70: 0 | AC70: 14.38 | AD70: 94.31 | AE70: 0 | AF70: 0 | AG70: 0 | AH70: 17.3 | AI70: 0 | AJ70: 0.35 | AK70: 17.65 | AL70: 251.33 | AM70: No | AN70: 3.099 | AO70: Yes | AP70: No | AR70: 206500dc-ba9e-4a58-be62-bb3f830ec1f3,206500dc-ba9e-4a58-be62-bb3f830ec1f3 | AS70: No | AW70: Yes | AX70: No
A71: 216199199765363 | C71: 2025-09-07 12:49:59 | D71: delivered | E71: regular | H71: SWIGGYIT | I71: 475 | J71: 15 | K71: 64 | L71: 0 | M71: 64 | N71: 426 | O71: 21.3 | P71: 447.3 | Q71: 447.3 | R71: 22.0% | S71: 98.41 | T71: 0 | U71: 0 | V71: 0 | W71: 0 | X71: 0 | Y71: 0 | Z71: 0 | AA71: 0 | AB71: 0 | AC71: 17.72 | AD71: 116.13 | AE71: 0 | AF71: 0 | AG71: 0 | AH71: 21.3 | AI71: 0 | AJ71: 0.43 | AK71: 21.73 | AL71: 309.46 | AM71: No | AN71: 3.415 | AO71: Yes | AP71: No | AR71: 206500dc-ba9e-4a58-be62-bb3f830ec1f3,206500dc-ba9e-4a58-be62-bb3f830ec1f3 | AS71: No | AW71: Yes | AX71: No
A72: 216199461938669 | C72: 2025-09-07 12:54:21 | D72: delivered | E72: regular | I72: 690 | J72: 30 | K72: 0 | L72: 0 | M72: 0 | N72: 720 | O72: 36 | P72: 756 | Q72: 756 | R72: 20.0% | S72: 151.2 | T72: 7 | U72: 0 | V72: 0 | W72: 0 | X72: 0 | Y72: 0 | Z72: 0 | AA72: 0 | AB72: 0 | AC72: 28.48 | AD72: 186.68 | AE72: 0 | AF72: 0 | AG72: 0 | AH72: 36 | AI72: 0 | AJ72: 0.72 | AK72: 36.72 | AL72: 532.6 | AM72: Yes | AN72: 7.111 | AO72: Yes | AP72: No | AS72: No | AW72: No | AX72: No
A73: 216199511804990 | C73: 2025-09-07 12:55:11 | D73: delivered | E73: regular | H73: TRYNEW | I73: 475 | J73: 15 | K73: 64 | L73: 0 | M73: 64 | N73: 426 | O73: 21.3 | P73: 447.3 | Q73: 447.3 | R73: 22.0% | S73: 98.41 | T73: 12 | U73: 0 | V73: 0 | W73: 0 | X73: 0 | Y73: 0 | Z73: 0 | AA73: 0 | AB73: 0 | AC73: 19.88 | AD73: 130.29 | AE73: 0 | AF73: 0 | AG73: 0 | AH73: 21.3 | AI73: 0 | AJ73: 0.43 | AK73: 21.73 | AL73: 295.3 | AM73: Yes | AN73: 8.624 | AO73: Yes | AP73: No | AR73: 100833489 | AS73: No | AW73: Yes | AX73: No
A74: 216199599708297 | C74: 2025-09-07 12:56:39 | D74: delivered | E74: regular | H74: FLAVORFUL | I74: 1195 | J74: 40 | K74: 99.98 | L74: 0 | M74: 99.98 | N74: 1135.02 | O74: 56.76 | P74: 1191.776 | Q74: 1191.78 | R74: 16.0% | S74: 190.68 | T74: 0 | U74: 0 | V74: 0 | W74: 0 | X74: 0 | Y74: 0 | Z74: 0 | AA74: 0 | AB74: 0 | AC74: 34.32 | AD74: 225 | AE74: 0 | AF74: 0 | AG74: 0 | AH74: 56.75 | AI74: 0 | AJ74: 1.14 | AK74: 57.89 | AL74: 908.87 | AM74: No | AN74: 3.503 | AO74: Yes | AP74: No | AR74: edf7fbf5-8b49-4c79-bc71-c8bc873565cd,206500dc-ba9e-4a58-be62-bb3f830ec1f3,edf7fbf5-8b49-4c79-bc71-c8bc873565cd,206500dc-ba9e-4a58-be62-bb3f830ec1f3 | AS74: No | AW74: Yes | AX74: No
A75: 216199760114041 | C75: 2025-09-07 12:59:20 | D75: delivered | E75: regular | I75: 970 | J75: 30 | K75: 0 | L75: 0 | M75: 0 | N75: 1000 | O75: 50 | P75: 1050 | Q75: 1050 | R75: 16.0% | S75: 168 | T75: 0 | U75: 0 | V75: 0 | W75: 0 | X75: 0 | Y75: 0 | Z75: 0 | AA75: 0 | AB75: 0 | AC75: 30.24 | AD75: 198.24 | AE75: 0 | AF75: 0 | AG75: 0 | AH75: 50 | AI75: 0 | AJ75: 1 | AK75: 51 | AL75: 800.76 | AM75: No | AN75: 3.099 | AO75: Yes | AP75: No | AS75: No | AW75: No | AX75: No
A76: 216199894015506 | C76: 2025-09-07 13:01:34 | D76: delivered | E76: regular | H76: SWIGGYIT | I76: 445 | J76: 15 | K76: 64 | L76: 0 | M76: 64 | N76: 396 | O76: 19.8 | P76: 415.8 | Q76: 415.8 | R76: 22.0% | S76: 91.48 | T76: 0 | U76: 0 | V76: 0 | W76: 0 | X76: 0 | Y76: 0 | Z76: 0 | AA76: 0 | AB76: 0 | AC76: 16.46 | AD76: 107.94 | AE76: 0 | AF76: 0 | AG76: 0 | AH76: 19.8 | AI76: 0 | AJ76: 0.4 | AK76: 20.2 | AL76: 287.65 | AM76: No | AN76: 3.989 | AO76: Yes | AP76: No | AR76: 206500dc-ba9e-4a58-be62-bb3f830ec1f3,206500dc-ba9e-4a58-be62-bb3f830ec1f3 | AS76: No | AW76: Yes | AX76: No
A77: 216199923201109 | C77: 2025-09-07 13:02:03 | D77: delivered | E77: regular | H77: FLAVORFUL | I77: 950 | J77: 30 | K77: 100 | L77: 0 | M77: 100 | N77: 880 | O77: 44 | P77: 924 | Q77: 924 | R77: 16.0% | S77: 147.84 | T77: 0 | U77: 0 | V77: 0 | W77: 0 | X77: 0 | Y77: 0 | Z77: 0 | AA77: 0 | AB77: 0 | AC77: 26.62 | AD77: 174.46 | AE77: 0 | AF77: 0 | AG77: 0 | AH77: 44 | AI77: 0 | AJ77: 0.88 | AK77: 44.88 | AL77: 704.68 | AM77: No | AN77: 4.159 | AO77: Yes | AP77: No | AR77: 7606c900-b758-4b84-92de-33b98896600a,206500dc-ba9e-4a58-be62-bb3f830ec1f3,7606c900-b758-4b84-92de-33b98896600a,206500dc-ba9e-4a58-be62-bb3f830ec1f3 | AS77: No | AW77: Yes | AX77: No
A78: 216199966448292 | C78: 2025-09-07 13:02:46 | D78: delivered | E78: regular | H78: SWIGGYIT | I78: 375 | J78: 15 | K78: 64 | L78: 0 | M78: 64 | N78: 326 | O78: 16.3 | P78: 342.3 | Q78: 342.3 | R78: 22.0% | S78: 75.31 | T78: 12 | U78: 0 | V78: 0 | W78: 0 | X78: 0 | Y78: 0 | Z78: 0 | AA78: 0 | AB78: 0 | AC78: 15.72 | AD78: 103.03 | AE78: 0 | AF78: 0 | AG78: 0 | AH78: 16.3 | AI78: 0 | AJ78: 0.33 | AK78: 16.63 | AL78: 222.65 | AM78: Yes | AN78: 8.337 | AO78: Yes | AP78: No | AR78: 100833489 | AS78: No | AW78: Yes | AX78: No
A79: 216200106118404 | C79: 2025-09-07 13:05:06 | D79: delivered | E79: regular | H79: TOPUPOFFER | I79: 1240 | J79: 40 | K79: 124 | L79: 0 | M79: 124 | N79: 1156 | O79: 57.8 | P79: 1213.8 | Q79: 1213.8 | R79: 16.0% | S79: 194.21 | T79: 0 | U79: 0 | V79: 0 | W79: 0 | X79: 0 | Y79: 0 | Z79: 0 | AA79: 0 | AB79: 0 | AC79: 34.96 | AD79: 229.17 | AE79: 0 | AF79: 0 | AG79: 0 | AH79: 57.8 | AI79: 0 | AJ79: 1.16 | AK79: 58.96 | AL79: 925.68 | AM79: No | AN79: 2.087 | AO79: Yes | AP79: No | AQ79: PARTY | AR79: be7fce84-a812-40a2-babc-59f9691c2c16,be7fce84-a812-40a2-babc-59f9691c2c16 | AS79: No | AW79: Yes | AX79: No
A80: 216200115985437 | C80: 2025-09-07 13:05:15 | D80: delivered | E80: regular | H80: MISSEDYOU | I80: 575 | J80: 22 | K80: 63.99 | L80: 0 | M80: 63.99 | N80: 533.01 | O80: 26.66 | P80: 559.668 | Q80: 559.67 | R80: 20.0% | S80: 111.93 | T80: 0 | U80: 0 | V80: 0 | W80: 0 | X80: 0 | Y80: 0 | Z80: 0 | AA80: 0 | AB80: 0 | AC80: 20.14 | AD80: 132.07 | AE80: 0 | AF80: 0 | AG80: 0 | AH80: 26.65 | AI80: 0 | AJ80: 0.53 | AK80: 27.18 | AL80: 400.39 | AM80: No | AN80: 2.894 | AO80: Yes | AP80: No | AR80: 3cbea324-c81d-47fe-9904-a3a62cd9b3c0,206500dc-ba9e-4a58-be62-bb3f830ec1f3,3cbea324-c81d-47fe-9904-a3a62cd9b3c0,206500dc-ba9e-4a58-be62-bb3f830ec1f3 | AS80: No | AW80: Yes | AX80: No
A81: 216200142519419 | C81: 2025-09-07 13:05:42 | D81: delivered | E81: regular | H81: PARTY | I81: 3335 | J81: 110 | K81: 333.5 | L81: 0 | M81: 333.5 | N81: 3111.5 | O81: 155.58 | P81: 3267.08 | Q81: 3267.08 | R81: 10.0% | S81: 326.71 | T81: 7 | U81: 0 | V81: 0 | W81: 0 | X81: 0 | Y81: 0 | Z81: 0 | AA81: 0 | AB81: 0 | AC81: 60.06 | AD81: 393.77 | AE81: 0 | AF81: 0 | AG81: 0 | AH81: 155.57 | AI81: 0 | AJ81: 3.11 | AK81: 158.68 | AL81: 2714.61 | AM81: Yes | AN81: 7.723 | AO81: Yes | AP81: No | AR81: 87080508 | AS81: No | AW81: Yes | AX81: No
A82: 216200198529392 | C82: 2025-09-07 13:06:38 | D82: delivered | E82: regular | H82: TRYNEW | I82: 445 | J82: 15 | K82: 64 | L82: 0 | M82: 64 | N82: 396 | O82: 19.8 | P82: 415.8 | Q82: 415.8 | R82: 22.0% | S82: 91.48 | T82: 0 | U82: 0 | V82: 0 | W82: 0 | X82: 0 | Y82: 0 | Z82: 0 | AA82: 0 | AB82: 0 | AC82: 16.46 | AD82: 107.94 | AE82: 0 | AF82: 0 | AG82: 0 | AH82: 19.8 | AI82: 0 | AJ82: 0.4 | AK82: 20.2 | AL82: 287.65 | AM82: No | AN82: 5.671 | AO82: Yes | AP82: No | AR82: 206500dc-ba9e-4a58-be62-bb3f830ec1f3,206500dc-ba9e-4a58-be62-bb3f830ec1f3 | AS82: No | AW82: Yes | AX82: No
A83: 216200302386098 | C83: 2025-09-07 13:08:22 | D83: delivered | E83: regular | H83: FLAVORFUL | I83: 1090 | J83: 35 | K83: 99.99 | L83: 0 | M83: 99.99 | N83: 1025.01 | O83: 51.26 | P83: 1076.268 | Q83: 1076.27 | R83: 16.0% | S83: 172.2 | T83: 0 | U83: 0 | V83: 0 | W83: 0 | X83: 0 | Y83: 0 | Z83: 0 | AA83: 0 | AB83: 0 | AC83: 31 | AD83: 203.2 | AE83: 0 | AF83: 0 | AG83: 0 | AH83: 51.25 | AI83: 0 | AJ83: 1.03 | AK83: 52.28 | AL83: 820.79 | AM83: No | AN83: 4.893 | AO83: Yes | AP83: No | AR83: 7278fabe-b2ae-4535-8f7b-8c48777a6275,206500dc-ba9e-4a58-be62-bb3f830ec1f3,7278fabe-b2ae-4535-8f7b-8c48777a6275,206500dc-ba9e-4a58-be62-bb3f830ec1f3 | AS83: No | AW83: Yes | AX83: No
A84: 216200340768020 | C84: 2025-09-07 13:09:00 | D84: delivered | E84: regular | H84: TRYNEW | I84: 345 | J84: 15 | K84: 64 | L84: 0 | M84: 64 | N84: 296 | O84: 14.8 | P84: 310.8 | Q84: 310.8 | R84: 22.0% | S84: 68.38 | T84: 0 | U84: 0 | V84: 0 | W84: 0 | X84: 0 | Y84: 0 | Z84: 0 | AA84: 0 | AB84: 0 | AC84: 12.3 | AD84: 80.68 | AE84: 0 | AF84: 0 | AG84: 0 | AH84: 14.8 | AI84: 0 | AJ84: 0.3 | AK84: 15.1 | AL84: 215.01 | AM84: No | AN84: 3.589 | AO84: Yes | AP84: No | AR84: 206500dc-ba9e-4a58-be62-bb3f830ec1f3,206500dc-ba9e-4a58-be62-bb3f830ec1f3 | AS84: No | AW84: Yes | AX84: No
A85: 216200491055766 | C85: 2025-09-07 13:11:31 | D85: delivered | E85: regular | H85: SWIGGYIT | I85: 475 | J85: 15 | K85: 64 | L85: 0 | M85: 64 | N85: 426 | O85: 21.3 | P85: 447.3 | Q85: 447.3 | R85: 22.0% | S85: 98.41 | T85: 0 | U85: 0 | V85: 0 | W85: 0 | X85: 0 | Y85: 0 | Z85: 0 | AA85: 0 | AB85: 0 | AC85: 17.72 | AD85: 116.13 | AE85: 0 | AF85: 0 | AG85: 0 | AH85: 21.3 | AI85: 0 | AJ85: 0.43 | AK85: 21.73 | AL85: 309.46 | AM85: No | AN85: 3.099 | AO85: Yes | AP85: No | AR85: 206500dc-ba9e-4a58-be62-bb3f830ec1f3,206500dc-ba9e-4a58-be62-bb3f830ec1f3 | AS85: No | AW85: Yes | AX85: No
A86: 216200510166881 | C86: 2025-09-07 13:11:50 | D86: delivered | E86: regular | H86: TRYNEW | I86: 525 | J86: 15 | K86: 64 | L86: 0 | M86: 64 | N86: 476 | O86: 23.8 | P86: 499.8 | Q86: 499.8 | R86: 20.0% | S86: 99.96 | T86: 0 | U86: 0 | V86: 0 | W86: 0 | X86: 0 | Y86: 0 | Z86: 0 | AA86: 0 | AB86: 0 | AC86: 18 | AD86: 117.96 | AE86: 0 | AF86: 0 | AG86: 0 | AH86: 23.8 | AI86: 0 | AJ86: 0.48 | AK86: 24.28 | AL86: 357.58 | AM86: No | AN86: 2.768 | AO86: Yes | AP86: No | AR86: 206500dc-ba9e-4a58-be62-bb3f830ec1f3,206500dc-ba9e-4a58-be62-bb3f830ec1f3 | AS86: No | AW86: Yes | AX86: No
A87: 216200550261108 | C87: 2025-09-07 13:12:30 | D87: delivered | E87: regular | H87: SWIGGYIT | I87: 595 | J87: 20 | K87: 64 | L87: 0 | M87: 64 | N87: 551 | O87: 27.56 | P87: 578.56 | Q87: 578.56 | R87: 20.0% | S87: 115.71 | T87: 0 | U87: 0 | V87: 0 | W87: 0 | X87: 0 | Y87: 0 | Z87: 0 | AA87: 0 | AB87: 0 | AC87: 20.82 | AD87: 136.53 | AE87: 0 | AF87: 0 | AG87: 0 | AH87: 27.55 | AI87: 0 | AJ87: 0.55 | AK87: 28.1 | AL87: 413.9 | AM87: No | AN87: 4.805 | AO87: Yes | AP87: No | AR87: afaa29fc-bc1c-47c6-aac0-77cf21844dde,206500dc-ba9e-4a58-be62-bb3f830ec1f3,afaa29fc-bc1c-47c6-aac0-77cf21844dde,206500dc-ba9e-4a58-be62-bb3f830ec1f3 | AS87: No | AW87: Yes | AX87: No
A88: 216200555444629 | C88: 2025-09-07 13:12:35 | D88: delivered | E88: regular | H88: MISSEDYOU | I88: 475 | J88: 15 | K88: 64 | L88: 0 | M88: 64 | N88: 426 | O88: 21.3 | P88: 447.3 | Q88: 447.3 | R88: 22.0% | S88: 98.41 | T88: 0 | U88: 0 | V88: 0 | W88: 0 | X88: 0 | Y88: 0 | Z88: 0 | AA88: 0 | AB88: 0 | AC88: 17.72 | AD88: 116.13 | AE88: 0 | AF88: 0 | AG88: 0 | AH88: 21.3 | AI88: 0 | AJ88: 0.43 | AK88: 21.73 | AL88: 309.46 | AM88: No | AN88: 2.743 | AO88: Yes | AP88: No | AR88: 206500dc-ba9e-4a58-be62-bb3f830ec1f3,206500dc-ba9e-4a58-be62-bb3f830ec1f3 | AS88: No | AW88: Yes | AX88: No
A89: 216200597239180 | C89: 2025-09-07 13:13:17 | D89: delivered | E89: regular | H89: XTRAPARTY | I89: 4790 | J89: 206 | K89: 502.92 | L89: 325.69 | M89: 828.61 | N89: 4167.39 | O89: 208.36 | P89: 4375.748 | Q89: 4375.75 | R89: 10.0% | S89: 437.58 | T89: 7 | U89: 0 | V89: 0 | W89: 0 | X89: 0 | Y89: 0 | Z89: 0 | AA89: 0 | AB89: 0 | AC89: 80.02 | AD89: 524.6 | AE89: 0 | AF89: 0 | AG89: 0 | AH89: 208.37 | AI89: 0 | AJ89: 4.17 | AK89: 212.54 | AL89: 3638.61 | AM89: Yes | AN89: 6.456 | AO89: Yes | AP89: No | AR89: 206500dc-ba9e-4a58-be62-bb3f830ec1f3,d0c8ce29-e7da-4899-b002-bc56925f059c,206500dc-ba9e-4a58-be62-bb3f830ec1f3,d0c8ce29-e7da-4899-b002-bc56925f059c | AS89: No | AW89: Yes | AX89: No
A90: 216200600528863 | C90: 2025-09-07 13:13:20 | D90: delivered | E90: regular | H90: MISSEDYOU | I90: 450 | J90: 20 | K90: 64 | L90: 0 | M90: 64 | N90: 406 | O90: 20.3 | P90: 426.3 | Q90: 426.3 | R90: 22.0% | S90: 93.79 | T90: 20 | U90: 0 | V90: 0 | W90: 0 | X90: 0 | Y90: 0 | Z90: 0 | AA90: 0 | AB90: 0 | AC90: 20.48 | AD90: 134.27 | AE90: 0 | AF90: 0 | AG90: 0 | AH90: 20.3 | AI90: 0 | AJ90: 0.41 | AK90: 20.71 | AL90: 271.32 | AM90: Yes | AN90: 11.988 | AO90: Yes | AP90: No | AR90: 100833489 | AS90: No | AW90: Yes | AX90: No
A91: 216200670862130 | C91: 2025-09-07 13:14:30 | D91: delivered | E91: regular | H91: FLAVORFUL | I91: 1035 | J91: 45 | K91: 99.99 | L91: 0 | M91: 99.99 | N91: 980.01 | O91: 49 | P91: 1029.008 | Q91: 1029.01 | R91: 16.0% | S91: 164.64 | T91: 0 | U91: 0 | V91: 0 | W91: 0 | X91: 0 | Y91: 0 | Z91: 0 | AA91: 0 | AB91: 0 | AC91: 29.64 | AD91: 194.28 | AE91: 0 | AF91: 0 | AG91: 0 | AH91: 49 | AI91: 0 | AJ91: 0.98 | AK91: 49.98 | AL91: 784.75 | AM91: No | AN91: 2.743 | AO91: Yes | AP91: No | AR91: 1513618b-f015-4d89-a9a7-5b4ca343881b,1513618b-f015-4d89-a9a7-5b4ca343881b | AS91: No | AW91: Yes | AX91: No
... A94: 216200973953191 | C94: 2025-09-07 13:19:33 | D94: delivered | E94: regular | H94: FLAVORFUL | I94: 940 | J94: 30 | K94: 99.99 | L94: 0 | M94: 99.99 | N94: 870.01 | O94: 43.5 | P94: 913.508 | Q94: 913.51 | R94: 16.0% | S94: 146.16 | T94: 0 | U94: 0 | V94: 0 | W94: 0 | X94: 0 | Y94: 0 | Z94: 0 | AA94: 0 | AB94: 0 | AC94: 26.3 | AD94: 172.46 | AE94: 0 | AF94: 0 | AG94: 0 | AH94: 43.5 | AI94: 0 | AJ94: 0.87 | AK94: 44.37 | AL94: 696.66 | AM94: No | AN94: 3.989 | AO94: Yes | AP94: No | AR94: 206500dc-ba9e-4a58-be62-bb3f830ec1f3,206500dc-ba9e-4a58-be62-bb3f830ec1f3 | AS94: No | AW94: Yes | AX94: No
A95: 216201024285791 | C95: 2025-09-07 13:20:24 | D95: delivered | E95: regular | I95: 950 | J95: 30 | K95: 0 | L95: 0 | M95: 0 | N95: 980 | O95: 49 | P95: 1029 | Q95: 1029 | R95: 16.0% | S95: 164.64 | T95: 0 | U95: 0 | V95: 0 | W95: 0 | X95: 0 | Y95: 0 | Z95: 0 | AA95: 0 | AB95: 0 | AC95: 29.64 | AD95: 194.28 | AE95: 0 | AF95: 0 | AG95: 0 | AH95: 49 | AI95: 0 | AJ95: 0.98 | AK95: 49.98 | AL95: 784.74 | AM95: No | AN95: 5.103 | AO95: Yes | AP95: No | AR95: 206500dc-ba9e-4a58-be62-bb3f830ec1f3 | AS95: No | AW95: Yes | AX95: No
A96: 216201061618061 | C96: 2025-09-07 13:21:01 | D96: delivered | E96: regular | I96: 245 | J96: 10 | K96: 0 | L96: 0 | M96: 0 | N96: 255 | O96: 12.76 | P96: 267.76 | Q96: 267.76 | R96: 22.0% | S96: 58.91 | T96: 0 | U96: 0 | V96: 0 | W96: 0 | X96: 0 | Y96: 0 | Z96: 0 | AA96: 0 | AB96: 0 | AC96: 10.6 | AD96: 69.51 | AE96: 0 | AF96: 0 | AG96: 0 | AH96: 12.75 | AI96: 0 | AJ96: 0.26 | AK96: 13.01 | AL96: 185.23 | AM96: No | AN96: 5.182 | AO96: Yes | AP96: No | AR96: b7a7c44d-6f0c-4301-be7e-fd1c61ddc821,206500dc-ba9e-4a58-be62-bb3f830ec1f3 | AS96: Yes | AT96: 216197974850379 | AW96: Yes | AX96: No
A97: 216201123804859 | C97: 2025-09-07 13:22:03 | D97: delivered | E97: regular | H97: FLAVORFUL | I97: 720 | J97: 30 | K97: 99.99 | L97: 0 | M97: 99.99 | N97: 650.01 | O97: 32.5 | P97: 682.508 | Q97: 682.51 | R97: 20.0% | S97: 136.5 | T97: 7 | U97: 0 | V97: 0 | W97: 0 | X97: 0 | Y97: 0 | Z97: 0 | AA97: 0 | AB97: 0 | AC97: 25.84 | AD97: 169.34 | AE97: 0 | AF97: 0 | AG97: 0 | AH97: 32.5 | AI97: 0 | AJ97: 0.65 | AK97: 33.15 | AL97: 480.04 | AM97: Yes | AN97: 6.342 | AO97: Yes | AP97: No | AR97: 103197863 | AS97: No | AW97: No | AX97: No
A98: 216201284949210 | C98: 2025-09-07 13:24:44 | D98: delivered | E98: regular | H98: FLAVORFUL | I98: 820 | J98: 30 | K98: 99.99 | L98: 0 | M98: 99.99 | N98: 750.01 | O98: 37.5 | P98: 787.508 | Q98: 787.51 | R98: 20.0% | S98: 157.5 | T98: 12 | U98: 0 | V98: 0 | W98: 0 | X98: 0 | Y98: 0 | Z98: 0 | AA98: 0 | AB98: 0 | AC98: 30.5 | AD98: 200 | AE98: 0 | AF98: 0 | AG98: 0 | AH98: 37.5 | AI98: 0 | AJ98: 0.75 | AK98: 38.25 | AL98: 549.24 | AM98: Yes | AN98: 8.907 | AO98: Yes | AP98: No | AR98: 103197863 | AS98: No | AW98: No | AX98: No
A99: 216201304077118 | C99: 2025-09-07 13:25:04 | D99: delivered | E99: regular | H99: FLAVORFUL | I99: 1050 | J99: 30 | K99: 99.99 | L99: 0 | M99: 99.99 | N99: 980.01 | O99: 49 | P99: 1029.008 | Q99: 1029.01 | R99: 16.0% | S99: 164.64 | T99: 0 | U99: 0 | V99: 0 | W99: 0 | X99: 0 | Y99: 0 | Z99: 0 | AA99: 0 | AB99: 0 | AC99: 29.64 | AD99: 194.28 | AE99: 0 | AF99: 0 | AG99: 0 | AH99: 49 | AI99: 0 | AJ99: 0.98 | AK99: 49.98 | AL99: 784.75 | AM99: No | AN99: 4.686 | AO99: Yes | AP99: No | AR99: b4033a24-7d8b-4e42-ad89-726a3cb02228,206500dc-ba9e-4a58-be62-bb3f830ec1f3,b4033a24-7d8b-4e42-ad89-726a3cb02228,206500dc-ba9e-4a58-be62-bb3f830ec1f3 | AS99: No | AW99: Yes | AX99: No
A100: 216201323553222 | C100: 2025-09-07 13:25:23 | D100: delivered | E100: regular | H100: FLAVORFUL | I100: 940 | J100: 30 | K100: 99.99 | L100: 0 | M100: 99.99 | N100: 870.01 | O100: 43.5 | P100: 913.508 | Q100: 913.51 | R100: 16.0% | S100: 146.16 | T100: 0 | U100: 0 | V100: 0 | W100: 0 | X100: 0 | Y100: 0 | Z100: 0 | AA100: 0 | AB100: 0 | AC100: 26.3 | AD100: 172.46 | AE100: 0 | AF100: 0 | AG100: 0 | AH100: 43.5 | AI100: 0 | AJ100: 0.87 | AK100: 44.37 | AL100: 696.66 | AM100: No | AN100: 2.743 | AO100: Yes | AP100: No | AR100: 1820a811-55f2-4fb6-9694-7cd7e72a5efa,206500dc-ba9e-4a58-be62-bb3f830ec1f3,1820a811-55f2-4fb6-9694-7cd7e72a5efa,206500dc-ba9e-4a58-be62-bb3f830ec1f3 | AS100: No | AW100: Yes | AX100: No
A101: 216201360793457 | C101: 2025-09-07 13:26:00 | D101: delivered | E101: regular | H101: MISSEDYOU | I101: 540 | J101: 25 | K101: 63.99 | L101: 0 | M101: 63.99 | N101: 501.01 | O101: 25.06 | P101: 526.068 | Q101: 526.07 | R101: 20.0% | S101: 105.21 | T101: 0 | U101: 0 | V101: 0 | W101: 0 | X101: 0 | Y101: 0 | Z101: 0 | AA101: 0 | AB101: 0 | AC101: 18.94 | AD101: 124.15 | AE101: 0 | AF101: 0 | AG101: 0 | AH101: 25.05 | AI101: 0 | AJ101: 0.5 | AK101: 25.55 | AL101: 376.36 | AM101: No | AN101: 2.56 | AO101: Yes | AP101: No | AR101: 206500dc-ba9e-4a58-be62-bb3f830ec1f3,206500dc-ba9e-4a58-be62-bb3f830ec1f3 | AS101: No | AW101: Yes | AX101: No
A102: 216201370083813 | C102: 2025-09-07 13:26:10 | D102: delivered | E102: regular | I102: 445 | J102: 15 | K102: 0 | L102: 0 | M102: 0 | N102: 460 | O102: 23 | P102: 483 | Q102: 483 | R102: 22.0% | S102: 106.26 | T102: 12 | U102: 0 | V102: 0 | W102: 0 | X102: 0 | Y102: 0 | Z102: 0 | AA102: 0 | AB102: 0 | AC102: 21.28 | AD102: 139.54 | AE102: 0 | AF102: 0 | AG102: 0 | AH102: 23 | AI102: 0 | AJ102: 0.46 | AK102: 23.46 | AL102: 319.98 | AM102: Yes | AN102: 8.035 | AO102: Yes | AP102: No | AR102: 206500dc-ba9e-4a58-be62-bb3f830ec1f3 | AS102: No | AW102: Yes | AX102: No
...

Sheet D2W2
A1: Adjustments this week
A2: Adjustment Type | B2: Total Amount | C2: Settled Amount | D2: Outstanding Amount | E2: Period From | F2: Period To | G2: Invoice Number | H2: Remarks
A3: CPC Ads | B3: ₹-4856.880000000001 | C3: ₹-4856.88 | D3: ₹0.0 | E3: 2025-09-07 | F3: 2025-09-13 | G3: 250917FS36003881 | H3: CPC Ads for service period 07 September 2025 to 13 September 2025
A4: CPC Ads | B4: ₹-7929.600000000001 | C4: ₹-7929.6 | D4: ₹0.0 | E4: 2025-09-07 | F4: 2025-09-13 | G4: 250917FS36003881 | H4: CPC Ads for service period 07 September 2025 to 13 September 2025
A5: CPC Ads | B5: ₹-5468.120000000001 | C5: ₹-5468.12 | D5: ₹0.0 | E5: 2025-09-07 | F5: 2025-09-13 | G5: 250917FS36003881 | H5: CPC Ads for service period 07 September 2025 to 13 September 2025
A6: CPC Ads | B6: ₹-6558.4400000000005 | C6: ₹-6558.44 | D6: ₹0.0 | E6: 2025-09-07 | F6: 2025-09-13 | G6: 250917FS36003881 | H6: CPC Ads for service period 07 September 2025 to 13 September 2025
A7: CPC Ads | B7: ₹-5468.120000000001 | C7: ₹-5468.12 | D7: ₹0.0 | E7: 2025-09-07 | F7: 2025-09-13 | G7: 250917FS36003881 | H7: CPC Ads for service period 07 September 2025 to 13 September 2025
A8: CPC Ads | B8: ₹-6574.960000000001 | C8: ₹-6574.96 | D8: ₹0.0 | E8: 2025-09-07 | F8: 2025-09-13 | G8: 250917FS36003881 | H8: CPC Ads for service period 07 September 2025 to 13 September 2025
A9: CPC Ads | B9: ₹-4856.880000000001 | C9: ₹-4856.88 | D9: ₹0.0 | E9: 2025-09-07 | F9: 2025-09-13 | G9: 250917FS36003881 | H9: CPC Ads for service period 07 September 2025 to 13 September 2025
A11: Adjustments from previous week
A12: Adjusment Type | B12: Total Amount | C12: Settled Amount | D12: Outstanding Amount | E12: Period From | F12: Period To | G12: Invoice Number | H12: Remarks
A14: Total Adjustments | B14: ₹-41713.0 | C14: ₹-41713.0 | D14: ₹0.0

Sheet D1W3
I1: 7270 | J1: 274 | K1: 693.44 | L1: 0 | M1: 693.44 | N1: 6850.56 | O1: 342.58 | P1: 7193.128 | Q1: 6529.54 | R1: 0 | S1: 1212.9 | T1: 0 | U1: 0 | V1: 0 | W1: 0 | X1: 0 | Y1: 0 | Z1: 0 | AA1: 0 | AB1: 0 | AC1: 218.36 | AD1: 1431.26 | AE1: 663.6 | AF1: 0 | AG1: 663.6 | AH1: 310.92 | AI1: 0 | AJ1: 6 | AK1: 316.92 | AL1: 4781.31 | AM1: 0 | AN1: 67.357 | AO1: 0 | AP1: 0 | AQ1: 0 | AR1: 0 | AS1: 0 | AT1: 0 | AU1: 821.9 | AV1: 0 | AW1: 0 | AX1: 0 | AY1: 0 | AZ1: 0 | BA1: 0 | BB1: 0 | BC1: 0 | BD1: 0 | BE1: 0 | BF1: 0 | BG1: 0 | BH1: 0 | BI1: 0 | BJ1: 0 | BK1: 0 | BL1: 0 | BM1: 0 | BN1: 0 | BO1: 0 | BP1: 0 | BQ1: 0 | BR1: 0 | BS1: 0 | BT1: 0 | BU1: 0 | BV1: 0 | BW1: 0 | BX1: 0 | BY1: 0 | BZ1: 0 | CA1: 0 | CB1: 0 | CC1: 0
I2: 1097495 | J2: 39637 | K2: 107778.84 | L2: 2566.22 | M2: 110345.05 | N2: 1026786.9 | O2: 51343.12 | P2: 1078129.3 | Q2: 1078129.2 | R2: 0 | S2: 187994.66 | T2: 4143 | U2: 0 | V2: 0 | W2: 0 | X2: 0 | Y2: 0 | Z2: 0 | AA2: 0 | AB2: 0 | AC2: 34582.68 | AD2: 226720.34 | AE2: 0 | AF2: 936 | AG2: 936 | AH2: 51339.15 | AI2: 0 | AJ2: 1029.26 | AK2: 52368.41 | AL2: 798097.97 | AM2: 0 | AN2: 6937.821 | AO2: 0 | AP2: 0 | AQ2: 0 | AR2: 0 | AS2: 0 | AT2: 0 | AU2: 0 | AV2: 0 | AW2: 0 | AX2: 0 | AY2: 0 | AZ2: 0 | BA2: 0 | BB2: 0 | BC2: 0 | BD2: 0 | BE2: 0 | BF2: 0 | BG2: 0 | BH2: 0 | BI2: 0 | BJ2: 0 | BK2: 0 | BL2: 0 | BM2: 0 | BN2: 0 | BO2: 0 | BP2: 0 | BQ2: 0 | BR2: 0 | BS2: 0 | BT2: 0 | BU2: 0 | BV2: 0 | BW2: 0 | BX2: 0 | BY2: 0 | BZ2: 0 | CA2: 0 | CB2: 0 | CC2: 0
I3: 1303622.7 | J3: 47094.98 | K3: 127997.29 | L3: 3028.1396 | M3: 131025.42 | N3: 1219692.3 | O3: 60989.126 | P3: 1280680.5 | Q3: 1279897.3 | R3: 0 | S3: 223264.92 | T3: 4888.74 | U3: 0 | V3: 0 | W3: 0 | X3: 0 | Y3: 0 | Z3: 0 | AA3: 0 | AB3: 0 | AC3: 41065.227 | AD3: 269218.89 | AE3: 783.048 | AF3: 1104.48 | AG3: 1887.528 | AH3: 60947.083 | AI3: 0 | AJ3: 1221.6068 | AK3: 62168.689 | AL3: 947397.55 | AM3: 0 | AN3: 8266.11 | AO3: 0 | AP3: 0 | AQ3: 0 | AR3: 0 | AS3: 0 | AT3: 0 | AU3: 969.842 | AV3: 0 | AW3: 0 | AX3: 0 | AY3: 0 | AZ3: 0 | BA3: 0 | BB3: 0 | BC3: 0 | BD3: 0 | BE3: 0 | BF3: 0 | BG3: 0 | BH3: 0 | BI3: 0 | BJ3: 0 | BK3: 0 | BL3: 0 | BM3: 0 | BN3: 0 | BO3: 0 | BP3: 0 | BQ3: 0 | BR3: 0 | BS3: 0 | BT3: 0 | BU3: 0 | BV3: 0 | BW3: 0 | BX3: 0 | BY3: 0 | BZ3: 0 | CA3: 0 | CB3: 0 | CC3: 0
I4: 1104765 | J4: 39911 | K4: 108472.28 | L4: 2566.22 | M4: 111038.49 | N4: 1033637.5 | O4: 51685.7 | P4: 1085322.5 | Q4: 1084658.8 | R4: 0 | S4: 189207.56 | T4: 4143 | U4: 0 | V4: 0 | W4: 0 | X4: 0 | Y4: 0 | Z4: 0 | AA4: 0 | AB4: 0 | AC4: 34801.04 | AD4: 228151.6 | AE4: 663.6 | AF4: 936 | AG4: 1599.6 | AH4: 51650.07 | AI4: 0 | AJ4: 1035.26 | AK4: 52685.33 | AL4: 802879.28 | AM4: 0 | AN4: 7005.178 | AO4: 0 | AP4: 0 | AQ4: 0 | AR4: 0 | AS4: 0 | AT4: 0 | AU4: 821.9 | AV4: 0 | AW4: 0 | AX4: 0 | AY4: 0 | AZ4: 0 | BA4: 0 | BB4: 0 | BC4: 0 | BD4: 0 | BE4: 0 | BF4: 0 | BG4: 0 | BH4: 0 | BI4: 0 | BJ4: 0 | BK4: 0 | BL4: 0 | BM4: 0 | BN4: 0 | BO4: 0 | BP4: 0 | BQ4: 0 | BR4: 0 | BS4: 0 | BT4: 0 | BU4: 0 | BV4: 0 | BW4: 0 | BX4: 0 | BY4: 0 | BZ4: 0 | CA4: 0 | CB4: 0 | CC4: 0
A5: Order ID | B5: Parent Order ID | C5: Order Date | D5: Order Status | E5: Order Category | F5: Order Payment Type | G5: Cancelled By? | H5: Coupon type applied by customer | I5: Item Total | J5: Packaging Charges | K5: Restaurant Discounts (Promo, Freebies, Flat Off, etc.) | L5: Swiggy One Exclusive Offer Discount | M5: Restaurant Discount Share [3a+3b] | N5: Net Bill Value (before taxes) [1+2-3] | O5: GST Collected | P5: Total Customer Paid [4+5] | Q5: Commission charged on | R5: Service Fees % | S5: Commission | T5: Long Distance Charges | U5: Discount on Long Distance Fee | V5: Pocket Hero Fees | W5: Swiggy One Fees | X5: Payment Collection Charges | Y5: Restaurant Cancellation Charges | Z5: Call Center Charges | AA5: Delivery Fee sponsored by Restaurant (w/o tax) | AB5: Bolt Fees | AC5: GST on Service Fee @18% | AD5: Total Swiggy Fees [6+7+8-9+10+11+12+13+14+15+16] | AE5: Customer Cancellations | AF5: Customer Complaints | AG5: Complaint & Cancellation Charges [17+18] | AH5: GST Deduction | AI5: TCS | AJ5: TDS | AK5: Total Taxes [19+20+21] | AL5: Net Payout for Order (after taxes) [A-B-C-D] | AM5: Long Distance Order | AN5: Last Mile (in km) | AO5: MFR Accurate? | AP5: MFR Pressed? | AQ5: Coupon Code Sourced | AR5: Discount Campaign ID | AS5: Replicated Order | AT5: Base order ID | AU5: Cancellation time | AV5: Pick Up Status | AW5: Swiggy One Customer? | AX5: Pocket Hero Order?
A6: 216668091624756 | C6: 2025-09-12 23:04:51 | D6: delivered | E6: regular | H6: SWIGGYIT | I6: 395 | J6: 15 | K6: 64 | L6: 0 | M6: 64 | N6: 346 | O6: 17.3 | P6: 363.3 | Q6: 363.3 | R6: 22.0% | S6: 79.93 | T6: 0 | U6: 0 | V6: 0 | W6: 0 | X6: 0 | Y6: 0 | Z6: 0 | AA6: 0 | AB6: 0 | AC6: 14.38 | AD6: 94.31 | AE6: 0 | AF6: 0 | AG6: 0 | AH6: 17.3 | AI6: 0 | AJ6: 0.35 | AK6: 17.65 | AL6: 251.33 | AM6: No | AN6: 2.751 | AO6: Yes | AP6: No | AR6: 206500dc-ba9e-4a58-be62-bb3f830ec1f3,206500dc-ba9e-4a58-be62-bb3f830ec1f3 | AS6: No | AW6: Yes | AX6: No
A7: 216754635315387 | C7: 2025-09-13 23:07:15 | D7: delivered | E7: regular | H7: TRYNEW | I7: 445 | J7: 15 | K7: 64 | L7: 0 | M7: 64 | N7: 396 | O7: 19.8 | P7: 415.8 | Q7: 415.8 | R7: 22.0% | S7: 91.48 | T7: 0 | U7: 0 | V7: 0 | W7: 0 | X7: 0 | Y7: 0 | Z7: 0 | AA7: 0 | AB7: 0 | AC7: 16.46 | AD7: 107.94 | AE7: 0 | AF7: 83 | AG7: 83 | AH7: 19.8 | AI7: 0 | AJ7: 0.4 | AK7: 20.2 | AL7: 204.65 | AM7: No | AN7: 4.192 | AO7: Yes | AP7: No | AR7: 206500dc-ba9e-4a58-be62-bb3f830ec1f3,206500dc-ba9e-4a58-be62-bb3f830ec1f3 | AS7: No | AW7: Yes | AX7: No
A8: 216799557850606 | C8: 2025-09-14 11:35:57 | D8: delivered | E8: regular | H8: PARTY | I8: 2060 | J8: 65 | K8: 206 | L8: 0 | M8: 206 | N8: 1919 | O8: 95.96 | P8: 2014.96 | Q8: 2014.96 | R8: 12.0% | S8: 241.8 | T8: 12 | U8: 0 | V8: 0 | W8: 0 | X8: 0 | Y8: 0 | Z8: 0 | AA8: 0 | AB8: 0 | AC8: 45.68 | AD8: 299.48 | AE8: 0 | AF8: 0 | AG8: 0 | AH8: 95.95 | AI8: 0 | AJ8: 1.92 | AK8: 97.87 | AL8: 1617.6 | AM8: Yes | AN8: 8.185 | AO8: Yes | AP8: No | AR8: 108830926 | AS8: No | AW8: Yes | AX8: No
A9: 216799600967608 | C9: 2025-09-14 11:36:40 | D9: delivered | E9: regular | H9: FLAVORFUL | I9: 965 | J9: 40 | K9: 99.98 | L9: 0 | M9: 99.98 | N9: 905.02 | O9: 45.26 | P9: 950.276 | Q9: 950.28 | R9: 16.0% | S9: 152.04 | T9: 30 | U9: 0 | V9: 0 | W9: 0 | X9: 0 | Y9: 0 | Z9: 0 | AA9: 0 | AB9: 0 | AC9: 32.76 | AD9: 214.8 | AE9: 0 | AF9: 0 | AG9: 0 | AH9: 45.25 | AI9: 0 | AJ9: 0.91 | AK9: 46.16 | AL9: 689.3 | AM9: Yes | AN9: 13.572 | AO9: Yes | AP9: No | AR9: 103197863 | AS9: No | AW9: Yes | AX9: No
A10: 216799635453209 | C10: 2025-09-14 11:37:15 | D10: delivered | E10: regular | H10: SWIGGYIT | I10: 600 | J10: 25 | K10: 64 | L10: 0 | M10: 64 | N10: 561 | O10: 28.06 | P10: 589.06 | Q10: 589.06 | R10: 20.0% | S10: 117.81 | T10: 0 | U10: 0 | V10: 0 | W10: 0 | X10: 0 | Y10: 0 | Z10: 0 | AA10: 0 | AB10: 0 | AC10: 21.2 | AD10: 139.01 | AE10: 0 | AF10: 0 | AG10: 0 | AH10: 28.05 | AI10: 0 | AJ10: 0.56 | AK10: 28.61 | AL10: 421.41 | AM10: No | AN10: 2.768 | AO10: Yes | AP10: No | AR10: 206500dc-ba9e-4a58-be62-bb3f830ec1f3,206500dc-ba9e-4a58-be62-bb3f830ec1f3 | AS10: No | AW10: Yes | AX10: No
A11: 216801150054441 | C11: 2025-09-14 12:02:30 | D11: delivered | E11: regular | H11: SWIGGYIT | I11: 445 | J11: 15 | K11: 64 | L11: 0 | M11: 64 | N11: 396 | O11: 19.8 | P11: 415.8 | Q11: 415.8 | R11: 22.0% | S11: 91.48 | T11: 0 | U11: 0 | V11: 0 | W11: 0 | X11: 0 | Y11: 0 | Z11: 0 | AA11: 0 | AB11: 0 | AC11: 16.46 | AD11: 107.94 | AE11: 0 | AF11: 0 | AG11: 0 | AH11: 19.8 | AI11: 0 | AJ11: 0.4 | AK11: 20.2 | AL11: 287.65 | AM11: No | AN11: 2.86 | AO11: Yes | AP11: No | AR11: 206500dc-ba9e-4a58-be62-bb3f830ec1f3,206500dc-ba9e-4a58-be62-bb3f830ec1f3 | AS11: No | AW11: Yes | AX11: No
A12: 216801157821444 | C12: 2025-09-14 12:02:37 | D12: delivered | E12: regular | H12: SWIGGYIT | I12: 495 | J12: 15 | K12: 64 | L12: 0 | M12: 64 | N12: 446 | O12: 22.3 | P12: 468.3 | Q12: 468.3 | R12: 22.0% | S12: 103.03 | T12: 0 | U12: 0 | V12: 0 | W12: 0 | X12: 0 | Y12: 0 | Z12: 0 | AA12: 0 | AB12: 0 | AC12: 18.54 | AD12: 121.57 | AE12: 0 | AF12: 0 | AG12: 0 | AH12: 22.3 | AI12: 0 | AJ12: 0.45 | AK12: 22.75 | AL12: 323.97 | AM12: No | AN12: 3.557 | AO12: Yes | AP12: No | AR12: 7579b951-953f-47b6-8456-cae125b0a66d,206500dc-ba9e-4a58-be62-bb3f830ec1f3,7579b951-953f-47b6-8456-cae125b0a66d,206500dc-ba9e-4a58-be62-bb3f830ec1f3 | AS12: No | AW12: Yes | AX12: No
A13: 216801198572911 | C13: 2025-09-14 12:03:18 | D13: delivered | E13: regular | H13: MISSEDYOU | I13: 375 | J13: 15 | K13: 64 | L13: 0 | M13: 64 | N13: 326 | O13: 16.3 | P13: 342.3 | Q13: 342.3 | R13: 22.0% | S13: 75.31 | T13: 12 | U13: 0 | V13: 0 | W13: 0 | X13: 0 | Y13: 0 | Z13: 0 | AA13: 0 | AB13: 0 | AC13: 15.72 | AD13: 103.03 | AE13: 0 | AF13: 0 | AG13: 0 | AH13: 16.3 | AI13: 0 | AJ13: 0.33 | AK13: 16.63 | AL13: 222.65 | AM13: Yes | AN13: 9.062 | AO13: Yes | AP13: No | AR13: 100833489 | AS13: No | AW13: Yes | AX13: No
A14: 216801260098839 | C14: 2025-09-14 12:04:20 | D14: delivered | E14: regular | H14: SWIGGYIT | I14: 495 | J14: 15 | K14: 64 | L14: 0 | M14: 64 | N14: 446 | O14: 22.3 | P14: 468.3 | Q14: 468.3 | R14: 22.0% | S14: 103.03 | T14: 0 | U14: 0 | V14: 0 | W14: 0 | X14: 0 | Y14: 0 | Z14: 0 | AA14: 0 | AB14: 0 | AC14: 18.54 | AD14: 121.57 | AE14: 0 | AF14: 0 | AG14: 0 | AH14: 22.3 | AI14: 0 | AJ14: 0.45 | AK14: 22.75 | AL14: 323.97 | AM14: No | AN14: 4.628 | AO14: Yes | AP14: No | AR14: 206500dc-ba9e-4a58-be62-bb3f830ec1f3,206500dc-ba9e-4a58-be62-bb3f830ec1f3 | AS14: No | AW14: Yes | AX14: No
A15: 216801274317158 | C15: 2025-09-14 12:04:34 | D15: delivered | E15: regular | H15: FLAVORFUL | I15: 870 | J15: 30 | K15: 99.99 | L15: 0 | M15: 99.99 | N15: 800.01 | O15: 40 | P15: 840.008 | Q15: 840.01 | R15: 20.0% | S15: 168 | T15: 0 | U15: 0 | V15: 0 | W15: 0 | X15: 0 | Y15: 0 | Z15: 0 | AA15: 0 | AB15: 0 | AC15: 30.24 | AD15: 198.24 | AE15: 0 | AF15: 0 | AG15: 0 | AH15: 40 | AI15: 0 | AJ15: 0.8 | AK15: 40.8 | AL15: 600.97 | AM15: No | AN15: 2.768 | AO15: Yes | AP15: No | AR15: 206500dc-ba9e-4a58-be62-bb3f830ec1f3,206500dc-ba9e-4a58-be62-bb3f830ec1f3 | AS15: No | AW15: Yes | AX15: No
A16: 216801418125968 | C16: 2025-09-14 12:06:58 | D16: delivered | E16: regular | H16: FLAVORFUL | I16: 1415 | J16: 50 | K16: 99.98 | L16: 0 | M16: 99.98 | N16: 1365.02 | O16: 68.26 | P16: 1433.276 | Q16: 1433.28 | R16: 14.0% | S16: 200.66 | T16: 30 | U16: 0 | V16: 0 | W16: 0 | X16: 0 | Y16: 0 | Z16: 0 | AA16: 0 | AB16: 0 | AC16: 41.52 | AD16: 272.18 | AE16: 0 | AF16: 0 | AG16: 0 | AH16: 68.25 | AI16: 0 | AJ16: 1.37 | AK16: 69.62 | AL16: 1091.48 | AM16: Yes | AN16: 14.135 | AO16: Yes | AP16: No | AR16: 103197863 | AS16: No | AW16: Yes | AX16: No
A17: 216801421920391 | C17: 2025-09-14 12:07:01 | D17: delivered | E17: regular | I17: 1020 | J17: 37 | K17: 0 | L17: 0 | M17: 0 | N17: 1057 | O17: 52.86 | P17: 1109.86 | Q17: 1109.86 | R17: 16.0% | S17: 177.58 | T17: 12 | U17: 0 | V17: 0 | W17: 0 | X17: 0 | Y17: 0 | Z17: 0 | AA17: 0 | AB17: 0 | AC17: 34.12 | AD17: 223.7 | AE17: 0 | AF17: 0 | AG17: 0 | AH17: 52.85 | AI17: 0 | AJ17: 1.06 | AK17: 53.91 | AL17: 832.24 | AM17: Yes | AN17: 9.189 | AO17: Yes | AP17: No | AS17: No | AW17: No | AX17: No
A18: 216801556147063 | C18: 2025-09-14 12:09:16 | D18: delivered | E18: regular | H18: TRYNEW | I18: 475 | J18: 15 | K18: 64 | L18: 0 | M18: 64 | N18: 426 | O18: 21.3 | P18: 447.3 | Q18: 447.3 | R18: 22.0% | S18: 98.41 | T18: 7 | U18: 0 | V18: 0 | W18: 0 | X18: 0 | Y18: 0 | Z18: 0 | AA18: 0 | AB18: 0 | AC18: 18.98 | AD18: 124.39 | AE18: 0 | AF18: 0 | AG18: 0 | AH18: 21.3 | AI18: 0 | AJ18: 0.43 | AK18: 21.73 | AL18: 301.2 | AM18: Yes | AN18: 7.313 | AO18: Yes | AP18: No | AR18: f238e1df-2a25-4850-ac0c-96018069644d,f238e1df-2a25-4850-ac0c-96018069644d | AS18: No | AW18: Yes | AX18: No
A19: 216801696205535 | C19: 2025-09-14 12:11:36 | D19: delivered | E19: regular | H19: FLAVORFUL | I19: 820 | J19: 30 | K19: 99.99 | L19: 0 | M19: 99.99 | N19: 750.01 | O19: 37.5 | P19: 787.508 | Q19: 787.51 | R19: 20.0% | S19: 157.5 | T19: 7 | U19: 0 | V19: 0 | W19: 0 | X19: 0 | Y19: 0 | Z19: 0 | AA19: 0 | AB19: 0 | AC19: 29.62 | AD19: 194.12 | AE19: 0 | AF19: 0 | AG19: 0 | AH19: 37.5 | AI19: 0 | AJ19: 0.75 | AK19: 38.25 | AL19: 555.14 | AM19: Yes | AN19: 7.522 | AO19: Yes | AP19: No | AR19: 1c54f9d1-402a-446c-9b55-d0e63ed9b3cf,1c54f9d1-402a-446c-9b55-d0e63ed9b3cf | AS19: No | AW19: Yes | AX19: No
A20: 216801709059692 | C20: 2025-09-14 12:11:49 | D20: delivered | E20: regular | H20: PARTY | I20: 1465 | J20: 45 | K20: 146.5 | L20: 0 | M20: 146.5 | N20: 1363.5 | O20: 68.18 | P20: 1431.68 | Q20: 1431.68 | R20: 14.0% | S20: 200.44 | T20: 12 | U20: 0 | V20: 0 | W20: 0 | X20: 0 | Y20: 0 | Z20: 0 | AA20: 0 | AB20: 0 | AC20: 38.24 | AD20: 250.68 | AE20: 0 | AF20: 259 | AG20: 259 | AH20: 68.17 | AI20: 0 | AJ20: 1.36 | AK20: 69.53 | AL20: 852.46 | AM20: Yes | AN20: 9.832 | AO20: Yes | AP20: No | AR20: 108830926 | AS20: No | AW20: Yes | AX20: No
A21: 216801758043156 | C21: 2025-09-14 12:12:38 | D21: delivered | E21: regular | I21: 2060 | J21: 75 | K21: 0 | L21: 0 | M21: 0 | N21: 2135 | O21: 106.76 | P21: 2241.76 | Q21: 2241.76 | R21: 12.0% | S21: 269.01 | T21: 0 | U21: 0 | V21: 0 | W21: 0 | X21: 0 | Y21: 0 | Z21: 0 | AA21: 0 | AB21: 0 | AC21: 48.42 | AD21: 317.43 | AE21: 0 | AF21: 0 | AG21: 0 | AH21: 106.75 | AI21: 0 | AJ21: 2.14 | AK21: 108.89 | AL21: 1815.43 | AM21: No | AN21: 3.701 | AO21: Yes | AP21: No | AR21: 206500dc-ba9e-4a58-be62-bb3f830ec1f3 | AS21: No | AW21: Yes | AX21: No
A22: 216801767813547 | C22: 2025-09-14 12:12:47 | D22: delivered | E22: regular | I22: 790 | J22: 30 | K22: 0 | L22: 0 | M22: 0 | N22: 820 | O22: 41 | P22: 861 | Q22: 861 | R22: 20.0% | S22: 172.2 | T22: 7 | U22: 0 | V22: 0 | W22: 0 | X22: 0 | Y22: 0 | Z22: 0 | AA22: 0 | AB22: 0 | AC22: 32.26 | AD22: 211.46 | AE22: 0 | AF22: 0 | AG22: 0 | AH22: 41 | AI22: 0 | AJ22: 0.82 | AK22: 41.82 | AL22: 607.72 | AM22: Yes | AN22: 6.519 | AO22: Yes | AP22: No | AR22: db612bd7-4c49-4328-afed-67fdb7138ab2 | AS22: No | AW22: No | AX22: No
A23: 216801779431475 | C23: 2025-09-14 12:12:59 | D23: delivered | E23: regular | H23: TRYNEW | I23: 445 | J23: 15 | K23: 64 | L23: 0 | M23: 64 | N23: 396 | O23: 19.8 | P23: 415.8 | Q23: 415.8 | R23: 22.0% | S23: 91.48 | T23: 0 | U23: 0 | V23: 0 | W23: 0 | X23: 0 | Y23: 0 | Z23: 0 | AA23: 0 | AB23: 0 | AC23: 16.46 | AD23: 107.94 | AE23: 0 | AF23: 0 | AG23: 0 | AH23: 19.8 | AI23: 0 | AJ23: 0.4 | AK23: 20.2 | AL23: 287.65 | AM23: No | AN23: 3.666 | AO23: Yes | AP23: No | AR23: 206500dc-ba9e-4a58-be62-bb3f830ec1f3,206500dc-ba9e-4a58-be62-bb3f830ec1f3 | AS23: No | AW23: Yes | AX23: No
A24: 216801780662782 | C24: 2025-09-14 12:13:00 | D24: delivered | E24: regular | H24: TRYNEW | I24: 445 | J24: 15 | K24: 64 | L24: 0 | M24: 64 | N24: 396 | O24: 19.8 | P24: 415.8 | Q24: 415.8 | R24: 22.0% | S24: 91.48 | T24: 12 | U24: 0 | V24: 0 | W24: 0 | X24: 0 | Y24: 0 | Z24: 0 | AA24: 0 | AB24: 0 | AC24: 18.62 | AD24: 122.1 | AE24: 0 | AF24: 0 | AG24: 0 | AH24: 19.8 | AI24: 0 | AJ24: 0.4 | AK24: 20.2 | AL24: 273.49 | AM24: Yes | AN24: 9.174 | AO24: Yes | AP24: No | AR24: 100833489 | AS24: No | AW24: Yes | AX24: No
A25: 216801795783228 | C25: 2025-09-14 12:13:15 | D25: delivered | E25: regular | H25: SWIGGYIT | I25: 375 | J25: 15 | K25: 64 | L25: 0 | M25: 64 | N25: 326 | O25: 16.3 | P25: 342.3 | Q25: 342.3 | R25: 22.0% | S25: 75.31 | T25: 7 | U25: 0 | V25: 0 | W25: 0 | X25: 0 | Y25: 0 | Z25: 0 | AA25: 0 | AB25: 0 | AC25: 14.82 | AD25: 97.13 | AE25: 0 | AF25: 0 | AG25: 0 | AH25: 16.3 | AI25: 0 | AJ25: 0.33 | AK25: 16.63 | AL25: 228.55 | AM25: Yes | AN25: 7.996 | AO25: Yes | AP25: No | AR25: 100833489 | AS25: No | AW25: Yes | AX25: No
A26: 216801816030048 | C26: 2025-09-14 12:13:36 | D26: delivered | E26: regular | I26: 475 | J26: 15 | K26: 0 | L26: 0 | M26: 0 | N26: 490 | O26: 24.5 | P26: 514.5 | Q26: 514.5 | R26: 20.0% | S26: 102.9 | T26: 20 | U26: 0 | V26: 0 | W26: 0 | X26: 0 | Y26: 0 | Z26: 0 | AA26: 0 | AB26: 0 | AC26: 22.12 | AD26: 145.02 | AE26: 0 | AF26: 0 | AG26: 0 | AH26: 24.5 | AI26: 0 | AJ26: 0.49 | AK26: 24.99 | AL26: 344.49 | AM26: Yes | AN26: 10.624 | AO26: Yes | AP26: No | AS26: No | AW26: Yes | AX26: No
A27: 216801825363310 | C27: 2025-09-14 12:13:45 | D27: delivered | E27: regular | H27: TOPUPOFFER | I27: 1345 | J27: 54 | K27: 63.98 | L27: 0 | M27: 63.98 | N27: 1335.02 | O27: 66.76 | P27: 1401.776 | Q27: 1401.78 | R27: 14.0% | S27: 196.25 | T27: 0 | U27: 0 | V27: 0 | W27: 0 | X27: 0 | Y27: 0 | Z27: 0 | AA27: 0 | AB27: 0 | AC27: 35.32 | AD27: 231.57 | AE27: 0 | AF27: 0 | AG27: 0 | AH27: 66.75 | AI27: 0 | AJ27: 1.34 | AK27: 68.09 | AL27: 1102.1 | AM27: No | AN27: 3.503 | AO27: Yes | AP27: No | AQ27: MISSEDYOU | AR27: 21229eab-43bd-4347-96b9-dfa4d0e5f288,206500dc-ba9e-4a58-be62-bb3f830ec1f3,21229eab-43bd-4347-96b9-dfa4d0e5f288,206500dc-ba9e-4a58-be62-bb3f830ec1f3 | AS27: No | AW27: Yes | AX27: No
A28: 216801845156442 | C28: 2025-09-14 12:14:05 | D28: delivered | E28: regular | H28: FLAVORFUL | I28: 800 | J28: 30 | K28: 99.99 | L28: 0 | M28: 99.99 | N28: 730.01 | O28: 36.5 | P28: 766.508 | Q28: 766.51 | R28: 20.0% | S28: 153.3 | T28: 30 | U28: 0 | V28: 0 | W28: 0 | X28: 0 | Y28: 0 | Z28: 0 | AA28: 0 | AB28: 0 | AC28: 33 | AD28: 216.3 | AE28: 0 | AF28: 0 | AG28: 0 | AH28: 36.5 | AI28: 0 | AJ28: 0.73 | AK28: 37.23 | AL28: 512.99 | AM28: Yes | AN28: 13.384 | AO28: Yes | AP28: No | AR28: 103197863 | AS28: No | AW28: Yes | AX28: No
A29: 216801894993797 | C29: 2025-09-14 12:14:54 | D29: delivered | E29: regular | H29: TRYNEW | I29: 395 | J29: 15 | K29: 64 | L29: 0 | M29: 64 | N29: 346 | O29: 17.3 | P29: 363.3 | Q29: 363.3 | R29: 22.0% | S29: 79.93 | T29: 20 | U29: 0 | V29: 0 | W29: 0 | X29: 0 | Y29: 0 | Z29: 0 | AA29: 0 | AB29: 0 | AC29: 17.98 | AD29: 117.91 | AE29: 0 | AF29: 0 | AG29: 0 | AH29: 17.3 | AI29: 0 | AJ29: 0.35 | AK29: 17.65 | AL29: 227.73 | AM29: Yes | AN29: 10.624 | AO29: Yes | AP29: No | AR29: 100833489 | AS29: No | AW29: Yes | AX29: No
A30: 216801985440355 | C30: 2025-09-14 12:16:25 | D30: delivered | E30: regular | H30: FLAVORFUL | I30: 850 | J30: 30 | K30: 100 | L30: 0 | M30: 100 | N30: 780 | O30: 39 | P30: 819 | Q30: 819 | R30: 20.0% | S30: 163.8 | T30: 0 | U30: 0 | V30: 0 | W30: 0 | X30: 0 | Y30: 0 | Z30: 0 | AA30: 0 | AB30: 0 | AC30: 29.48 | AD30: 193.28 | AE30: 0 | AF30: 0 | AG30: 0 | AH30: 39 | AI30: 0 | AJ30: 0.78 | AK30: 39.78 | AL30: 585.94 | AM30: No | AN30: 4.681 | AO30: Yes | AP30: No | AR30: 206500dc-ba9e-4a58-be62-bb3f830ec1f3,206500dc-ba9e-4a58-be62-bb3f830ec1f3 | AS30: No | AW30: Yes | AX30: No
A31: 216802012066041 | C31: 2025-09-14 12:16:52 | D31: delivered | E31: regular | H31: TRYNEW | I31: 375 | J31: 15 | K31: 64 | L31: 0 | M31: 64 | N31: 326 | O31: 16.3 | P31: 342.3 | Q31: 342.3 | R31: 22.0% | S31: 75.31 | T31: 0 | U31: 0 | V31: 0 | W31: 0 | X31: 0 | Y31: 0 | Z31: 0 | AA31: 0 | AB31: 0 | AC31: 13.56 | AD31: 88.87 | AE31: 0 | AF31: 0 | AG31: 0 | AH31: 16.3 | AI31: 0 | AJ31: 0.33 | AK31: 16.63 | AL31: 236.81 | AM31: No | AN31: 4.327 | AO31: Yes | AP31: No | AR31: 206500dc-ba9e-4a58-be62-bb3f830ec1f3,206500dc-ba9e-4a58-be62-bb3f830ec1f3 | AS31: No | AW31: Yes | AX31: No
A32: 216802040549801 | C32: 2025-09-14 12:17:20 | D32: delivered | E32: regular | H32: SWIGGYLOVE-YSOAHO | I32: 445 | J32: 15 | K32: 64 | L32: 0 | M32: 64 | N32: 396 | O32: 19.8 | P32: 415.8 | Q32: 415.8 | R32: 22.0% | S32: 91.48 | T32: 7 | U32: 0 | V32: 0 | W32: 0 | X32: 0 | Y32: 0 | Z32: 0 | AA32: 0 | AB32: 0 | AC32: 17.72 | AD32: 116.2 | AE32: 0 | AF32: 0 | AG32: 0 | AH32: 19.8 | AI32: 0 | AJ32: 0.4 | AK32: 20.2 | AL32: 279.39 | AM32: Yes | AN32: 6.409 | AO32: Yes | AP32: No | AQ32: TRYNEW | AR32: 206500dc-ba9e-4a58-be62-bb3f830ec1f3,206500dc-ba9e-4a58-be62-bb3f830ec1f3 | AS32: No | AW32: Yes | AX32: No
A33: 216802189217422 | C33: 2025-09-14 12:19:49 | D33: delivered | E33: regular | H33: PARTY | I33: 1245 | J33: 52 | K33: 124.49 | L33: 0 | M33: 124.49 | N33: 1172.51 | O33: 58.62 | P33: 1231.13 | Q33: 1231.13 | R33: 16.0% | S33: 196.98 | T33: 0 | U33: 0 | V33: 0 | W33: 0 | X33: 0 | Y33: 0 | Z33: 0 | AA33: 0 | AB33: 0 | AC33: 35.46 | AD33: 232.44 | AE33: 0 | AF33: 0 | AG33: 0 | AH33: 58.63 | AI33: 0 | AJ33: 1.17 | AK33: 59.8 | AL33: 938.91 | AM33: No | AN33: 4.749 | AO33: Yes | AP33: No | AR33: 206500dc-ba9e-4a58-be62-bb3f830ec1f3,206500dc-ba9e-4a58-be62-bb3f830ec1f3 | AS33: No | AW33: Yes | AX33: No
A34: 216802234453938 | C34: 2025-09-14 12:20:34 | D34: delivered | E34: regular | H34: FLAVORFUL | I34: 1295 | J34: 52 | K34: 99.98 | L34: 0 | M34: 99.98 | N34: 1247.02 | O34: 62.36 | P34: 1309.376 | Q34: 1309.38 | R34: 16.0% | S34: 209.5 | T34: 0 | U34: 0 | V34: 0 | W34: 0 | X34: 0 | Y34: 0 | Z34: 0 | AA34: 0 | AB34: 0 | AC34: 37.72 | AD34: 247.22 | AE34: 0 | AF34: 443 | AG34: 443 | AH34: 62.35 | AI34: 0 | AJ34: 1.25 | AK34: 63.6 | AL34: 555.57 | AM34: No | AN34: 4.751 | AO34: Yes | AP34: No | AR34: 206500dc-ba9e-4a58-be62-bb3f830ec1f3,206500dc-ba9e-4a58-be62-bb3f830ec1f3 | AS34: No | AW34: Yes | AX34: No
A35: 216802250382080 | C35: 2025-09-14 12:20:50 | D35: delivered | E35: regular | H35: SWIGGYIT | I35: 475 | J35: 15 | K35: 64 | L35: 0 | M35: 64 | N35: 426 | O35: 21.3 | P35: 447.3 | Q35: 447.3 | R35: 22.0% | S35: 98.41 | T35: 0 | U35: 0 | V35: 0 | W35: 0 | X35: 0 | Y35: 0 | Z35: 0 | AA35: 0 | AB35: 0 | AC35: 17.72 | AD35: 116.13 | AE35: 0 | AF35: 0 | AG35: 0 | AH35: 21.3 | AI35: 0 | AJ35: 0.43 | AK35: 21.73 | AL35: 309.46 | AM35: No | AN35: 3.099 | AO35: Yes | AP35: No | AR35: 206500dc-ba9e-4a58-be62-bb3f830ec1f3,206500dc-ba9e-4a58-be62-bb3f830ec1f3 | AS35: No | AW35: Yes | AX35: No
A36: 216802275782424 | C36: 2025-09-14 12:21:15 | D36: delivered | E36: regular | H36: PARTY | I36: 1475 | J36: 68 | K36: 147.5 | L36: 0 | M36: 147.5 | N36: 1395.5 | O36: 69.78 | P36: 1465.28 | Q36: 1465.28 | R36: 14.0% | S36: 205.14 | T36: 0 | U36: 0 | V36: 0 | W36: 0 | X36: 0 | Y36: 0 | Z36: 0 | AA36: 0 | AB36: 0 | AC36: 36.92 | AD36: 242.06 | AE36: 0 | AF36: 0 | AG36: 0 | AH36: 69.78 | AI36: 0 | AJ36: 1.4 | AK36: 71.18 | AL36: 1152.03 | AM36: No | AN36: 4.448 | AO36: Yes | AP36: No | AR36: 206500dc-ba9e-4a58-be62-bb3f830ec1f3,206500dc-ba9e-4a58-be62-bb3f830ec1f3 | AS36: No | AW36: Yes | AX36: No
A37: 216802356995912 | C37: 2025-09-14 12:22:36 | D37: delivered | E37: regular | H37: SWIGGYIT | I37: 595 | J37: 20 | K37: 64 | L37: 0 | M37: 64 | N37: 551 | O37: 27.56 | P37: 578.56 | Q37: 578.56 | R37: 20.0% | S37: 115.71 | T37: 0 | U37: 0 | V37: 0 | W37: 0 | X37: 0 | Y37: 0 | Z37: 0 | AA37: 0 | AB37: 0 | AC37: 20.82 | AD37: 136.53 | AE37: 0 | AF37: 0 | AG37: 0 | AH37: 27.55 | AI37: 0 | AJ37: 0.55 | AK37: 28.1 | AL37: 413.9 | AM37: No | AN37: 2.165 | AO37: Yes | AP37: No | AR37: 206500dc-ba9e-4a58-be62-bb3f830ec1f3,206500dc-ba9e-4a58-be62-bb3f830ec1f3 | AS37: No | AW37: Yes | AX37: No
A38: 216802393448294 | C38: 2025-09-14 12:23:13 | D38: delivered | E38: regular | H38: FLAVORFUL | I38: 1095 | J38: 40 | K38: 99.98 | L38: 0 | M38: 99.98 | N38: 1035.02 | O38: 51.76 | P38: 1086.776 | Q38: 1086.78 | R38: 16.0% | S38: 173.88 | T38: 0 | U38: 0 | V38: 0 | W38: 0 | X38: 0 | Y38: 0 | Z38: 0 | AA38: 0 | AB38: 0 | AC38: 31.3 | AD38: 205.18 | AE38: 0 | AF38: 0 | AG38: 0 | AH38: 51.75 | AI38: 0 | AJ38: 1.04 | AK38: 52.79 | AL38: 828.81 | AM38: No | AN38: 4.327 | AO38: Yes | AP38: No | AR38: 206500dc-ba9e-4a58-be62-bb3f830ec1f3,206500dc-ba9e-4a58-be62-bb3f830ec1f3 | AS38: No | AW38: Yes | AX38: No
A39: 216802521278721 | C39: 2025-09-14 12:25:21 | D39: delivered | E39: regular | H39: TOPUPOFFER | I39: 525 | J39: 20 | K39: 64 | L39: 0 | M39: 64 | N39: 481 | O39: 24.06 | P39: 505.06 | Q39: 505.06 | R39: 20.0% | S39: 101.01 | T39: 7 | U39: 0 | V39: 0 | W39: 0 | X39: 0 | Y39: 0 | Z39: 0 | AA39: 0 | AB39: 0 | AC39: 19.44 | AD39: 127.45 | AE39: 0 | AF39: 0 | AG39: 0 | AH39: 24.05 | AI39: 0 | AJ39: 0.48 | AK39: 24.53 | AL39: 353.07 | AM39: Yes | AN39: 6.258 | AO39: Yes | AP39: No | AQ39: SWIGGYIT | AR39: 206500dc-ba9e-4a58-be62-bb3f830ec1f3,206500dc-ba9e-4a58-be62-bb3f830ec1f3 | AS39: No | AW39: Yes | AX39: No
A40: 216802584185426 | C40: 2025-09-14 12:26:24 | D40: delivered | E40: regular | H40: TRYNEW | I40: 375 | J40: 15 | K40: 64 | L40: 0 | M40: 64 | N40: 326 | O40: 16.3 | P40: 342.3 | Q40: 342.3 | R40: 22.0% | S40: 75.31 | T40: 12 | U40: 0 | V40: 0 | W40: 0 | X40: 0 | Y40: 0 | Z40: 0 | AA40: 0 | AB40: 0 | AC40: 15.72 | AD40: 103.03 | AE40: 0 | AF40: 0 | AG40: 0 | AH40: 16.3 | AI40: 0 | AJ40: 0.33 | AK40: 16.63 | AL40: 222.65 | AM40: Yes | AN40: 9.275 | AO40: Yes | AP40: No | AR40: 100833489 | AS40: No | AW40: Yes | AX40: No
A41: 216802672667656 | C41: 2025-09-14 12:27:52 | D41: delivered | E41: regular | H41: FLAVORFUL | I41: 1120 | J41: 40 | K41: 99.99 | L41: 0 | M41: 99.99 | N41: 1060.01 | O41: 53 | P41: 1113.008 | Q41: 1113.01 | R41: 16.0% | S41: 178.08 | T41: 0 | U41: 0 | V41: 0 | W41: 0 | X41: 0 | Y41: 0 | Z41: 0 | AA41: 0 | AB41: 0 | AC41: 32.06 | AD41: 210.14 | AE41: 0 | AF41: 0 | AG41: 0 | AH41: 53 | AI41: 0 | AJ41: 1.06 | AK41: 54.06 | AL41: 848.82 | AM41: No | AN41: 5.049 | AO41: Yes | AP41: No | AR41: 206500dc-ba9e-4a58-be62-bb3f830ec1f3,206500dc-ba9e-4a58-be62-bb3f830ec1f3 | AS41: No | AW41: Yes | AX41: No
A42: 216802679214116 | C42: 2025-09-14 12:27:59 | D42: delivered | E42: regular | I42: 1020 | J42: 35 | K42: 0 | L42: 0 | M42: 0 | N42: 1055 | O42: 52.76 | P42: 1107.76 | Q42: 1107.76 | R42: 16.0% | S42: 177.24 | T42: 0 | U42: 0 | V42: 0 | W42: 0 | X42: 0 | Y42: 0 | Z42: 0 | AA42: 0 | AB42: 0 | AC42: 31.9 | AD42: 209.14 | AE42: 0 | AF42: 0 | AG42: 0 | AH42: 52.75 | AI42: 0 | AJ42: 1.05 | AK42: 53.8 | AL42: 844.8 | AM42: No | AN42: 3.427 | AO42: Yes | AP42: No | AR42: 206500dc-ba9e-4a58-be62-bb3f830ec1f3 | AS42: No | AW42: Yes | AX42: No
A43: 216802743613342 | C43: 2025-09-14 12:29:03 | D43: delivered | E43: regular | H43: TRYNEW | I43: 475 | J43: 15 | K43: 64 | L43: 0 | M43: 64 | N43: 426 | O43: 21.3 | P43: 447.3 | Q43: 447.3 | R43: 22.0% | S43: 98.41 | T43: 0 | U43: 0 | V43: 0 | W43: 0 | X43: 0 | Y43: 0 | Z43: 0 | AA43: 0 | AB43: 0 | AC43: 17.72 | AD43: 116.13 | AE43: 0 | AF43: 0 | AG43: 0 | AH43: 21.3 | AI43: 0 | AJ43: 0.43 | AK43: 21.73 | AL43: 309.46 | AM43: No | AN43: 3.701 | AO43: Yes | AP43: No | AR43: 206500dc-ba9e-4a58-be62-bb3f830ec1f3,206500dc-ba9e-4a58-be62-bb3f830ec1f3 | AS43: No | AW43: Yes | AX43: No
A44: 216802756600181 | C44: 2025-09-14 12:29:16 | D44: delivered | E44: regular | I44: 375 | J44: 15 | K44: 0 | L44: 0 | M44: 0 | N44: 390 | O44: 19.5 | P44: 409.5 | Q44: 409.5 | R44: 22.0% | S44: 90.09 | T44: 0 | U44: 0 | V44: 0 | W44: 0 | X44: 0 | Y44: 0 | Z44: 0 | AA44: 0 | AB44: 0 | AC44: 16.22 | AD44: 106.31 | AE44: 0 | AF44: 0 | AG44: 0 | AH44: 19.5 | AI44: 0 | AJ44: 0.39 | AK44: 19.89 | AL44: 283.3 | AM44: No | AN44: 3.989 | AO44: Yes | AP44: No | AS44: No | AW44: No | AX44: No
A45: 216802826143699 | C45: 2025-09-14 12:30:26 | D45: delivered | E45: regular | H45: TRYNEW | I45: 445 | J45: 15 | K45: 64 | L45: 0 | M45: 64 | N45: 396 | O45: 19.8 | P45: 415.8 | Q45: 415.8 | R45: 22.0% | S45: 91.48 | T45: 0 | U45: 0 | V45: 0 | W45: 0 | X45: 0 | Y45: 0 | Z45: 0 | AA45: 0 | AB45: 0 | AC45: 16.46 | AD45: 107.94 | AE45: 0 | AF45: 0 | AG45: 0 | AH45: 19.8 | AI45: 0 | AJ45: 0.4 | AK45: 20.2 | AL45: 287.65 | AM45: No | AN45: 2.751 | AO45: Yes | AP45: No | AR45: 206500dc-ba9e-4a58-be62-bb3f830ec1f3,206500dc-ba9e-4a58-be62-bb3f830ec1f3 | AS45: No | AW45: Yes | AX45: No
A46: 216802832950040 | C46: 2025-09-14 12:30:32 | D46: delivered | E46: regular | I46: 295 | J46: 10 | K46: 0 | L46: 0 | M46: 0 | N46: 305 | O46: 15.26 | P46: 320.26 | Q46: 320.24 | R46: 22.0% | S46: 70.45 | T46: 0 | U46: 0 | V46: 0 | W46: 0 | X46: 0 | Y46: 0 | Z46: 0 | AA46: 0 | AB46: 0 | AC46: 12.68 | AD46: 83.13 | AE46: 0 | AF46: 0 | AG46: 0 | AH46: 15.25 | AI46: 0 | AJ46: 0.3 | AK46: 15.55 | AL46: 221.56 | AM46: No | AN46: 2.27 | AO46: Yes | AP46: No | AR46: 206500dc-ba9e-4a58-be62-bb3f830ec1f3 | AS46: No | AW46: Yes | AX46: No
A47: 216802853707997 | C47: 2025-09-14 12:30:53 | D47: delivered | E47: regular | H47: FLAVORFUL | I47: 720 | J47: 25 | K47: 99.99 | L47: 0 | M47: 99.99 | N47: 645.01 | O47: 32.26 | P47: 677.268 | Q47: 677.27 | R47: 20.0% | S47: 135.45 | T47: 0 | U47: 0 | V47: 0 | W47: 0 | X47: 0 | Y47: 0 | Z47: 0 | AA47: 0 | AB47: 0 | AC47: 24.38 | AD47: 159.83 | AE47: 0 | AF47: 0 | AG47: 0 | AH47: 32.25 | AI47: 0 | AJ47: 0.65 | AK47: 32.9 | AL47: 484.53 | AM47: No | AN47: 3.557 | AO47: Yes | AP47: No | AR47: 206500dc-ba9e-4a58-be62-bb3f830ec1f3,206500dc-ba9e-4a58-be62-bb3f830ec1f3 | AS47: No | AW47: Yes | AX47: No
A48: 216802865544387 | C48: 2025-09-14 12:31:05 | D48: delivered | E48: regular | H48: SWIGGYIT | I48: 295 | J48: 15 | K48: 64 | L48: 0 | M48: 64 | N48: 246 | O48: 12.3 | P48: 258.3 | Q48: 258.3 | R48: 22.0% | S48: 56.83 | T48: 0 | U48: 0 | V48: 0 | W48: 0 | X48: 0 | Y48: 0 | Z48: 0 | AA48: 0 | AB48: 0 | AC48: 10.22 | AD48: 67.05 | AE48: 0 | AF48: 0 | AG48: 0 | AH48: 12.3 | AI48: 0 | AJ48: 0.25 | AK48: 12.55 | AL48: 178.68 | AM48: No | AN48: 2.768 | AO48: Yes | AP48: No | AR48: f5c2722b-1b7c-4fbc-aeb4-0a3dcb43f369,206500dc-ba9e-4a58-be62-bb3f830ec1f3,f5c2722b-1b7c-4fbc-aeb4-0a3dcb43f369,206500dc-ba9e-4a58-be62-bb3f830ec1f3 | AS48: No | AW48: Yes | AX48: No
A49: 216802866546636 | C49: 2025-09-14 12:31:06 | D49: delivered | E49: regular | H49: MISSEDYOU | I49: 445 | J49: 15 | K49: 64 | L49: 0 | M49: 64 | N49: 396 | O49: 19.8 | P49: 415.8 | Q49: 415.8 | R49: 22.0% | S49: 91.48 | T49: 0 | U49: 0 | V49: 0 | W49: 0 | X49: 0 | Y49: 0 | Z49: 0 | AA49: 0 | AB49: 0 | AC49: 16.46 | AD49: 107.94 | AE49: 0 | AF49: 0 | AG49: 0 | AH49: 19.8 | AI49: 0 | AJ49: 0.4 | AK49: 20.2 | AL49: 287.65 | AM49: No | AN49: 4.427 | AO49: Yes | AP49: No | AR49: 206500dc-ba9e-4a58-be62-bb3f830ec1f3,206500dc-ba9e-4a58-be62-bb3f830ec1f3 | AS49: No | AW49: Yes | AX49: No
A50: 216802967904358 | C50: 2025-09-14 12:32:47 | D50: delivered | E50: regular | H50: TRYNEW | I50: 295 | J50: 15 | K50: 64 | L50: 0 | M50: 64 | N50: 246 | O50: 12.3 | P50: 258.3 | Q50: 258.3 | R50: 22.0% | S50: 56.83 | T50: 0 | U50: 0 | V50: 0 | W50: 0 | X50: 0 | Y50: 0 | Z50: 0 | AA50: 0 | AB50: 0 | AC50: 10.22 | AD50: 67.05 | AE50: 0 | AF50: 0 | AG50: 0 | AH50: 12.3 | AI50: 0 | AJ50: 0.25 | AK50: 12.55 | AL50: 178.68 | AM50: No | AN50: 4.249 | AO50: Yes | AP50: No | AR50: 206500dc-ba9e-4a58-be62-bb3f830ec1f3,206500dc-ba9e-4a58-be62-bb3f830ec1f3 | AS50: No | AW50: Yes | AX50: No
A51: 216803071186483 | C51: 2025-09-14 12:34:31 | D51: delivered | E51: regular | H51: FLAVORFUL | I51: 850 | J51: 30 | K51: 99.99 | L51: 0 | M51: 99.99 | N51: 780.01 | O51: 39 | P51: 819.008 | Q51: 819.01 | R51: 20.0% | S51: 163.8 | T51: 20 | U51: 0 | V51: 0 | W51: 0 | X51: 0 | Y51: 0 | Z51: 0 | AA51: 0 | AB51: 0 | AC51: 33.08 | AD51: 216.88 | AE51: 0 | AF51: 0 | AG51: 0 | AH51: 39 | AI51: 0 | AJ51: 0.78 | AK51: 39.78 | AL51: 562.34 | AM51: Yes | AN51: 10.584 | AO51: Yes | AP51: No | AR51: 103197863 | AS51: No | AW51: Yes | AX51: No
A52: 216803174008859 | C52: 2025-09-14 12:36:14 | D52: delivered | E52: regular | H52: FLAVORFUL | I52: 1090 | J52: 35 | K52: 99.99 | L52: 0 | M52: 99.99 | N52: 1025.01 | O52: 51.26 | P52: 1076.268 | Q52: 1076.27 | R52: 16.0% | S52: 172.2 | T52: 0 | U52: 0 | V52: 0 | W52: 0 | X52: 0 | Y52: 0 | Z52: 0 | AA52: 0 | AB52: 0 | AC52: 31 | AD52: 203.2 | AE52: 0 | AF52: 0 | AG52: 0 | AH52: 51.25 | AI52: 0 | AJ52: 1.03 | AK52: 52.28 | AL52: 820.79 | AM52: No | AN52: 3.666 | AO52: Yes | AP52: No | AR52: 206500dc-ba9e-4a58-be62-bb3f830ec1f3,206500dc-ba9e-4a58-be62-bb3f830ec1f3 | AS52: No | AW52: Yes | AX52: No
A53: 216803377419844 | C53: 2025-09-14 12:39:37 | D53: delivered | E53: regular | I53: 670 | J53: 25 | K53: 0 | L53: 0 | M53: 0 | N53: 695 | O53: 34.76 | P53: 729.76 | Q53: 729.76 | R53: 20.0% | S53: 145.95 | T53: 12 | U53: 0 | V53: 0 | W53: 0 | X53: 0 | Y53: 0 | Z53: 0 | AA53: 0 | AB53: 0 | AC53: 28.44 | AD53: 186.39 | AE53: 0 | AF53: 0 | AG53: 0 | AH53: 34.75 | AI53: 0 | AJ53: 0.7 | AK53: 35.45 | AL53: 507.93 | AM53: Yes | AN53: 9.83 | AO53: Yes | AP53: No | AS53: No | AW53: Yes | AX53: No
